Workbook
Name AgentPattern: _Lists!$D$2:$D$8
Name AgentStatus: _Lists!$A$2:$A$9
Name Autonomy: _Lists!$B$2:$B$7
Name ChargingBasis: _Lists!$K$2:$K$10
Name Complexity: _Lists!$F$2:$F$5
Name Confidence: _Lists!$N$2:$N$8
Name CostClass: _Lists!$J$2:$J$10
Name Currency: _Lists!$P$2:$P$9
Name Environment: _Lists!$Q$2:$Q$9
Name EvidenceType: _Lists!$O$2:$O$8
Name Frequency: _Lists!$L$2:$L$7
Name Hosting: _Lists!$R$2:$R$6
Name Inclusion: _Lists!$M$2:$M$7
Name InputSource: _Lists!$I$2:$I$8
Name ModelClass: _Lists!$S$2:$S$8
Name Owner: _Lists!$T$2:$T$7
Name Scenario: _Lists!$H$2:$H$7
Name SolutionType: _Lists!$C$2:$C$4
Name Technology: _Lists!$E$2:$E$6
Name ValidationStatus: _Lists!$U$2:$U$7
Name YesNo: _Lists!$G$2:$G$4

Sheet Instructions
A1: AMS RFP | AI Agent Cost Estimator | Bidder Instructions
A2: Purpose: capture a consistent, auditable and comparable partner submission linking every AI-enabled AMS capability to demand, consumption, cost, benefit and supporting evidence, while retaining the existing normalized monthly cost model.
A4: 1. NON-NEGOTIABLE SUBMISSION RULES
A5: 1 | B5: Use one unique Agent ID across AI_Agent_Inventory, Demand_Scenarios, AI_Consumption, Cost_Register and Benefits.
A6: 2 | B6: Enter data only in blue-font/yellow-fill cells. Do not overwrite formulas, linked cells, summaries, charts or controlled lists.
A7: 3 | B7: Provide all five scenarios: Minimum adoption, Expected case, High adoption, Peak/stress case and PepsiCo standard.
A8: 4 | B8: Use one reporting currency and disclose source, region, SKU/version, effective date, discount, markup, term, escalation and pricing validity.
A9: 5 | B9: Enter every cost once. Avoid duplication across Unit_Costs, Cost_Register, Infra_Sizing, Staffing, licenses, platform services and pass-through charges.
A10: 6 | B10: Explain required blanks, zero values, exclusions, dependencies, minimum commitments, optional items and PepsiCo-funded components.
A11: 7 | B11: Reference supporting document or artifact names, file links, pricing sources or attachment IDs in each Evidence Reference / Pricing Source field, and select the appropriate Input Source.
A12: 8 | B12: Retain all remaining worksheets, formulas, validations and sheet names. The hidden _Lists sheet must not be modified.
A14: 2. REQUIRED COMPLETION SEQUENCE
A15: Step | B15: Sheet | C15: Primary owner | D15: Type | E15: What the bidder must enter or review | F15: Completion test | G15: Key control | H15: Partner Action
A16: 1 | B16: AI_Agent_Inventory | C16: AI / solution lead | D16: Sheet within this document | E16: Enter one row per AI-enabled capability: identity, scope, status, autonomy, pattern, technology, complexity, instances, controls, ownership, hosting and evidence. | F16: Every proposed capability has one unique Agent ID. | G16: Reuse the Agent ID in every connected sheet. | H16: Input
A17: 2 | B17: Demand_Scenarios | C17: Service / process owner | D17: Sheet within this document | E17: Enter one row per Agent ID and scenario: trigger unit, eligible volume, adoption, executions, retries, outcomes, peak, concurrency, runtime, growth and rollout. | F17: All five scenarios exist for every priced capability. | G17: Enter percentages as rates, for example 25%, not 25. | H17: Input
A18: 3 | B18: AI_Consumption | C18: AI architect / FinOps | D18: Sheet within this document | E18: Enter one row per Agent ID, scenario and model/service: routing, calls, tokens, caching, retries, AI services, prices and commercial terms. | F18: Consumption and prices are traceable to design or evidence. | G18: Do not duplicate system prompt, retrieval/tool or retry consumption. | H18: Input
A19: 4 | B19: Assumptions | C19: Estimator | D19: Sheet within this document | E19: Complete normalized monthly timeline, rollout, adoption, workload, LLM behavior, token sizing and token prices. | F19: Inputs align with the proposed rollout and monthly model. | G19: Explain differences from Demand_Scenarios. | H19: Input
A20: 5 | B20: Unit_Costs | C20: Platform / FinOps | D20: Sheet within this document | E20: Enter normalized platform, data, observability and licensing rates in the units shown; complete Notes / Source. | F20: Rates use a consistent currency, region, SKU and pricing basis. | G20: Do not duplicate rates or costs in Cost_Register. | H20: Input
A21: 6 | B21: Cost_Register | C21: Commercial / FinOps | D21: Sheet within this document | E21: Enter each cost component once with one mandatory classification, charging basis, quantity, rate, frequency, inclusion, Years 1–5 quantities, source and evidence. | F21: Net rate and Years 1–5 costs reconcile to the offer. | G21: Do not overwrite formula columns; document shared-cost allocation. | H21: Input + formulas
A22: 7 | B22: Infra_Sizing | C22: Cloud architect | D22: Sheet within this document | E22: Enter baseline capacity, fixed/shared services and networking/security overhead for the monthly model. | F22: Capacity and environments match the architecture. | G22: Avoid costs already embedded in blended rates or Cost_Register. | H22: Input
A23: 8 | B23: Staffing | C23: Service delivery lead | D23: Sheet within this document | E23: Enter incremental operator FTEs, loaded cost and pod allocation, or document exclusion/inclusion in AMS. | F23: Pod allocation equals total FTEs and matches the service model. | G23: Do not duplicate labor included in another cost line. | H23: Input if applicable
A24: 9 | B24: Benefits | C24: Value lead | D24: Sheet within this document | E24: Enter measurable outcomes, baseline, target, formula, financial value, confidence, commitment, validation, dependencies and attribution control. | F24: Benefits are measurable and evidence-referenced. | G24: Prevent overlap across agents, towers and labor productivity. | H24: Input
A25: Supporting evidence | B25: Architecture / Risk / Commercial | C25: External RFP attachments / bidder repository | D25: Provide supporting architecture, pricing, delivery, control, operations and boundary artifacts outside this workbook; reference the exact document name, attachment ID or accessible link in each relevant Evidence Reference field. | E25: Every material Evidence Reference or Pricing Source points to a supplied artifact or authoritative source. | F25: Identify access restrictions, open gaps and resolution dates in Notes / Exclusions or the bidder response. | G25: Input / reference | H25: Input
A26: 11 | B26: LLM_Calc / Observability | C26: Estimator / reviewers | D26: Sheet within this document | E26: Review selected-month token, AI-service, logging and dashboard outputs. | F26: Outputs move logically with demand and unit rates. | G26: Do not type over formulas. | H26: Review only
A27: 12 | B27: Model_Monthly / Summary / Charts | C27: Estimator / reviewers | D27: Sheet within this document | E27: Review the normalized monthly platform, run-cost, staffing and executive outputs. | F27: Monthly outputs reconcile to Assumptions, Unit_Costs, Infra_Sizing and Staffing. | G27: This remains the normalized monthly view. | H27: Review only
A28: 13 | B28: Five_Year_TCO | C28: Commercial lead + reviewers | D28: Sheet within this document | E28: Review Years 1–5 cost by scenario/classification, benefit, net benefit, unit economics and variance to PepsiCo standard. | F28: Totals reconcile to Cost_Register, Benefits and the bid. | G28: Resolve material zero values and variances before submission. | H28: Review only
A29: 14 | B29: Final certification | C29: Authorized representative | D29: Recommendation for bidders | E29: Confirm formula visibility, completeness, availability status, exclusions, dependencies, ownership, portability, exit treatment and validity. | F29: Submission is complete and ready for normalization. | G29: Retain workbook structure and calculation lineage. | H29: Certification
A32: 3. INPUT AND CALCULATION CONVENTIONS
A33: Blue font / yellow fill | B33: Bidder-editable input requiring completion or a documented non-applicability statement.
A34: Green fill / black font | B34: Formula-driven or linked cell. Do not overwrite.
A35: Asterisk (*) | B35: Mandatory field for a completed row.
A36: Shared costs | B36: Use Agent ID / Shared = Shared and explain the allocation method.
A37: Headless agents | B37: Use the documented trigger or invocation unit. Do not automatically equate trigger, execution, run and LLM call.
A38: Demand formula | B38: Annual executions = eligible monthly volume × eligible % × adoption % × executions per eligible unit × 12, with documented adjustments only.
A39: Net unit rate | B39: Gross unit rate × (1 − discount %) × (1 + partner markup %).
A40: Five-year cost | B40: Each year cost = that year quantity × net unit rate; Five-Year Cost = sum of Years 1–5.
A41: Benefits | B41: State baseline, target, formula, validation source, confidence, commitment, dependencies and overlap control.
A42: Unit economics | B42: Use the same scenario population and period in the cost numerator and volume/outcome denominator.
A44: 4. FINAL RECONCILIATION CHECKLIST
A45: ☑ | B45: Agent IDs reconcile across AI_Agent_Inventory, Demand_Scenarios, AI_Consumption, Cost_Register and Benefits.
A46: ☑ | B46: All five scenarios are complete and the PepsiCo standard assumptions are not altered.
A47: ☑ | B47: Cost_Register totals reconcile to Five_Year_TCO and the commercial proposal.
A48: ☑ | B48: Benefits reconcile to Five_Year_TCO and include explicit overlap and attribution controls.
A49: ☑ | B49: Unit_Costs, Infra_Sizing, Staffing and Cost_Register do not duplicate the same cost.
A50: ☑ | B50: Model_Monthly, Summary and Charts remain consistent with the normalized monthly model.
A51: ☑ | B51: Mandatory components, licenses, minimum commitments, markups, exclusions, dependencies and exit charges are fully disclosed.
A52: ☑ | B52: Prototype and roadmap items are clearly classified and are not presented as production-available.

Sheet AI_Agent_Inventory
A1: AMS RFP | AI Agent Inventory
A2: BIDDER INPUT: One row per proposed AI-enabled capability. Use the same unique Agent ID in all technical, cost, benefit and evidence sheets.
A4: Agent ID* | B4: Agent Name* | C4: Description* | D4: AMS Tower* | E4: Application Scope* | F4: Business Process | G4: Use-case Category | H4: Supported Languages | I4: Capability Status* | J4: Autonomy* | K4: User/Headless* | L4: Agent Pattern* | M4: Technology* | N4: Complexity* | O4: Logical Agents | P4: Deployed Instances | Q4: Markets / BUs | R4: Environments | S4: Systems Updated | T4: Human Approval Gate | U4: Kill Switch | V4: Rollback / Override | W4: Code Owner | X4: Prompt / Workflow Owner | Y4: Data / Logs Owner | Z4: Hosting Model | AA4: Evidence Reference | AB4: Assumption Source* | AC4: Notes | AD4: Subagents
A5: AIA-001 | B5: Incident Triage Copilot | C5: Classifies, enriches and routes incidents using service context and knowledge. | D5: Service Desk | E5: Enterprise applications | F5: Incident management | G5: Triage and routing | H5: English, French, Spanish | I5: Configurable existing capability | J5: Recommendation-based | K5: User-facing | L5: Domain agent | M5: Agentic AI | N5: Medium | O5: 1 | P5: 3 | Q5: UK, EMEA, India | R5: Development, Test, Production | S5: ServiceNow | T5: Yes | U5: Yes | V5: Assignment group override | W5: Partner | X5: Joint | Y5: PepsiCo | Z5: Hybrid | AA5: Architecture Pack AP-01; Control Matrix CM-01 | AB5: Partner-estimated | AC5: Human approval required for priority and resolver changes. | AD5: 15 proposed-agent entries: Triage Agent [POC Completed]; Categorization of Incident [In Prod]; Incident-copilot Agent [POC Completed]; Isummarizer BOT [Pilot]; Intake Agent [POC Completed]; Ticket Hygiene Agent [POC Completed]; Incident-copilot Agent WM [POC Completed]; Triage Agent WM [POC Completed]; MIM Agent [Pilot]; Agent Sherlock (L3 Triage Agent) [Pilot]; Communication Agent [POC Completed]; Ticket Creation Automation Agent [In Prod]; Email Processing Agent [In Prod]; Outlook Inbox Automation Agent [POC Completed]; Intelligent Incident Agent [Pilot]
A6: AIA-002 | B6: Safe Auto-Remediation Agent | C6: Executes approved runbooks for repeatable infrastructure and application faults. | D6: Cloud & Infrastructure | E6: Azure and hosted applications | F6: Incident resolution | G6: Self-healing | H6: English | I6: Reusable accelerator | J6: Bounded autonomous execution | K6: Headless | L6: Orchestration agent | M6: Blended | N6: Complex | O6: 3 | P6: 6 | Q6: UK, EMEA, India | R6: Development, Test, Production, DR | S6: Azure, ServiceNow | T6: Yes | U6: Yes | V6: Runbook rollback and manual stop | W6: Partner | X6: Partner | Y6: PepsiCo | Z6: PepsiCo-hosted | AA6: Architecture Pack AP-02; Runbook Catalogue RC-01 | AB6: Partner-estimated | AC6: Only allow-listed actions; privileged access via managed identity. | AD6: 27 proposed-agent entries: Data Management Agent [POC Completed]; Nexthink Automation Agent [In Prod]; Intelligent Ticket Resolution [POC Completed]; PR Deletion – Old Purchase Requisition Deletions [In Prod]; Auto log Analyzer and Resolution Agent [In Prod]; Moveit Service - Start and Stop Services [In Prod]; Cross Reference Manager Agent [POC Completed]; Ticket Update Automation Agent [In Prod]; Sales order completed still demand showing in MD04 [In Prod]; PFNA Data Sync issue fixer & Reconciliation Agent [To be custom built for PepsiCo]; DataQualitySentinel [To be custom built for PepsiCo]; PFNA Alerts Remediation Agent [To be custom built for PepsiCo]; PACE- Invoice Reconciler and Reprocesseser [To be custom built for PepsiCo]; GTMS_EXCEPTION_LOG_SYNC_AGENT [To be custom built for PepsiCo]; WMS- Stock Integrity Agent [To be custom built for PepsiCo]; PACE- DataQualitySentinel [To be custom built for PepsiCo]; PACE- Stock Integrity Agent [To be custom built for PepsiCo]; PEPSICOSELL_MASTER_CONFIG_AGENT [To be custom built for PepsiCo]; PEPSICOSELL_DATASYNC_AGENT [To be custom built for PepsiCo]; DELIVERSMARTR_DATASYNC_AGENT [To be custom built for PepsiCo]; PACE- RA-VAN Integrity Agent [To be custom built for PepsiCo]; PACE- Visit Exception Resolution Agent [To be custom built for PepsiCo]; PEPSICONNECT_DATASYNC_RECONCILIATION_AGENT [To be custom built for PepsiCo]; PEPSICONNECT_REWARD_ID_VERIFICATION_AGENT [To be custom built for PepsiCo]; PEPSICONNECT_DATA_SYNC_RECONCILIATION_AGENT [To be custom built for PepsiCo]; AMESA- Skelta WF Task Transfer [To be custom built for PepsiCo]; PBNA_STAR2_DATAFIX_AGENT [To be custom built for PepsiCo]
A7: AIA-003 | B7: Knowledge Resolution Copilot | C7: Retrieves governed knowledge and drafts resolution guidance with citations. | D7: Service Desk | E7: Enterprise applications | F7: Knowledge management | G7: Knowledge search and answer | H7: English, French, Spanish | I7: Production-proven | J7: Assistive | K7: User-facing | L7: Single-agent | M7: GenAI | N7: Medium | O7: 1 | P7: 3 | Q7: UK, EMEA, India | R7: Production | S7: ServiceNow, SharePoint | T7: Yes | U7: Yes | V7: Discard response and use standard search | W7: Partner | X7: Joint | Y7: PepsiCo | Z7: Hybrid | AA7: Architecture Pack AP-03; Knowledge Evaluation KE-01 | AB7: Benchmark-based | AC7: Answers restricted to approved indexed sources. | AD7: 15 proposed-agent entries: SOP Execution Agent [POC Completed]; MoMo Integration Chatbot [Pilot]; Support Assistant [Pilot]; Content Writer Agent [In Prod]; Knowledge Base (KB) Search with Guided Probing Agent [In Prod]; IRR - Incident Resolution Recommender [POC Completed]; AI Support Assistant [Pilot]; Intelligent Support Assistant [Pilot]; Resolution Notes Agent [In Prod]; Ask me Agent for business users [In Prod]; Snap.IO : Virtual Assistant [POC Completed]; DataGuard Agent [Pilot]; Rev-EAGLE [Pilot]; Knowledge Base Agent [POC Completed]; PEPSICONNECT_CONTENT_CONFIG_AGENT [To be custom built for PepsiCo]
A8: AIA-004 | B8: Service Request Fulfilment Agent | C8: Validates standard requests and orchestrates approved fulfilment workflows. | D8: Service Desk | E8: Service catalog | F8: Request fulfilment | G8: Workflow fulfilment | H8: English | I8: Configurable existing capability | J8: Human-approved execution | K8: User-facing | L8: Orchestration agent | M8: Blended | N8: Complex | O8: 2 | P8: 4 | Q8: UK, EMEA, India | R8: Test, Production | S8: ServiceNow, Entra ID | T8: Yes | U8: Yes | V8: Cancel workflow and restore prior state | W8: Partner | X8: Joint | Y8: PepsiCo | Z8: Hybrid | AA8: Architecture Pack AP-04; Workflow Catalogue WC-01 | AB8: Partner-estimated | AC8: Approval retained for access, spend and data changes. | AD8: 31 proposed-agent entries: TOMI [Pilot]; Intra-day Business KPI Reporting (Tapestry) [In Prod]; Scout Agent: [In Prod]; Rev-PULSE [Pilot]; Ticket Status Retrieval Agent [In Prod]; Service Request Creation Agent [In Prod]; Voice Channel Agent [In Prod]; Envision [In Prod]; Manufacturing Copilot [In Prod]; APAD [Pilot]; Forward a PO for Approval [In Prod]; Salesforce Agentforce(standard Query Data Capability) Agent [In Prod]; Email verfication and Delivery Agent [In Prod]; Accounts Payable Auto Invoice Generation Agent [In Prod]; Document Classification Agent [Pilot]; ABBYY_PO_ANALYZER_AGENT [To be custom built for PepsiCo]; TradeEdge-DiscountLens [To be custom built for PepsiCo]; PEPSICOSELL_Master_DATA_ROUTE_AGENT [To be custom built for PepsiCo]; FREEWEIGH_INSTALLISSUE_AGENT [To be custom built for PepsiCo]; PEPSICONNECT_SALES_TARGET_VALIDATION_AGENT [To be custom built for PepsiCo]; PEPSICONNECT_ORDER_FLOW_AGENT [To be custom built for PepsiCo]; PEPSICONNECT_INVOICE_PROCESS_VALIDATION_AGENT [To be custom built for PepsiCo]; PEPSICONNECT_MASTER_DATA_VALIDATION_AGENT [To be custom built for PepsiCo]; PEPSICONNECT_PROMOTION_PRODUCT_ENRICHMENT_AGENT [To be custom built for PepsiCo]; PEPSICONNECT_POINTS_TRANSFER_AGENT [To be custom built for PepsiCo]; PACE- Data Report Generator [To be custom built for PepsiCo]; PBNA_MODERENREPORT_DATAPULL_AGENT [To be custom built for PepsiCo]; PBNA_DELIVERY_DATAPULL_AGENT [To be custom built for PepsiCo]; PBNA_TPM_DATAPULL_AGENT [To be custom built for PepsiCo]; PBNA_TPM_ACCESS_AGENT [To be custom built for PepsiCo]; PBNA_STAR2_DATAPULL_AGENT [To be custom built for PepsiCo]
A9: AIA-005 | B9: Problem Trend Analyst | C9: Correlates recurring incidents and proposes problem records and known errors. | D9: Service Management | E9: Enterprise applications | F9: Problem management | G9: Trend and root-cause analysis | H9: English | I9: Reusable accelerator | J9: Recommendation-based | K9: User-facing | L9: Multi-agent | M9: Agentic AI | N9: Complex | O9: 3 | P9: 3 | Q9: UK, EMEA, India | R9: Production | S9: ServiceNow, Log Analytics | T9: Yes | U9: Yes | V9: Analyst rejects candidate problem | W9: Partner | X9: Partner | Y9: PepsiCo | Z9: Hybrid | AA9: Architecture Pack AP-05; Evaluation Report ER-01 | AB9: Benchmark-based | AC9: Correlation is advisory; problem manager owns publication. | AD9: 7 proposed-agent entries: RCA Agent [In Prod]; SNOW Incident Pattern Analyzer [POC Completed]; RCA finder for Incident [POC Completed]; Incident Triage and RCA Agent [POC Completed]; Issue Predictor & Root Cause Identifier [In Prod]; Root Cause Identifier Agent [In Prod]; PACE- Issue analyser [To be custom built for PepsiCo]
A10: AIA-006 | B10: Change Risk Advisor | C10: Scores change risk using history, dependencies, conflicts and test evidence. | D10: Change & Release | E10: Enterprise applications | F10: Change enablement | G10: Risk assessment | H10: English | I10: Configurable existing capability | J10: Recommendation-based | K10: User-facing | L10: Supervisor agent | M10: Agentic AI | N10: Highly complex | O10: 4 | P10: 3 | Q10: UK, EMEA, India | R10: Test, Production | S10: ServiceNow, Azure DevOps | T10: Yes | U10: Yes | V10: CAB override with rationale | W10: Partner | X10: Joint | Y10: PepsiCo | Z10: Hybrid | AA10: Architecture Pack AP-06; Risk Model RM-01 | AB10: Partner-estimated | AC10: No autonomous approval; CAB remains accountable. | AD10: 4 proposed-agent entries: Code Scanner Agent [POC Completed]; Supply Chain Trade Compliance Agent [In Prod]; SDLC Lifecycle Agents - Review Agent [Pilot]; PACE- EOT Compliance Agent [To be custom built for PepsiCo]
A11: AIA-007 | B11: Test Case Generation Copilot | C11: Generates traceable regression tests from requirements and change records. | D11: Application Engineering | E11: Retail and CPG applications | F11: Testing | G11: Test generation | H11: English | I11: Reusable accelerator | J11: Assistive | K11: User-facing | L11: Domain agent | M11: GenAI | N11: Medium | O11: 1 | P11: 3 | Q11: UK, EMEA, India | R11: Development, Test | S11: Azure DevOps | T11: Yes | U11: Yes | V11: Reviewer edits or rejects generated tests | W11: Partner | X11: Partner | Y11: PepsiCo | Z11: Partner-hosted | AA11: Architecture Pack AP-07; Quality Benchmark QB-01 | AB11: Benchmark-based | AC11: Generated tests require engineering review before execution. | AD11: 4 proposed-agent entries: Agent based UI Automation – QA [POC Completed]; AgentQ - Test Case Generator [POC Completed]; SDLC Lifecycle Agents - TST Agent [Pilot]; PACE- Smoke Test executor [To be custom built for PepsiCo]
A12: AIA-008 | B12: Release Validation Agent | C12: Checks release evidence, deployment health and rollback readiness. | D12: Change & Release | E12: Enterprise applications | F12: Release management | G12: Release assurance | H12: English | I12: Net-new build | J12: Human-approved execution | K12: Headless | L12: Supervisor agent | M12: Blended | N12: Complex | O12: 3 | P12: 3 | Q12: UK, EMEA, India | R12: Test, Production | S12: Azure DevOps, ServiceNow | T12: Yes | U12: Yes | V12: Stop deployment and invoke rollback | W12: Partner | X12: Joint | Y12: PepsiCo | Z12: Hybrid | AA12: Architecture Pack AP-08; Release Control RC-02 | AB12: Partner-estimated | AC12: Deployment gates remain deterministic and auditable. | AD12: 12 proposed-agent entries: SDLC Lifecycle Agents [Pilot]; Product Lifecycle Management Agent [Pilot] ×2; Job Scheduler Migration Agent [POC Completed]; SDLC Lifecycle Agents - Dev Agent [Pilot]; SDLC Lifecycle Agents - DB Agent [Pilot]; SDLC Lifecycle Agents - API Agent [Pilot]; SDLC Lifecycle Agents - FE Agent [Pilot]; SDLC Lifecycle Agents - Doc Agent [Pilot]; SDLC Lifecycle Agents - Orchestrator Agent [Pilot]; NA- Application Enhachement [To be custom built for PepsiCo]; PBNA_DELIVERY_CODEFIX_AGENT [To be custom built for PepsiCo]
A13: AIA-009 | B13: Event Correlation Agent | C13: Clusters alerts, suppresses duplicates and opens enriched incidents. | D13: Cloud & Infrastructure | E13: Azure and hosted applications | F13: Event management | G13: Alert correlation | H13: English | I13: Production-proven | J13: Bounded autonomous execution | K13: Headless | L13: Multi-agent | M13: Blended | N13: Complex | O13: 3 | P13: 6 | Q13: UK, EMEA, India | R13: Production, DR | S13: Azure Monitor, Splunk, ServiceNow | T13: Yes | U13: Yes | V13: Disable correlation rule and replay events | W13: Partner | X13: Partner | Y13: PepsiCo | Z13: PepsiCo-hosted | AA13: Architecture Pack AP-09; Operations Evidence OE-01 | AB13: Production reference | AC13: Auto-creation limited by confidence and severity thresholds. | AD13: 17 proposed-agent entries: Incident Management Agent [POC Completed]; Alert Verification System Agent [Pilot]; Observability Dashboard Agent [Pilot]; Incident Management Dashboard Agent [Pilot]; Observability Assistant [POC Completed]; Incident Intelligence Agent [Pilot]; Log Analyser Agent [Pilot]; Performance and Capacity Management [POC Completed]; Batch Health Analyzer [In Prod]; OCC Agent [POC Completed]; DigitalOpsAgent [In Prod]; Long Running Process Watchdog [POC Completed]; Execution Log Analyzer Agent [POC Completed]; High Volume Analyzer Agent [POC Completed]; ART Alert Insight Agent [Pilot]; GTMS_ALERT_OPTIMIZER_AGENT [To be custom built for PepsiCo]; PFNA Anomaly Detection Agent [To be custom built for PepsiCo]
A14: AIA-010 | B14: Access Request Assistant | C14: Guides users, validates entitlements and prepares access requests. | D14: Identity & Access | E14: Enterprise applications | F14: Access management | G14: Request assistance | H14: English, French, Spanish | I14: Configurable existing capability | J14: Human-approved execution | K14: User-facing | L14: Domain agent | M14: Agentic AI | N14: Complex | O14: 2 | P14: 3 | Q14: UK, EMEA, India | R14: Production | S14: ServiceNow, Entra ID | T14: Yes | U14: Yes | V14: Approver rejects; workflow revokes on error | W14: Partner | X14: Joint | Y14: PepsiCo | Z14: Hybrid | AA14: Architecture Pack AP-10; IAM Control IC-01 | AB14: Partner-estimated | AC14: No direct privileged access grant without owner approval. | AD14: 13 proposed-agent entries: Intelli Access Agent [Pilot]; Password reset & Incorrect intent recognition using ServiceNow NLU [In Prod]; User Access Agent Assist [In Prod]; SAVVY_USERPROFILE_AGENT [To be custom built for PepsiCo]; SAVVY_ACCESS_AGENT [To be custom built for PepsiCo]; DELIVERSMARTR_ACCESS_AGENT [To be custom built for PepsiCo]; PEPSICONNECT_PROFILE_MANAGEMENT_AGENT [To be custom built for PepsiCo]; AMESA- DB Role Configurator [To be custom built for PepsiCo]; PACE- User Activation & deactivation [To be custom built for PepsiCo]; FinOps- User Activation & deactivation [To be custom built for PepsiCo]; AMESA- App Dromant Users [To be custom built for PepsiCo]; PBNA_MODERENReport_ACCESS_AGENT [To be custom built for PepsiCo]; PBNA_DELIVERY_ACCESS_AGENT [To be custom built for PepsiCo]
A15: AIA-011 | B15: Business Data Integrity & Reconciliation Agent | C15: Detects, diagnoses, reconciles and corrects business-transaction and master-data inconsistencies across enterprise applications. Read-only analysis and write actions use separate control tiers, with data-owner approval, before-and-after evidence, duplicate prevention and rollback for changes.
A16: AIA-012 | B16: Interaction Orchestrator | C16: Provides omnichannel front door across chat, email, voice and shared mailboxes. It creates, updates and checks tickets and sends routine communications, then hands off triage, knowledge, fulfilment and access work to the appropriate super agent.
A17: AIA-013 | B17: Operations Reporting & Insights Agent | C17: Produces governed operational dashboards, incident summaries, performance and capacity forecasts, and high-volume execution insights. It is read-only and advisory, using approved KPI definitions and data lineage while source agents retain correlation and remediation ownership.
A18: AIA-014 | B18: Commercial Intelligence & Sales Enablement Copilot | C18: Provides governed commercial research, pricing and rate insights, and CRM or Salesforce business queries to support sales decisions. Tickets to IT team can be provided
A19: AIA-015 | B19: Customer Order Operations Orchestrator | C19: Coordinates routine customer-order operations such as order entry, validation, status progression and approved exception handling.
A20: AIA-016 | B20: Business Analytics & Data Query Copilot | C20: Enables governed business KPI reporting, natural-language or text-to-SQL queries and dashboard generation over certified datasets. It enforces semantic definitions, row-level security and data-owner controls and is distinct from AMS operational reporting.
A21: AIA-017 | B21: Finance & Accounts Payable Automation Agent | C21: Automates controlled finance and accounts-payable activities such as invoice extraction or generation, validation, matching and workflow preparation. Duplicate, tax and PO checks, segregation of duties and finance approval are required before posting.

Sheet Demand_Scenarios
A1: AMS RFP | Demand, Workload & Adoption
A2: BIDDER INPUT: Provide one row per Agent ID and required scenario. “Trigger Unit” may be incidents, requests, alerts, deployments, test cases, interactions or API runs.
A4: Agent ID* | B4: Scenario* | C4: Trigger Unit* | D4: Eligible Monthly Volume* | E4: Eligible %* | F4: Adoption %* | G4: Executions / Eligible Unit* | H4: Retry % * | I4: Success % * | J4: Autonomous Resolution % * | K4: Human Escalation % * | L4: Peak Multiplier | M4: Concurrency | N4: Avg Runtime (min) | O4: Monthly Growth % * | P4: Seasonality Factor | Q4: Rollout Start Month | R4: Input Source* | S4: Evidence Reference | T4: Notes
A5: AIA-001 | B5: Minimum adoption | C5: incidents | D5: 7000 | E5: 1 | F5: 0.25 | G5: 1 | H5: 0.04 | I5: 0.92 | J5: 0.25 | K5: 0.12 | L5: 1.3 | M5: 8 | N5: 1.8 | O5: 0.005 | P5: 1 | Q5: 1 | R5: Partner-estimated | S5: Demand Model DM-01; workload workshop pending | T5: Scenario-scaled partner estimate; validate against 12 months of source-system history. Demand executions exclude retry attempts; retry is applied once in AI consumption sizing.
A6: AIA-001 | B6: Expected case | C6: incidents | D6: 7000 | E6: 1 | F6: 0.6 | G6: 1 | H6: 0.06 | I6: 0.94 | J6: 0.45 | K6: 0.1 | L6: 1.6 | M6: 16 | N6: 1.8 | O6: 0.01 | P6: 1 | Q6: 1 | R6: Partner-estimated | S6: Demand Model DM-01; workload workshop pending | T6: Scenario-scaled partner estimate; validate against 12 months of source-system history. Demand executions exclude retry attempts; retry is applied once in AI consumption sizing.
A7: AIA-001 | B7: High adoption | C7: incidents | D7: 7000 | E7: 1 | F7: 0.8 | G7: 1 | H7: 0.08 | I7: 0.95 | J7: 0.6 | K7: 0.08 | L7: 1.9 | M7: 28 | N7: 1.8 | O7: 0.015 | P7: 1 | Q7: 1 | R7: Partner-estimated | S7: Demand Model DM-01; workload workshop pending | T7: Scenario-scaled partner estimate; validate against 12 months of source-system history. Demand executions exclude retry attempts; retry is applied once in AI consumption sizing.
A8: AIA-001 | B8: Peak/stress case | C8: incidents | D8: 7000 | E8: 1 | F8: 0.95 | G8: 1 | H8: 0.12 | I8: 0.93 | J8: 0.65 | K8: 0.12 | L8: 2.5 | M8: 45 | N8: 1.8 | O8: 0.02 | P8: 1 | Q8: 1 | R8: Partner-estimated | S8: Demand Model DM-01; workload workshop pending | T8: Scenario-scaled partner estimate; validate against 12 months of source-system history. Demand executions exclude retry attempts; retry is applied once in AI consumption sizing.
A9: AIA-001 | B9: PepsiCo standard | C9: incidents | D9: 7000 | E9: 1 | F9: 0.7 | G9: 1 | H9: 0.07 | I9: 0.95 | J9: 0.5 | K9: 0.09 | L9: 1.8 | M9: 20 | N9: 1.8 | O9: 0.01 | P9: 1 | Q9: 1 | R9: Assumption requiring validation | S9: Demand Model DM-01; workload workshop pending | T9: Placeholder standard case pending PepsiCo volume validation. Demand executions exclude retry attempts; retry is applied once in AI consumption sizing.
A10: AIA-002 | B10: Minimum adoption | C10: eligible incidents | D10: 500 | E10: 0.65 | F10: 0.25 | G10: 1 | H10: 0.04 | I10: 0.92 | J10: 0.25 | K10: 0.12 | L10: 1.3 | M10: 8 | N10: 4.5 | O10: 0.005 | P10: 1 | Q10: 2 | R10: Partner-estimated | S10: Demand Model DM-01; workload workshop pending | T10: Scenario-scaled partner estimate; validate against 12 months of source-system history. Demand executions exclude retry attempts; retry is applied once in AI consumption sizing.
A11: AIA-002 | B11: Expected case | C11: eligible incidents | D11: 500 | E11: 0.65 | F11: 0.6 | G11: 1 | H11: 0.06 | I11: 0.94 | J11: 0.45 | K11: 0.1 | L11: 1.6 | M11: 16 | N11: 4.5 | O11: 0.01 | P11: 1 | Q11: 2 | R11: Partner-estimated | S11: Demand Model DM-01; workload workshop pending | T11: Scenario-scaled partner estimate; validate against 12 months of source-system history. Demand executions exclude retry attempts; retry is applied once in AI consumption sizing.
A12: AIA-002 | B12: High adoption | C12: eligible incidents | D12: 500 | E12: 0.65 | F12: 0.8 | G12: 1 | H12: 0.08 | I12: 0.95 | J12: 0.6 | K12: 0.08 | L12: 1.9 | M12: 28 | N12: 4.5 | O12: 0.015 | P12: 1 | Q12: 2 | R12: Partner-estimated | S12: Demand Model DM-01; workload workshop pending | T12: Scenario-scaled partner estimate; validate against 12 months of source-system history. Demand executions exclude retry attempts; retry is applied once in AI consumption sizing.
A13: AIA-002 | B13: Peak/stress case | C13: eligible incidents | D13: 500 | E13: 0.65 | F13: 0.95 | G13: 1 | H13: 0.12 | I13: 0.93 | J13: 0.65 | K13: 0.12 | L13: 2.5 | M13: 45 | N13: 4.5 | O13: 0.02 | P13: 1 | Q13: 2 | R13: Partner-estimated | S13: Demand Model DM-01; workload workshop pending | T13: Scenario-scaled partner estimate; validate against 12 months of source-system history. Demand executions exclude retry attempts; retry is applied once in AI consumption sizing.
A14: AIA-002 | B14: PepsiCo standard | C14: eligible incidents | D14: 500 | E14: 0.65 | F14: 0.7 | G14: 1 | H14: 0.07 | I14: 0.95 | J14: 0.5 | K14: 0.09 | L14: 1.8 | M14: 20 | N14: 4.5 | O14: 0.01 | P14: 1 | Q14: 2 | R14: Assumption requiring validation | S14: Demand Model DM-01; workload workshop pending | T14: Placeholder standard case pending PepsiCo volume validation. Demand executions exclude retry attempts; retry is applied once in AI consumption sizing.
A15: AIA-003 | B15: Minimum adoption | C15: knowledge interactions | D15: 575 | E15: 0.9 | F15: 0.25 | G15: 1 | H15: 0.04 | I15: 0.92 | J15: 0.25 | K15: 0.12 | L15: 1.3 | M15: 8 | N15: 1.5 | O15: 0.005 | P15: 1 | Q15: 1 | R15: Partner-estimated | S15: Demand Model DM-01; workload workshop pending | T15: Scenario-scaled partner estimate; validate against 12 months of source-system history. Demand executions exclude retry attempts; retry is applied once in AI consumption sizing.
A16: AIA-003 | B16: Expected case | C16: knowledge interactions | D16: 575 | E16: 0.9 | F16: 0.6 | G16: 1 | H16: 0.06 | I16: 0.94 | J16: 0.45 | K16: 0.1 | L16: 1.6 | M16: 16 | N16: 1.5 | O16: 0.01 | P16: 1 | Q16: 1 | R16: Partner-estimated | S16: Demand Model DM-01; workload workshop pending | T16: Scenario-scaled partner estimate; validate against 12 months of source-system history. Demand executions exclude retry attempts; retry is applied once in AI consumption sizing.
... A54: AIA-010 | B54: PepsiCo standard | C54: access requests | D54: 1200 | E54: 0.8 | F54: 0.7 | G54: 1 | H54: 0.07 | I54: 0.95 | J54: 0.5 | K54: 0.09 | L54: 1.8 | M54: 20 | N54: 3 | O54: 0.01 | P54: 1 | Q54: 3 | R54: Assumption requiring validation | S54: Demand Model DM-01; workload workshop pending | T54: Placeholder standard case pending PepsiCo volume validation. Demand executions exclude retry attempts; retry is applied once in AI consumption sizing.
A55: AIA-011 | B55: Minimum adoption | C55: Incidents & Requests | D55: 2800 | E55: 0.8
A56: AIA-011 | B56: Expected case | C56: Incidents & Requests | D56: 2800 | E56: 0.8
A57: AIA-011 | B57: High adoption | C57: Incidents & Requests | D57: 2800 | E57: 0.8
A58: AIA-011 | B58: Peak/stress case | C58: Incidents & Requests | D58: 2800 | E58: 0.8
A59: AIA-011 | B59: PepsiCo standard | C59: Incidents & Requests | D59: 2800 | E59: 0.8
A60: AIA-012 | B60: Minimum adoption | C60: incidents | D60: 200 | E60: 0.8
A61: AIA-012 | B61: Expected case | C61: incidents | D61: 200 | E61: 0.8
A62: AIA-012 | B62: High adoption | C62: incidents | D62: 200 | E62: 0.8
A63: AIA-012 | B63: Peak/stress case | C63: incidents | D63: 200 | E63: 0.8
A64: AIA-012 | B64: PepsiCo standard | C64: incidents | D64: 200 | E64: 0.8
A65: AIA-013 | B65: Minimum adoption | C65: incidents | D65: 250 | E65: 0.8
A66: AIA-013 | B66: Expected case | C66: incidents | D66: 250 | E66: 0.8
... A89: AIA-017 | B89: PepsiCo standard | C89: Incidents & Requests | D89: 50 | E89: 0.8

Sheet AI_Consumption
A1: AMS RFP | LLM & AI Services Consumption
A2: BIDDER INPUT: One row per Agent ID, scenario and model/service. Capture routing, fallback, caching and contracted pricing. Do not duplicate retrieval/tool tokens.
A4: Agent ID* | B4: Scenario* | C4: Provider* | D4: Model / Service Name* | E4: Version / SKU | F4: Model Class* | G4: Primary / Fallback | H4: Hosting / Deployment | I4: Calls per Execution* | J4: Input Tokens / Call* | K4: Output Tokens / Call* | L4: System Prompt Tokens | M4: Retrieval / Tool Tokens | N4: Agent-to-Agent Exchanges | O4: Cache Hit % | P4: Retry % | Q4: Unit Price Input / 1M | R4: Unit Price Output / 1M | S4: Other Unit Price | T4: Other Unit of Measure | U4: Currency* | V4: Region | W4: Effective Date | X4: Enterprise Discount % | Y4: Partner Markup % | Z4: Minimum Commitment | AA4: Pricing Source / Evidence* | AB4: Input Source* | AC4: Notes
A5: AIA-001 | B5: Minimum adoption | C5: Microsoft Azure | D5: GPT-4.1 mini | E5: gpt-4.1-mini-2025-04-14 | F5: Small | G5: Primary | H5: Azure AI Foundry | I5: 2 | J5: 1800 | K5: 350 | L5: 500 | M5: 700 | N5: 0 | O5: 0.25 | P5: 0.04 | Q5: 0.4 | R5: 1.6 | S5: 0 | T5: N/A | U5: USD | V5: US benchmark | W5: 46298 | X5: 0 | Y5: 0 | Z5: 0 | AA5: OpenAI public API pricing benchmark; validate Azure AI Foundry enterprise rate | AB5: List price | AC5: No discount or markup assumed; regional Azure pricing and data-residency uplift require validation. Demand executions exclude retries; the Retry % here is the single consumption uplift. No minimum commitment assumed; pricing validity is unconfirmed pending the contracted Azure rate card.
A6: AIA-001 | B6: Expected case | C6: Microsoft Azure | D6: GPT-4.1 mini | E6: gpt-4.1-mini-2025-04-14 | F6: Small | G6: Primary | H6: Azure AI Foundry | I6: 2 | J6: 1800 | K6: 350 | L6: 500 | M6: 700 | N6: 0 | O6: 0.25 | P6: 0.06 | Q6: 0.4 | R6: 1.6 | S6: 0 | T6: N/A | U6: USD | V6: US benchmark | W6: 46298 | X6: 0 | Y6: 0 | Z6: 0 | AA6: OpenAI public API pricing benchmark; validate Azure AI Foundry enterprise rate | AB6: List price | AC6: No discount or markup assumed; regional Azure pricing and data-residency uplift require validation. Demand executions exclude retries; the Retry % here is the single consumption uplift. No minimum commitment assumed; pricing validity is unconfirmed pending the contracted Azure rate card.
A7: AIA-001 | B7: High adoption | C7: Microsoft Azure | D7: GPT-4.1 mini | E7: gpt-4.1-mini-2025-04-14 | F7: Small | G7: Primary | H7: Azure AI Foundry | I7: 2 | J7: 1800 | K7: 350 | L7: 500 | M7: 700 | N7: 0 | O7: 0.25 | P7: 0.08 | Q7: 0.4 | R7: 1.6 | S7: 0 | T7: N/A | U7: USD | V7: US benchmark | W7: 46298 | X7: 0 | Y7: 0 | Z7: 0 | AA7: OpenAI public API pricing benchmark; validate Azure AI Foundry enterprise rate | AB7: List price | AC7: No discount or markup assumed; regional Azure pricing and data-residency uplift require validation. Demand executions exclude retries; the Retry % here is the single consumption uplift. No minimum commitment assumed; pricing validity is unconfirmed pending the contracted Azure rate card.
A8: AIA-001 | B8: Peak/stress case | C8: Microsoft Azure | D8: GPT-4.1 mini | E8: gpt-4.1-mini-2025-04-14 | F8: Small | G8: Primary | H8: Azure AI Foundry | I8: 2 | J8: 1800 | K8: 350 | L8: 500 | M8: 700 | N8: 0 | O8: 0.25 | P8: 0.12 | Q8: 0.4 | R8: 1.6 | S8: 0 | T8: N/A | U8: USD | V8: US benchmark | W8: 46298 | X8: 0 | Y8: 0 | Z8: 0 | AA8: OpenAI public API pricing benchmark; validate Azure AI Foundry enterprise rate | AB8: List price | AC8: No discount or markup assumed; regional Azure pricing and data-residency uplift require validation. Demand executions exclude retries; the Retry % here is the single consumption uplift. No minimum commitment assumed; pricing validity is unconfirmed pending the contracted Azure rate card.
A9: AIA-001 | B9: PepsiCo standard | C9: Microsoft Azure | D9: GPT-4.1 mini | E9: gpt-4.1-mini-2025-04-14 | F9: Small | G9: Primary | H9: Azure AI Foundry | I9: 2 | J9: 1800 | K9: 350 | L9: 500 | M9: 700 | N9: 0 | O9: 0.25 | P9: 0.07 | Q9: 0.4 | R9: 1.6 | S9: 0 | T9: N/A | U9: USD | V9: US benchmark | W9: 46298 | X9: 0 | Y9: 0 | Z9: 0 | AA9: OpenAI public API pricing benchmark; validate Azure AI Foundry enterprise rate | AB9: List price | AC9: No discount or markup assumed; regional Azure pricing and data-residency uplift require validation. Demand executions exclude retries; the Retry % here is the single consumption uplift. No minimum commitment assumed; pricing validity is unconfirmed pending the contracted Azure rate card.
A10: AIA-002 | B10: Minimum adoption | C10: Microsoft Azure | D10: GPT-4.1 | E10: gpt-4.1-2025-04-14 | F10: Large | G10: Primary | H10: Azure AI Foundry | I10: 1.2 | J10: 5000 | K10: 900 | L10: 500 | M10: 700 | N10: 1 | O10: 0.25 | P10: 0.04 | Q10: 2 | R10: 8 | S10: 0 | T10: N/A | U10: USD | V10: US benchmark | W10: 46298 | X10: 0 | Y10: 0 | Z10: 0 | AA10: OpenAI public API pricing benchmark; validate Azure AI Foundry enterprise rate | AB10: List price | AC10: No discount or markup assumed; regional Azure pricing and data-residency uplift require validation. Demand executions exclude retries; the Retry % here is the single consumption uplift. No minimum commitment assumed; pricing validity is unconfirmed pending the contracted Azure rate card.
A11: AIA-002 | B11: Expected case | C11: Microsoft Azure | D11: GPT-4.1 | E11: gpt-4.1-2025-04-14 | F11: Large | G11: Primary | H11: Azure AI Foundry | I11: 1.2 | J11: 5000 | K11: 900 | L11: 500 | M11: 700 | N11: 1 | O11: 0.25 | P11: 0.06 | Q11: 2 | R11: 8 | S11: 0 | T11: N/A | U11: USD | V11: US benchmark | W11: 46298 | X11: 0 | Y11: 0 | Z11: 0 | AA11: OpenAI public API pricing benchmark; validate Azure AI Foundry enterprise rate | AB11: List price | AC11: No discount or markup assumed; regional Azure pricing and data-residency uplift require validation. Demand executions exclude retries; the Retry % here is the single consumption uplift. No minimum commitment assumed; pricing validity is unconfirmed pending the contracted Azure rate card.
A12: AIA-002 | B12: High adoption | C12: Microsoft Azure | D12: GPT-4.1 | E12: gpt-4.1-2025-04-14 | F12: Large | G12: Primary | H12: Azure AI Foundry | I12: 1.2 | J12: 5000 | K12: 900 | L12: 500 | M12: 700 | N12: 1 | O12: 0.25 | P12: 0.08 | Q12: 2 | R12: 8 | S12: 0 | T12: N/A | U12: USD | V12: US benchmark | W12: 46298 | X12: 0 | Y12: 0 | Z12: 0 | AA12: OpenAI public API pricing benchmark; validate Azure AI Foundry enterprise rate | AB12: List price | AC12: No discount or markup assumed; regional Azure pricing and data-residency uplift require validation. Demand executions exclude retries; the Retry % here is the single consumption uplift. No minimum commitment assumed; pricing validity is unconfirmed pending the contracted Azure rate card.
A13: AIA-002 | B13: Peak/stress case | C13: Microsoft Azure | D13: GPT-4.1 | E13: gpt-4.1-2025-04-14 | F13: Large | G13: Primary | H13: Azure AI Foundry | I13: 1.2 | J13: 5000 | K13: 900 | L13: 500 | M13: 700 | N13: 1 | O13: 0.25 | P13: 0.12 | Q13: 2 | R13: 8 | S13: 0 | T13: N/A | U13: USD | V13: US benchmark | W13: 46298 | X13: 0 | Y13: 0 | Z13: 0 | AA13: OpenAI public API pricing benchmark; validate Azure AI Foundry enterprise rate | AB13: List price | AC13: No discount or markup assumed; regional Azure pricing and data-residency uplift require validation. Demand executions exclude retries; the Retry % here is the single consumption uplift. No minimum commitment assumed; pricing validity is unconfirmed pending the contracted Azure rate card.
A14: AIA-002 | B14: PepsiCo standard | C14: Microsoft Azure | D14: GPT-4.1 | E14: gpt-4.1-2025-04-14 | F14: Large | G14: Primary | H14: Azure AI Foundry | I14: 1.2 | J14: 5000 | K14: 900 | L14: 500 | M14: 700 | N14: 1 | O14: 0.25 | P14: 0.07 | Q14: 2 | R14: 8 | S14: 0 | T14: N/A | U14: USD | V14: US benchmark | W14: 46298 | X14: 0 | Y14: 0 | Z14: 0 | AA14: OpenAI public API pricing benchmark; validate Azure AI Foundry enterprise rate | AB14: List price | AC14: No discount or markup assumed; regional Azure pricing and data-residency uplift require validation. Demand executions exclude retries; the Retry % here is the single consumption uplift. No minimum commitment assumed; pricing validity is unconfirmed pending the contracted Azure rate card.
A15: AIA-003 | B15: Minimum adoption | C15: Microsoft Azure | D15: GPT-4.1 mini | E15: gpt-4.1-mini-2025-04-14 | F15: Small | G15: Primary | H15: Azure AI Foundry | I15: 2 | J15: 1800 | K15: 350 | L15: 500 | M15: 700 | N15: 0 | O15: 0.25 | P15: 0.04 | Q15: 0.4 | R15: 1.6 | S15: 0 | T15: N/A | U15: USD | V15: US benchmark | W15: 46298 | X15: 0 | Y15: 0 | Z15: 0 | AA15: OpenAI public API pricing benchmark; validate Azure AI Foundry enterprise rate | AB15: List price | AC15: No discount or markup assumed; regional Azure pricing and data-residency uplift require validation. Demand executions exclude retries; the Retry % here is the single consumption uplift. No minimum commitment assumed; pricing validity is unconfirmed pending the contracted Azure rate card.
A16: AIA-003 | B16: Expected case | C16: Microsoft Azure | D16: GPT-4.1 mini | E16: gpt-4.1-mini-2025-04-14 | F16: Small | G16: Primary | H16: Azure AI Foundry | I16: 2 | J16: 1800 | K16: 350 | L16: 500 | M16: 700 | N16: 0 | O16: 0.25 | P16: 0.06 | Q16: 0.4 | R16: 1.6 | S16: 0 | T16: N/A | U16: USD | V16: US benchmark | W16: 46298 | X16: 0 | Y16: 0 | Z16: 0 | AA16: OpenAI public API pricing benchmark; validate Azure AI Foundry enterprise rate | AB16: List price | AC16: No discount or markup assumed; regional Azure pricing and data-residency uplift require validation. Demand executions exclude retries; the Retry % here is the single consumption uplift. No minimum commitment assumed; pricing validity is unconfirmed pending the contracted Azure rate card.
... A54: AIA-010 | B54: PepsiCo standard | C54: Microsoft Azure | D54: GPT-4.1 mini | E54: gpt-4.1-mini-2025-04-14 | F54: Small | G54: Primary | H54: Azure AI Foundry | I54: 2 | J54: 1800 | K54: 350 | L54: 500 | M54: 700 | N54: 0 | O54: 0.25 | P54: 0.07 | Q54: 0.4 | R54: 1.6 | S54: 0 | T54: N/A | U54: USD | V54: US benchmark | W54: 46298 | X54: 0 | Y54: 0 | Z54: 0 | AA54: OpenAI public API pricing benchmark; validate Azure AI Foundry enterprise rate | AB54: List price | AC54: No discount or markup assumed; regional Azure pricing and data-residency uplift require validation. Demand executions exclude retries; the Retry % here is the single consumption uplift. No minimum commitment assumed; pricing validity is unconfirmed pending the contracted Azure rate card.

Sheet Assumptions
A1: Partner Model For Agent Cost Estimation
A2: Pepsi Agentic Operations – 18‑Month Operating & Cost Model (Azure + LLM) | J2: BIDDER INPUT: Complete blue/yellow cells for timeline, build/adoption, workload, LLM behavior, token sizing, and token prices. Values must reflect the proposed AMS solution and be evidence-based.
A4: Timeline & Scope | F4: Build Plan (override optional)
A5: Model start month | B5: 46235 | C5: (Edit) | F5: Quarter | G5: Agents built | H5: Months
A6: Months modeled | B6: 18 | F6: Q1 | G6: 2 | H6: 3
A7: Workdays per month (avg) | B7: 21 | F7: Q2 | G7: 2 | H7: 3
A8: Region / currency | B8: USD | US benchmark; validate Azure region and enterprise agreement | F8: Q3 | G8: 2 | H8: 3
F9: Q4 | G9: 2 | H9: 3
A10: Agent Build & Adoption | F10: Q5 | G10: 0 | H10: 3
A11: Starting agents in production (existing) | B11: 2 | F11: Q6 | G11: 0 | H11: 3
A12: Agents built per quarter (avg) | B12: 2
A13: Ramp‑up: % of new agents active in month 1 | B13: 0.35 | F13: Total built (plan) | G13: =SUM(G6:G11) -> 8
A14: Ramp‑up: % active in month 2 | B14: 0.7
A15: Ramp‑up: % active in month 3+ | B15: 0.9
A16: Retirement / deprecation (% of installed base per month) | B16: 0.005
A18: Workload (Tickets & Agent Behavior)
A19: Tickets handled per active agent per workday | B19: 35
A20: Percent of tickets that are ‘self‑healing / automated fix’ | B20: 0.4
A21: Reopens / follow‑ups (% of tickets generating extra work) | B21: 0.08
A22: Avg. minutes of agent runtime per ticket (compute) | B22: 3
A24: LLM Usage (Foundry / Azure OpenAI style pricing)
A25: LLM calls per ticket (small model) | B25: 2
A26: LLM calls per ticket (large / reasoning model) | B26: 0.3
A27: Avg input tokens per small call | B27: 1800
A28: Avg output tokens per small call | B28: 350 | D28: =B28*0.8 -> 280
A29: Avg input tokens per large call | B29: 5000 | D29: =B29*0.2 -> 1000
A30: Avg output tokens per large call | B30: 900 | D30: =B30*0.2 -> 180
A31: Cache hit rate on input tokens (if supported) | B31: 0.25
A32: Retrieval / tool tokens overhead per ticket (extra input tokens) | B32: 700
A34: Unit price – small model input ($/1M tokens) | B34: 0.4
A35: Unit price – small model output ($/1M tokens) | B35: 1.6
A36: Unit price – large model input ($/1M tokens) | B36: 2
A37: Unit price – large model output ($/1M tokens) | B37: 8
A39: Platform Unit Costs
A40: All Azure / tools unit costs are in the Unit_Costs tab (editable).
A41: Notes | B41: Normalized monthly view uses portfolio-level tickets per active agent and blended LLM behavior. Demand_Scenarios uses agent-specific trigger populations and adoption; Five_Year_TCO uses those detailed scenario populations. Differences are intentional and must be revalidated with PepsiCo source data.

Sheet Unit_Costs
A1: Partner Model For Agent Cost Estimation
A2: Unit Costs & Licensing (Azure / Tools) – editable | F2: BIDDER INPUT: Replace placeholders with proposed unit rates using the stated units. Complete Notes / Source with currency, region, SKU/tier, effective date, and pricing basis.
A4: Azure platform unit costs (replace with enterprise rates)
A5: Item | B5: Value | C5: Units | D5: Notes / Source
A6: AKS node cost (blended) | B6: 350 | C6: $/node/month | D6: Partner benchmark: blended AKS VM, disk and load balancer; validate Azure SKU/region | USD | US benchmark | effective 03-Oct-2026 | planning basis only | pricing validity unconfirmed; replace with contracted rate before submission.
A7: AKS nodes per 10 active agents (baseline) | B7: 1.5 | C7: nodes / 10 agents | D7: Sizing assumption: 1.5 nodes per 10 active agents incl. resilience | USD | US benchmark | effective 03-Oct-2026 | planning basis only | pricing validity unconfirmed; replace with contracted rate before submission.
A8: Azure Functions executions per ticket | B8: 3 | C8: exec / ticket | D8: Partner architecture estimate: orchestration and tool calls | USD | US benchmark | effective 03-Oct-2026 | planning basis only | pricing validity unconfirmed; replace with contracted rate before submission.
A9: Avg GB‑seconds per Function execution | B9: 0.25 | C9: GB‑s / exec | D9: 0.5 GB memory for 0.5 second average execution | USD | US benchmark | effective 03-Oct-2026 | planning basis only | pricing validity unconfirmed; replace with contracted rate before submission.
A10: Functions price | B10: 0.2 | C10: $ / 1M exec | D10: Azure Functions Consumption list price; official Microsoft pricing | USD | US benchmark | effective 03-Oct-2026 | planning basis only | pricing validity unconfirmed; replace with contracted rate before submission.
A11: Functions price | B11: 1.6e-05 | C11: $ / GB‑s | D11: Azure Functions Consumption list price; official Microsoft pricing | USD | US benchmark | effective 03-Oct-2026 | planning basis only | pricing validity unconfirmed; replace with contracted rate before submission.
A12: Functions monthly free grant | B12: 1000000 | C12: executions | D12: Azure Functions Consumption monthly free grant | USD | US benchmark | effective 03-Oct-2026 | planning basis only | pricing validity unconfirmed; replace with contracted rate before submission.
A13: Functions monthly free grant | B13: 400000 | C13: GB‑seconds | D13: Azure Functions Consumption monthly free grant | USD | US benchmark | effective 03-Oct-2026 | planning basis only | pricing validity unconfirmed; replace with contracted rate before submission.
A14: ADLS storage cost | B14: 0.02 | C14: $ / GB‑month | D14: Partner benchmark for hot/cool storage blend; validate redundancy tier | USD | US benchmark | effective 03-Oct-2026 | planning basis only | pricing validity unconfirmed; replace with contracted rate before submission.
A15: Data lake growth | B15: 0.6 | C15: GB / 1,000 tickets | D15: Prompt, trace and artifact retention assumption | USD | US benchmark | effective 03-Oct-2026 | planning basis only | pricing validity unconfirmed; replace with contracted rate before submission.
A16: Postgres vCore cost (blended) | B16: 0.35 | C16: $ / vCore‑hr | D16: Partner benchmark for Flexible Server blended compute; validate tier and HA | USD | US benchmark | effective 03-Oct-2026 | planning basis only | pricing validity unconfirmed; replace with contracted rate before submission.
A17: Postgres storage cost | B17: 0.12 | C17: $ / GB‑month | D17: Partner benchmark for PostgreSQL storage; validate region and redundancy | USD | US benchmark | effective 03-Oct-2026 | planning basis only | pricing validity unconfirmed; replace with contracted rate before submission.
... A24: Power BI Pro cost | B24: 14 | C24: $ / user‑month | D24: Microsoft Power BI Pro public list price, paid yearly; check existing E5 entitlement | USD | US benchmark | effective 03-Oct-2026 | planning basis only | pricing validity unconfirmed; replace with contracted rate before submission.

Sheet Agent Rollout Plan
A1: APP SUPER AGENT DEPLOYMENT GANTT | J1: 26-Q3 | K1: 26-Q4 | L1: 27-Q1 | M1: 27-Q2 | T1: Super Agent | U1: Start | V1: 26-Q3 Days | W1: 26-Q4 Days | X1: 27-Q1 Days | Y1: 27-Q2 Days | Z1: 26-Q3 Cases | AA1: 26-Q4 Cases | AB1: 27-Q1 Cases | AC1: 27-Q2 Cases
A2: Filtered from '194 Automation opportunities_SH' where App/Infra = App | Schedule based on Quarter; impact based on Annual Incident Count | J2: Jul–Sep 2026 | K2: Oct–Dec 2026 | L2: Jan–Mar 2027 | M2: Apr–Jun 2027 | T2: =A6 -> Event Correlation & Alert Intelligence Agent | U2: =D6 -> #REF! | V2: =MAX(0,MIN($E6,DATE(2026,9,30))-MAX($D6,DATE(2026,6,30))) -> #REF! | W2: =MAX(0,MIN($E6,DATE(2026,12,31))-MAX($D6,DATE(2026,9,30))) -> #REF! | X2: =MAX(0,MIN($E6,DATE(2027,3,31))-MAX($D6,DATE(2026,12,31))) -> #REF! | Y2: =MAX(0,MIN($E6,DATE(2027,6,30))-MAX($D6,DATE(2027,3,31))) -> #REF! | Z2: 4 | AA2: 13 | AB2: 8 | AC2: 0
A3: App records | B3: 116 | D3: Super Agents | E3: 12 | G3: Total annual incidents | H3: 95561 | T3: =A7 -> Business Data Integrity & Reconciliation Agent | U3: =D7 -> #REF! | V3: =MAX(0,MIN($E7,DATE(2026,9,30))-MAX($D7,DATE(2026,6,30))) -> #REF! | W3: =MAX(0,MIN($E7,DATE(2026,12,31))-MAX($D7,DATE(2026,9,30))) -> #REF! | X3: =MAX(0,MIN($E7,DATE(2027,3,31))-MAX($D7,DATE(2026,12,31))) -> #REF! | Y3: =MAX(0,MIN($E7,DATE(2027,6,30))-MAX($D7,DATE(2027,3,31))) -> #REF! | Z3: 3 | AA3: 6 | AB3: 4 | AC3: 0
T4: =A8 -> Safe Auto-Remediation Agent | U4: =D8 -> #REF! | V4: =MAX(0,MIN($E8,DATE(2026,9,30))-MAX($D8,DATE(2026,6,30))) -> #REF! | W4: =MAX(0,MIN($E8,DATE(2026,12,31))-MAX($D8,DATE(2026,9,30))) -> #REF! | X4: =MAX(0,MIN($E8,DATE(2027,3,31))-MAX($D8,DATE(2026,12,31))) -> #REF! | Y4: =MAX(0,MIN($E8,DATE(2027,6,30))-MAX($D8,DATE(2027,3,31))) -> #REF! | Z4: 4 | AA4: 4 | AB4: 2 | AC4: 0
A5: Super Agent | B5: Start Quarter | C5: End Quarter | D5: Start Date | E5: End Date | F5: Duration (Days) | G5: Annual Incidents | H5: NUMBER OF USE CASES | I5: Active Quarters | T5: =A9 -> Workforce & Customer Identity Lifecycle Assistant | U5: =D9 -> #REF! | V5: =MAX(0,MIN($E9,DATE(2026,9,30))-MAX($D9,DATE(2026,6,30))) -> #REF! | W5: =MAX(0,MIN($E9,DATE(2026,12,31))-MAX($D9,DATE(2026,9,30))) -> #REF! | X5: =MAX(0,MIN($E9,DATE(2027,3,31))-MAX($D9,DATE(2026,12,31))) -> #REF! | Y5: =MAX(0,MIN($E9,DATE(2027,6,30))-MAX($D9,DATE(2027,3,31))) -> #REF! | Z5: 5 | AA5: 2 | AB5: 2 | AC5: 0
A6: Event Correlation & Alert Intelligence Agent | B6: {=_xlfn.LET(_xlpm.q,_xlfn._xlws.FILTER(#REF!,(#REF!="App")*(#REF!=$A6)),INDEX(_xlfn._xlws.SORT(_xlpm.q),1))} -> #REF! | C6: {=_xlfn.LET(_xlpm.q,_xlfn._xlws.FILTER(#REF!,(#REF!="App")*(#REF!=$A6)),INDEX(_xlfn._xlws.SORT(_xlpm.q),ROWS(_xlpm.q)))} -> #REF! | D6: =DATE(2000+LEFT(B6,2),1+(RIGHT(B6,1)-1)*3,1) -> #REF! | E6: =EDATE(DATE(2000+LEFT(C6,2),1+(RIGHT(C6,1)-1)*3,1),3)-1 -> #REF! | F6: =E6-D6+1 -> #REF! | G6: =SUMIFS(#REF!,#REF!,"App",#REF!,$A6) -> #REF! | H6: =COUNTIFS(#REF!,"App",#REF!,$A6) -> #REF! | I6: {=COUNTA(_xlfn.UNIQUE(_xlfn._xlws.FILTER(#REF!,(#REF!="App")*(#REF!=$A6))))} -> 1 | T6: =A10 -> Problem & Root-Cause Analyst | U6: =D10 -> #REF! | V6: =MAX(0,MIN($E10,DATE(2026,9,30))-MAX($D10,DATE(2026,6,30))) -> #REF! | W6: =MAX(0,MIN($E10,DATE(2026,12,31))-MAX($D10,DATE(2026,9,30))) -> #REF! | X6: =MAX(0,MIN($E10,DATE(2027,3,31))-MAX($D10,DATE(2026,12,31))) -> #REF! | Y6: =MAX(0,MIN($E10,DATE(2027,6,30))-MAX($D10,DATE(2027,3,31))) -> #REF! | Z6: 6 | AA6: 2 | AB6: 7 | AC6: 7
A7: Business Data Integrity & Reconciliation Agent | B7: {=_xlfn.LET(_xlpm.q,_xlfn._xlws.FILTER(#REF!,(#REF!="App")*(#REF!=$A7)),INDEX(_xlfn._xlws.SORT(_xlpm.q),1))} -> #REF! | C7: {=_xlfn.LET(_xlpm.q,_xlfn._xlws.FILTER(#REF!,(#REF!="App")*(#REF!=$A7)),INDEX(_xlfn._xlws.SORT(_xlpm.q),ROWS(_xlpm.q)))} -> #REF! | D7: =DATE(2000+LEFT(B7,2),1+(RIGHT(B7,1)-1)*3,1) -> #REF! | E7: =EDATE(DATE(2000+LEFT(C7,2),1+(RIGHT(C7,1)-1)*3,1),3)-1 -> #REF! | F7: =E7-D7+1 -> #REF! | G7: =SUMIFS(#REF!,#REF!,"App",#REF!,$A7) -> #REF! | H7: =COUNTIFS(#REF!,"App",#REF!,$A7) -> #REF! | I7: {=COUNTA(_xlfn.UNIQUE(_xlfn._xlws.FILTER(#REF!,(#REF!="App")*(#REF!=$A7))))} -> 1 | T7: =A11 -> Incident Triage & Major Incident Copilot | U7: =D11 -> #REF! | V7: =MAX(0,MIN($E11,DATE(2026,9,30))-MAX($D11,DATE(2026,6,30))) -> #REF! | W7: =MAX(0,MIN($E11,DATE(2026,12,31))-MAX($D11,DATE(2026,9,30))) -> #REF! | X7: =MAX(0,MIN($E11,DATE(2027,3,31))-MAX($D11,DATE(2026,12,31))) -> #REF! | Y7: =MAX(0,MIN($E11,DATE(2027,6,30))-MAX($D11,DATE(2027,3,31))) -> #REF! | Z7: 1 | AA7: 1 | AB7: 2 | AC7: 0
A8: Safe Auto-Remediation Agent | B8: {=_xlfn.LET(_xlpm.q,_xlfn._xlws.FILTER(#REF!,(#REF!="App")*(#REF!=$A8)),INDEX(_xlfn._xlws.SORT(_xlpm.q),1))} -> #REF! | C8: {=_xlfn.LET(_xlpm.q,_xlfn._xlws.FILTER(#REF!,(#REF!="App")*(#REF!=$A8)),INDEX(_xlfn._xlws.SORT(_xlpm.q),ROWS(_xlpm.q)))} -> #REF! | D8: =DATE(2000+LEFT(B8,2),1+(RIGHT(B8,1)-1)*3,1) -> #REF! | E8: =EDATE(DATE(2000+LEFT(C8,2),1+(RIGHT(C8,1)-1)*3,1),3)-1 -> #REF! | F8: =E8-D8+1 -> #REF! | G8: =SUMIFS(#REF!,#REF!,"App",#REF!,$A8) -> #REF! | H8: =COUNTIFS(#REF!,"App",#REF!,$A8) -> #REF! | I8: {=COUNTA(_xlfn.UNIQUE(_xlfn._xlws.FILTER(#REF!,(#REF!="App")*(#REF!=$A8))))} -> 1 | T8: =A12 -> Enterprise Document Intelligence & Compliance Agent | U8: =D12 -> #REF! | V8: =MAX(0,MIN($E12,DATE(2026,9,30))-MAX($D12,DATE(2026,6,30))) -> #REF! | W8: =MAX(0,MIN($E12,DATE(2026,12,31))-MAX($D12,DATE(2026,9,30))) -> #REF! | X8: =MAX(0,MIN($E12,DATE(2027,3,31))-MAX($D12,DATE(2026,12,31))) -> #REF! | Y8: =MAX(0,MIN($E12,DATE(2027,6,30))-MAX($D12,DATE(2027,3,31))) -> #REF! | Z8: 13 | AA8: 2 | AB8: 4 | AC8: 0
A9: Workforce & Customer Identity Lifecycle Assistant | B9: {=_xlfn.LET(_xlpm.q,_xlfn._xlws.FILTER(#REF!,(#REF!="App")*(#REF!=$A9)),INDEX(_xlfn._xlws.SORT(_xlpm.q),1))} -> #REF! | C9: {=_xlfn.LET(_xlpm.q,_xlfn._xlws.FILTER(#REF!,(#REF!="App")*(#REF!=$A9)),INDEX(_xlfn._xlws.SORT(_xlpm.q),ROWS(_xlpm.q)))} -> #REF! | D9: =DATE(2000+LEFT(B9,2),1+(RIGHT(B9,1)-1)*3,1) -> #REF! | E9: =EDATE(DATE(2000+LEFT(C9,2),1+(RIGHT(C9,1)-1)*3,1),3)-1 -> #REF! | F9: =E9-D9+1 -> #REF! | G9: =SUMIFS(#REF!,#REF!,"App",#REF!,$A9) -> #REF! | H9: =COUNTIFS(#REF!,"App",#REF!,$A9) -> #REF! | I9: {=COUNTA(_xlfn.UNIQUE(_xlfn._xlws.FILTER(#REF!,(#REF!="App")*(#REF!=$A9))))} -> 1 | T9: =A13 -> Operations Reporting & Insights Agent | U9: =D13 -> #REF! | V9: =MAX(0,MIN($E13,DATE(2026,9,30))-MAX($D13,DATE(2026,6,30))) -> #REF! | W9: =MAX(0,MIN($E13,DATE(2026,12,31))-MAX($D13,DATE(2026,9,30))) -> #REF! | X9: =MAX(0,MIN($E13,DATE(2027,3,31))-MAX($D13,DATE(2026,12,31))) -> #REF! | Y9: =MAX(0,MIN($E13,DATE(2027,6,30))-MAX($D13,DATE(2027,3,31))) -> #REF! | Z9: 0 | AA9: 6 | AB9: 1 | AC9: 0
A10: Problem & Root-Cause Analyst | B10: {=_xlfn.LET(_xlpm.q,_xlfn._xlws.FILTER(#REF!,(#REF!="App")*(#REF!=$A10)),INDEX(_xlfn._xlws.SORT(_xlpm.q),1))} -> #REF! | C10: {=_xlfn.LET(_xlpm.q,_xlfn._xlws.FILTER(#REF!,(#REF!="App")*(#REF!=$A10)),INDEX(_xlfn._xlws.SORT(_xlpm.q),ROWS(_xlpm.q)))} -> #REF! | D10: =DATE(2000+LEFT(B10,2),1+(RIGHT(B10,1)-1)*3,1) -> #REF! | E10: =EDATE(DATE(2000+LEFT(C10,2),1+(RIGHT(C10,1)-1)*3,1),3)-1 -> #REF! | F10: =E10-D10+1 -> #REF! | G10: =SUMIFS(#REF!,#REF!,"App",#REF!,$A10) -> #REF! | H10: =COUNTIFS(#REF!,"App",#REF!,$A10) -> #REF! | I10: {=COUNTA(_xlfn.UNIQUE(_xlfn._xlws.FILTER(#REF!,(#REF!="App")*(#REF!=$A10))))} -> 1 | T10: =A14 -> Release Quality & Validation Agent | U10: =D14 -> #REF! | V10: =MAX(0,MIN($E14,DATE(2026,9,30))-MAX($D14,DATE(2026,6,30))) -> #REF! | W10: =MAX(0,MIN($E14,DATE(2026,12,31))-MAX($D14,DATE(2026,9,30))) -> #REF! | X10: =MAX(0,MIN($E14,DATE(2027,3,31))-MAX($D14,DATE(2026,12,31))) -> #REF! | Y10: =MAX(0,MIN($E14,DATE(2027,6,30))-MAX($D14,DATE(2027,3,31))) -> #REF! | Z10: 0 | AA10: 2 | AB10: 0 | AC10: 0
A11: Incident Triage & Major Incident Copilot | B11: {=_xlfn.LET(_xlpm.q,_xlfn._xlws.FILTER(#REF!,(#REF!="App")*(#REF!=$A11)),INDEX(_xlfn._xlws.SORT(_xlpm.q),1))} -> #REF! | C11: {=_xlfn.LET(_xlpm.q,_xlfn._xlws.FILTER(#REF!,(#REF!="App")*(#REF!=$A11)),INDEX(_xlfn._xlws.SORT(_xlpm.q),ROWS(_xlpm.q)))} -> #REF! | D11: =DATE(2000+LEFT(B11,2),1+(RIGHT(B11,1)-1)*3,1) -> #REF! | E11: =EDATE(DATE(2000+LEFT(C11,2),1+(RIGHT(C11,1)-1)*3,1),3)-1 -> #REF! | F11: =E11-D11+1 -> #REF! | G11: =SUMIFS(#REF!,#REF!,"App",#REF!,$A11) -> #REF! | H11: =COUNTIFS(#REF!,"App",#REF!,$A11) -> #REF! | I11: {=COUNTA(_xlfn.UNIQUE(_xlfn._xlws.FILTER(#REF!,(#REF!="App")*(#REF!=$A11))))} -> 1 | T11: =A15 -> Knowledge & Resolution Copilot | U11: =D15 -> #REF! | V11: =MAX(0,MIN($E15,DATE(2026,9,30))-MAX($D15,DATE(2026,6,30))) -> #REF! | W11: =MAX(0,MIN($E15,DATE(2026,12,31))-MAX($D15,DATE(2026,9,30))) -> #REF! | X11: =MAX(0,MIN($E15,DATE(2027,3,31))-MAX($D15,DATE(2026,12,31))) -> #REF! | Y11: =MAX(0,MIN($E15,DATE(2027,6,30))-MAX($D15,DATE(2027,3,31))) -> #REF! | Z11: 0 | AA11: 2 | AB11: 0 | AC11: 0
A12: Enterprise Document Intelligence & Compliance Agent | B12: {=_xlfn.LET(_xlpm.q,_xlfn._xlws.FILTER(#REF!,(#REF!="App")*(#REF!=$A12)),INDEX(_xlfn._xlws.SORT(_xlpm.q),1))} -> #REF! | C12: {=_xlfn.LET(_xlpm.q,_xlfn._xlws.FILTER(#REF!,(#REF!="App")*(#REF!=$A12)),INDEX(_xlfn._xlws.SORT(_xlpm.q),ROWS(_xlpm.q)))} -> #REF! | D12: =DATE(2000+LEFT(B12,2),1+(RIGHT(B12,1)-1)*3,1) -> #REF! | E12: =EDATE(DATE(2000+LEFT(C12,2),1+(RIGHT(C12,1)-1)*3,1),3)-1 -> #REF! | F12: =E12-D12+1 -> #REF! | G12: =SUMIFS(#REF!,#REF!,"App",#REF!,$A12) -> #REF! | H12: =COUNTIFS(#REF!,"App",#REF!,$A12) -> #REF! | I12: {=COUNTA(_xlfn.UNIQUE(_xlfn._xlws.FILTER(#REF!,(#REF!="App")*(#REF!=$A12))))} -> 1 | T12: =A16 -> Service Desk Intake & Interaction Orchestrator | U12: =D16 -> #REF! | V12: =MAX(0,MIN($E16,DATE(2026,9,30))-MAX($D16,DATE(2026,6,30))) -> #REF! | W12: =MAX(0,MIN($E16,DATE(2026,12,31))-MAX($D16,DATE(2026,9,30))) -> #REF! | X12: =MAX(0,MIN($E16,DATE(2027,3,31))-MAX($D16,DATE(2026,12,31))) -> #REF! | Y12: =MAX(0,MIN($E16,DATE(2027,6,30))-MAX($D16,DATE(2027,3,31))) -> #REF! | Z12: 0 | AA12: 0 | AB12: 2 | AC12: 0
A13: Operations Reporting & Insights Agent | B13: {=_xlfn.LET(_xlpm.q,_xlfn._xlws.FILTER(#REF!,(#REF!="App")*(#REF!=$A13)),INDEX(_xlfn._xlws.SORT(_xlpm.q),1))} -> #REF! | C13: {=_xlfn.LET(_xlpm.q,_xlfn._xlws.FILTER(#REF!,(#REF!="App")*(#REF!=$A13)),INDEX(_xlfn._xlws.SORT(_xlpm.q),ROWS(_xlpm.q)))} -> #REF! | D13: =DATE(2000+LEFT(B13,2),1+(RIGHT(B13,1)-1)*3,1) -> #REF! | E13: =EDATE(DATE(2000+LEFT(C13,2),1+(RIGHT(C13,1)-1)*3,1),3)-1 -> #REF! | F13: =E13-D13+1 -> #REF! | G13: =SUMIFS(#REF!,#REF!,"App",#REF!,$A13) -> #REF! | H13: =COUNTIFS(#REF!,"App",#REF!,$A13) -> #REF! | I13: {=COUNTA(_xlfn.UNIQUE(_xlfn._xlws.FILTER(#REF!,(#REF!="App")*(#REF!=$A13))))} -> 1 | T13: =A17 -> Service Request & Standard Data Extract Fulfilment Agent | U13: =D17 -> #REF! | V13: =MAX(0,MIN($E17,DATE(2026,9,30))-MAX($D17,DATE(2026,6,30))) -> #REF! | W13: =MAX(0,MIN($E17,DATE(2026,12,31))-MAX($D17,DATE(2026,9,30))) -> #REF! | X13: =MAX(0,MIN($E17,DATE(2027,3,31))-MAX($D17,DATE(2026,12,31))) -> #REF! | Y13: =MAX(0,MIN($E17,DATE(2027,6,30))-MAX($D17,DATE(2027,3,31))) -> #REF! | Z13: 0 | AA13: 0 | AB13: 1 | AC13: 0
A14: Release Quality & Validation Agent | B14: {=_xlfn.LET(_xlpm.q,_xlfn._xlws.FILTER(#REF!,(#REF!="App")*(#REF!=$A14)),INDEX(_xlfn._xlws.SORT(_xlpm.q),1))} -> #REF! | C14: {=_xlfn.LET(_xlpm.q,_xlfn._xlws.FILTER(#REF!,(#REF!="App")*(#REF!=$A14)),INDEX(_xlfn._xlws.SORT(_xlpm.q),ROWS(_xlpm.q)))} -> #REF! | D14: =DATE(2000+LEFT(B14,2),1+(RIGHT(B14,1)-1)*3,1) -> #REF! | E14: =EDATE(DATE(2000+LEFT(C14,2),1+(RIGHT(C14,1)-1)*3,1),3)-1 -> #REF! | F14: =E14-D14+1 -> #REF! | G14: =SUMIFS(#REF!,#REF!,"App",#REF!,$A14) -> #REF! | H14: =COUNTIFS(#REF!,"App",#REF!,$A14) -> #REF! | I14: {=COUNTA(_xlfn.UNIQUE(_xlfn._xlws.FILTER(#REF!,(#REF!="App")*(#REF!=$A14))))} -> 1
A15: Knowledge & Resolution Copilot | B15: {=_xlfn.LET(_xlpm.q,_xlfn._xlws.FILTER(#REF!,(#REF!="App")*(#REF!=$A15)),INDEX(_xlfn._xlws.SORT(_xlpm.q),1))} -> #REF! | C15: {=_xlfn.LET(_xlpm.q,_xlfn._xlws.FILTER(#REF!,(#REF!="App")*(#REF!=$A15)),INDEX(_xlfn._xlws.SORT(_xlpm.q),ROWS(_xlpm.q)))} -> #REF! | D15: =DATE(2000+LEFT(B15,2),1+(RIGHT(B15,1)-1)*3,1) -> #REF! | E15: =EDATE(DATE(2000+LEFT(C15,2),1+(RIGHT(C15,1)-1)*3,1),3)-1 -> #REF! | F15: =E15-D15+1 -> #REF! | G15: =SUMIFS(#REF!,#REF!,"App",#REF!,$A15) -> #REF! | H15: =COUNTIFS(#REF!,"App",#REF!,$A15) -> #REF! | I15: {=COUNTA(_xlfn.UNIQUE(_xlfn._xlws.FILTER(#REF!,(#REF!="App")*(#REF!=$A15))))} -> 1
A16: Service Desk Intake & Interaction Orchestrator | B16: {=_xlfn.LET(_xlpm.q,_xlfn._xlws.FILTER(#REF!,(#REF!="App")*(#REF!=$A16)),INDEX(_xlfn._xlws.SORT(_xlpm.q),1))} -> #REF! | C16: {=_xlfn.LET(_xlpm.q,_xlfn._xlws.FILTER(#REF!,(#REF!="App")*(#REF!=$A16)),INDEX(_xlfn._xlws.SORT(_xlpm.q),ROWS(_xlpm.q)))} -> #REF! | D16: =DATE(2000+LEFT(B16,2),1+(RIGHT(B16,1)-1)*3,1) -> #REF! | E16: =EDATE(DATE(2000+LEFT(C16,2),1+(RIGHT(C16,1)-1)*3,1),3)-1 -> #REF! | F16: =E16-D16+1 -> #REF! | G16: =SUMIFS(#REF!,#REF!,"App",#REF!,$A16) -> #REF! | H16: =COUNTIFS(#REF!,"App",#REF!,$A16) -> #REF! | I16: {=COUNTA(_xlfn.UNIQUE(_xlfn._xlws.FILTER(#REF!,(#REF!="App")*(#REF!=$A16))))} -> 1
A17: Service Request & Standard Data Extract Fulfilment Agent | B17: {=_xlfn.LET(_xlpm.q,_xlfn._xlws.FILTER(#REF!,(#REF!="App")*(#REF!=$A17)),INDEX(_xlfn._xlws.SORT(_xlpm.q),1))} -> #REF! | C17: {=_xlfn.LET(_xlpm.q,_xlfn._xlws.FILTER(#REF!,(#REF!="App")*(#REF!=$A17)),INDEX(_xlfn._xlws.SORT(_xlpm.q),ROWS(_xlpm.q)))} -> #REF! | D17: =DATE(2000+LEFT(B17,2),1+(RIGHT(B17,1)-1)*3,1) -> #REF! | E17: =EDATE(DATE(2000+LEFT(C17,2),1+(RIGHT(C17,1)-1)*3,1),3)-1 -> #REF! | F17: =E17-D17+1 -> #REF! | G17: =SUMIFS(#REF!,#REF!,"App",#REF!,$A17) -> #REF! | H17: =COUNTIFS(#REF!,"App",#REF!,$A17) -> #REF! | I17: {=COUNTA(_xlfn.UNIQUE(_xlfn._xlws.FILTER(#REF!,(#REF!="App")*(#REF!=$A17))))} -> 1

Sheet Cost_Register
A1: AMS RFP | Detailed AI Cost Register
A2: BIDDER INPUT: One row per cost component. Assign exactly one mandatory classification. Net rates and annual costs are formula-driven. Avoid costs already captured in the original Unit_Costs model.
A4: Cost Line ID* | B4: Agent ID / Shared* | C4: Scenario* | D4: Cost Component* | E4: Cost Category* | F4: Mandatory Classification* | G4: Charging Basis* | H4: Provider | I4: SKU / Version | J4: Environment | K4: Quantity* | L4: Unit of Measure* | M4: Gross Unit Rate* | N4: Discount % | O4: Partner Markup % | P4: Net Unit Rate | Q4: Frequency* | R4: Term Months | S4: Escalation % | T4: Currency* | U4: Region | V4: Effective Date | W4: Inclusion* | X4: Year 1 Quantity | Y4: Year 2 Quantity | Z4: Year 3 Quantity | AA4: Year 4 Quantity | AB4: Year 5 Quantity | AC4: Year 1 Cost | AD4: Year 2 Cost | AE4: Year 3 Cost | AF4: Year 4 Cost | AG4: Year 5 Cost | AH4: Five-Year Cost | AI4: Evidence Reference* | AJ4: Input Source* | AK4: Notes / Exclusions
A5: CL-001 | B5: Shared | C5: Minimum adoption | D5: Agent discovery, design and onboarding | E5: Implementation | F5: One-time | G5: Per agent | H5: Partner | I5: Implementation package | J5: Development, Test, Production | K5: 6 | L5: agents | M5: 45000 | N5: 0 | O5: 0 | P5: =IF(OR(M5="",M5=0),0,M5*(1-N5)*(1+O5)) -> 45000 | Q5: One-time | R5: 12 | S5: 0 | T5: USD | U5: US benchmark | V5: 46298 | W5: Separately priced | X5: 6 | Y5: 0 | Z5: 0 | AA5: 0 | AB5: 0 | AC5: =IFERROR(X5*$P5,0) -> 270000 | AD5: =IFERROR(Y5*$P5,0) -> 0 | AE5: =IFERROR(Z5*$P5,0) -> 0 | AF5: =IFERROR(AA5*$P5,0) -> 0 | AG5: =IFERROR(AB5*$P5,0) -> 0 | AH5: =SUM(AC5:AG5) -> 270000 | AI5: Commercial Workbook CW-01; Statement of Work pending | AJ5: Partner-estimated | AK5: One charge per deployed agent; excludes third-party licenses and customer remediation work. Shared allocation: quantity equals agents deployed in the scenario. Pricing validity: planning benchmark only; commercial proposal and contracted terms pending.
A6: CL-002 | B6: Shared | C6: Minimum adoption | D6: Managed AI and Agent Operations | E6: Managed service | F6: Recurring fixed | G6: Per hour | H6: Partner | I6: Blended delivery team | J6: Production | K6: 10452 | L6: hours | M6: 57.69 | N6: 0 | O6: 0 | P6: =IF(OR(M6="",M6=0),0,M6*(1-N6)*(1+O6)) -> 57.69 | Q6: Annual | R6: 60 | S6: 0.03 | T6: USD | U6: US benchmark | V6: 46298 | W6: Separately priced | X6: 10452 | Y6: 10765.56 | Z6: 11088.527 | AA6: 11421.183 | AB6: 11763.818 | AC6: =IFERROR(X6*$P6,0) -> 602975.88 | AD6: =IFERROR(Y6*$P6,0) -> 621065.16 | AE6: =IFERROR(Z6*$P6,0) -> 639697.11 | AF6: =IFERROR(AA6*$P6,0) -> 658888.02 | AG6: =IFERROR(AB6*$P6,0) -> 678654.67 | AH6: =SUM(AC6:AG6) -> 3201280.8 | AI6: Staffing model SM-01; rate card pending | AJ6: Partner-estimated | AK6: 7.5-FTE expected-case baseline; annual quantity includes 3% escalation and is the sole labor cost line. Shared allocation: operator hours scale with the scenario workload factor. Pricing validity: planning benchmark only; commercial proposal and contracted terms pending.
A7: CL-003 | B7: Shared | C7: Minimum adoption | D7: Azure platform shared services | E7: Platform | F7: Recurring fixed | G7: Other(s) | H7: Microsoft Azure | I7: AKS, data and integration bundle | J7: Shared | K7: 12 | L7: months | M7: 2400 | N7: 0 | O7: 0 | P7: =IF(OR(M7="",M7=0),0,M7*(1-N7)*(1+O7)) -> 2400 | Q7: Monthly | R7: 60 | S7: 0.03 | T7: USD | U7: US benchmark | V7: 46298 | W7: Pass-through | X7: 8.04 | Y7: 8.2812 | Z7: 8.529636 | AA7: 8.7855251 | AB7: 9.0490908 | AC7: =IFERROR(X7*$P7,0) -> 19296 | AD7: =IFERROR(Y7*$P7,0) -> 19874.88 | AE7: =IFERROR(Z7*$P7,0) -> 20471.126 | AF7: =IFERROR(AA7*$P7,0) -> 21085.26 | AG7: =IFERROR(AB7*$P7,0) -> 21717.818 | AH7: =SUM(AC7:AG7) -> 102445.08 | AI7: Architecture Pack AP-00; Azure estimate pending | AJ7: Partner-estimated | AK7: Shared platform allocation by scenario load; Unit_Costs is supporting detail, not an additional charge. Shared allocation: monthly shared platform charge scales with scenario load. Pricing validity: planning benchmark only; commercial proposal and contracted terms pending.
A8: CL-004 | B8: Shared | C8: Minimum adoption | D8: LLM inference consumption | E8: AI services | F8: Recurring variable | G8: Consumption-based | H8: Microsoft Azure | I8: GPT-4.1 / GPT-4.1 mini blend | J8: Production | K8: 600 | L8: million tokens | M8: 1.25 | N8: 0 | O8: 0 | P8: =IF(OR(M8="",M8=0),0,M8*(1-N8)*(1+O8)) -> 1.25 | Q8: Usage-based | R8: 60 | S8: 0 | T8: USD | U8: US benchmark | V8: 46298 | W8: Pass-through | X8: 600 | Y8: 660 | Z8: 726 | AA8: 798.6 | AB8: 878.46 | AC8: =IFERROR(X8*$P8,0) -> 750 | AD8: =IFERROR(Y8*$P8,0) -> 825 | AE8: =IFERROR(Z8*$P8,0) -> 907.5 | AF8: =IFERROR(AA8*$P8,0) -> 998.25 | AG8: =IFERROR(AB8*$P8,0) -> 1098.075 | AH8: =SUM(AC8:AG8) -> 4578.825 | AI8: OpenAI public API pricing benchmark; Azure rate pending | AJ8: List price | AK8: Blended token rate for planning only; replace with Azure AI Foundry contracted rates and measured routing mix. Shared allocation: token quantity scales with scenario AI consumption. Pricing validity: planning benchmark only; commercial proposal and contracted terms pending.
A9: CL-005 | B9: Shared | C9: Minimum adoption | D9: Observability, dashboards and reporting | E9: Observability | F9: Recurring fixed | G9: Other(s) | H9: Partner / Microsoft | I9: Managed observability bundle | J9: Production | K9: 12 | L9: months | M9: 3000 | N9: 0 | O9: 0 | P9: =IF(OR(M9="",M9=0),0,M9*(1-N9)*(1+O9)) -> 3000 | Q9: Monthly | R9: 60 | S9: 0.03 | T9: USD | U9: US benchmark | V9: 46298 | W9: Separately priced | X9: 8.04 | Y9: 8.2812 | Z9: 8.529636 | AA9: 8.7855251 | AB9: 9.0490908 | AC9: =IFERROR(X9*$P9,0) -> 24120 | AD9: =IFERROR(Y9*$P9,0) -> 24843.6 | AE9: =IFERROR(Z9*$P9,0) -> 25588.908 | AF9: =IFERROR(AA9*$P9,0) -> 26356.575 | AG9: =IFERROR(AB9*$P9,0) -> 27147.272 | AH9: =SUM(AC9:AG9) -> 128056.36 | AI9: Operations Model OM-01; license validation pending | AJ9: Partner-estimated | AK9: Includes dashboard operations; Power BI licenses assumed available separately where already entitled. Shared allocation: managed observability charge scales with scenario load. Pricing validity: planning benchmark only; commercial proposal and contracted terms pending.
A10: CL-006 | B10: Shared | C10: Minimum adoption | D10: Exit transition and knowledge transfer | E10: Exit | F10: Exit-related | G10: Separate project | H10: Partner | I10: Exit package | J10: Production | K10: 1 | L10: package | M10: 100000 | N10: 0 | O10: 0 | P10: =IF(OR(M10="",M10=0),0,M10*(1-N10)*(1+O10)) -> 100000 | Q10: One-time | R10: 60 | S10: 0 | T10: USD | U10: US benchmark | V10: 46298 | W10: Optional | X10: 0 | Y10: 0 | Z10: 0 | AA10: 0 | AB10: 1 | AC10: =IFERROR(X10*$P10,0) -> 0 | AD10: =IFERROR(Y10*$P10,0) -> 0 | AE10: =IFERROR(Z10*$P10,0) -> 0 | AF10: =IFERROR(AA10*$P10,0) -> 0 | AG10: =IFERROR(AB10*$P10,0) -> 100000 | AH10: =SUM(AC10:AG10) -> 100000 | AI10: Exit Plan EP-01 pending | AJ10: Partner-estimated | AK10: Optional year-5 transition package; excludes extraordinary data migration or third-party termination fees. Shared allocation: one portfolio exit package in Year 5. Pricing validity: planning benchmark only; commercial proposal and contracted terms pending.
A11: CL-007 | B11: Shared | C11: Expected case | D11: Agent discovery, design and onboarding | E11: Implementation | F11: One-time | G11: Per agent | H11: Partner | I11: Implementation package | J11: Development, Test, Production | K11: 10 | L11: agents | M11: 45000 | N11: 0 | O11: 0 | P11: =IF(OR(M11="",M11=0),0,M11*(1-N11)*(1+O11)) -> 45000 | Q11: One-time | R11: 12 | S11: 0 | T11: USD | U11: US benchmark | V11: 46298 | W11: Separately priced | X11: 10 | Y11: 0 | Z11: 0 | AA11: 0 | AB11: 0 | AC11: =IFERROR(X11*$P11,0) -> 450000 | AD11: =IFERROR(Y11*$P11,0) -> 0 | AE11: =IFERROR(Z11*$P11,0) -> 0 | AF11: =IFERROR(AA11*$P11,0) -> 0 | AG11: =IFERROR(AB11*$P11,0) -> 0 | AH11: =SUM(AC11:AG11) -> 450000 | AI11: Commercial Workbook CW-01; Statement of Work pending | AJ11: Partner-estimated | AK11: One charge per deployed agent; excludes third-party licenses and customer remediation work. Shared allocation: quantity equals agents deployed in the scenario. Pricing validity: planning benchmark only; commercial proposal and contracted terms pending.
A12: CL-008 | B12: Shared | C12: Expected case | D12: Managed AI and Agent Operations | E12: Managed service | F12: Recurring fixed | G12: Per hour | H12: Partner | I12: Blended delivery team | J12: Production | K12: 15600 | L12: hours | M12: 57.69 | N12: 0 | O12: 0 | P12: =IF(OR(M12="",M12=0),0,M12*(1-N12)*(1+O12)) -> 57.69 | Q12: Annual | R12: 60 | S12: 0.03 | T12: USD | U12: US benchmark | V12: 46298 | W12: Separately priced | X12: 15600 | Y12: 16068 | Z12: 16550.04 | AA12: 17046.541 | AB12: 17557.937 | AC12: =IFERROR(X12*$P12,0) -> 899964 | AD12: =IFERROR(Y12*$P12,0) -> 926962.92 | AE12: =IFERROR(Z12*$P12,0) -> 954771.81 | AF12: =IFERROR(AA12*$P12,0) -> 983414.96 | AG12: =IFERROR(AB12*$P12,0) -> 1012917.4 | AH12: =SUM(AC12:AG12) -> 4778031.1 | AI12: Staffing model SM-01; rate card pending | AJ12: Partner-estimated | AK12: 7.5-FTE expected-case baseline; annual quantity includes 3% escalation and is the sole labor cost line. Shared allocation: operator hours scale with the scenario workload factor. Pricing validity: planning benchmark only; commercial proposal and contracted terms pending.
A13: CL-009 | B13: Shared | C13: Expected case | D13: Azure platform shared services | E13: Platform | F13: Recurring fixed | G13: Other(s) | H13: Microsoft Azure | I13: AKS, data and integration bundle | J13: Shared | K13: 12 | L13: months | M13: 2400 | N13: 0 | O13: 0 | P13: =IF(OR(M13="",M13=0),0,M13*(1-N13)*(1+O13)) -> 2400 | Q13: Monthly | R13: 60 | S13: 0.03 | T13: USD | U13: US benchmark | V13: 46298 | W13: Pass-through | X13: 12 | Y13: 12.36 | Z13: 12.7308 | AA13: 13.112724 | AB13: 13.506106 | AC13: =IFERROR(X13*$P13,0) -> 28800 | AD13: =IFERROR(Y13*$P13,0) -> 29664 | AE13: =IFERROR(Z13*$P13,0) -> 30553.92 | AF13: =IFERROR(AA13*$P13,0) -> 31470.538 | AG13: =IFERROR(AB13*$P13,0) -> 32414.654 | AH13: =SUM(AC13:AG13) -> 152903.11 | AI13: Architecture Pack AP-00; Azure estimate pending | AJ13: Partner-estimated | AK13: Shared platform allocation by scenario load; Unit_Costs is supporting detail, not an additional charge. Shared allocation: monthly shared platform charge scales with scenario load. Pricing validity: planning benchmark only; commercial proposal and contracted terms pending.
A14: CL-010 | B14: Shared | C14: Expected case | D14: LLM inference consumption | E14: AI services | F14: Recurring variable | G14: Consumption-based | H14: Microsoft Azure | I14: GPT-4.1 / GPT-4.1 mini blend | J14: Production | K14: 1400 | L14: million tokens | M14: 1.25 | N14: 0 | O14: 0 | P14: =IF(OR(M14="",M14=0),0,M14*(1-N14)*(1+O14)) -> 1.25 | Q14: Usage-based | R14: 60 | S14: 0 | T14: USD | U14: US benchmark | V14: 46298 | W14: Pass-through | X14: 1400 | Y14: 1540 | Z14: 1694 | AA14: 1863.4 | AB14: 2049.74 | AC14: =IFERROR(X14*$P14,0) -> 1750 | AD14: =IFERROR(Y14*$P14,0) -> 1925 | AE14: =IFERROR(Z14*$P14,0) -> 2117.5 | AF14: =IFERROR(AA14*$P14,0) -> 2329.25 | AG14: =IFERROR(AB14*$P14,0) -> 2562.175 | AH14: =SUM(AC14:AG14) -> 10683.925 | AI14: OpenAI public API pricing benchmark; Azure rate pending | AJ14: List price | AK14: Blended token rate for planning only; replace with Azure AI Foundry contracted rates and measured routing mix. Shared allocation: token quantity scales with scenario AI consumption. Pricing validity: planning benchmark only; commercial proposal and contracted terms pending.
A15: CL-011 | B15: Shared | C15: Expected case | D15: Observability, dashboards and reporting | E15: Observability | F15: Recurring fixed | G15: Other(s) | H15: Partner / Microsoft | I15: Managed observability bundle | J15: Production | K15: 12 | L15: months | M15: 3000 | N15: 0 | O15: 0 | P15: =IF(OR(M15="",M15=0),0,M15*(1-N15)*(1+O15)) -> 3000 | Q15: Monthly | R15: 60 | S15: 0.03 | T15: USD | U15: US benchmark | V15: 46298 | W15: Separately priced | X15: 12 | Y15: 12.36 | Z15: 12.7308 | AA15: 13.112724 | AB15: 13.506106 | AC15: =IFERROR(X15*$P15,0) -> 36000 | AD15: =IFERROR(Y15*$P15,0) -> 37080 | AE15: =IFERROR(Z15*$P15,0) -> 38192.4 | AF15: =IFERROR(AA15*$P15,0) -> 39338.172 | AG15: =IFERROR(AB15*$P15,0) -> 40518.317 | AH15: =SUM(AC15:AG15) -> 191128.89 | AI15: Operations Model OM-01; license validation pending | AJ15: Partner-estimated | AK15: Includes dashboard operations; Power BI licenses assumed available separately where already entitled. Shared allocation: managed observability charge scales with scenario load. Pricing validity: planning benchmark only; commercial proposal and contracted terms pending.
A16: CL-012 | B16: Shared | C16: Expected case | D16: Exit transition and knowledge transfer | E16: Exit | F16: Exit-related | G16: Separate project | H16: Partner | I16: Exit package | J16: Production | K16: 1 | L16: package | M16: 100000 | N16: 0 | O16: 0 | P16: =IF(OR(M16="",M16=0),0,M16*(1-N16)*(1+O16)) -> 100000 | Q16: One-time | R16: 60 | S16: 0 | T16: USD | U16: US benchmark | V16: 46298 | W16: Optional | X16: 0 | Y16: 0 | Z16: 0 | AA16: 0 | AB16: 1 | AC16: =IFERROR(X16*$P16,0) -> 0 | AD16: =IFERROR(Y16*$P16,0) -> 0 | AE16: =IFERROR(Z16*$P16,0) -> 0 | AF16: =IFERROR(AA16*$P16,0) -> 0 | AG16: =IFERROR(AB16*$P16,0) -> 100000 | AH16: =SUM(AC16:AG16) -> 100000 | AI16: Exit Plan EP-01 pending | AJ16: Partner-estimated | AK16: Optional year-5 transition package; excludes extraordinary data migration or third-party termination fees. Shared allocation: one portfolio exit package in Year 5. Pricing validity: planning benchmark only; commercial proposal and contracted terms pending.
... A34: CL-030 | B34: Shared | C34: PepsiCo standard | D34: Exit transition and knowledge transfer | E34: Exit | F34: Exit-related | G34: Separate project | H34: Partner | I34: Exit package | J34: Production | K34: 1 | L34: package | M34: 100000 | N34: 0 | O34: 0 | P34: =IF(OR(M34="",M34=0),0,M34*(1-N34)*(1+O34)) -> 100000 | Q34: One-time | R34: 60 | S34: 0 | T34: USD | U34: US benchmark | V34: 46298 | W34: Optional | X34: 0 | Y34: 0 | Z34: 0 | AA34: 0 | AB34: 1 | AC34: =IFERROR(X34*$P34,0) -> 0 | AD34: =IFERROR(Y34*$P34,0) -> 0 | AE34: =IFERROR(Z34*$P34,0) -> 0 | AF34: =IFERROR(AA34*$P34,0) -> 0 | AG34: =IFERROR(AB34*$P34,0) -> 100000 | AH34: =SUM(AC34:AG34) -> 100000 | AI34: Exit Plan EP-01 pending | AJ34: Assumption requiring validation | AK34: Optional year-5 transition package; excludes extraordinary data migration or third-party termination fees. Shared allocation: one portfolio exit package in Year 5. Pricing validity: planning benchmark only; commercial proposal and contracted terms pending.
P35: =IF(OR(M35="",M35=0),0,M35*(1-N35)*(1+O35)) -> 0 | AC35: =IFERROR(X35*$P35,0) -> 0 | AD35: =IFERROR(Y35*$P35,0) -> 0 | AE35: =IFERROR(Z35*$P35,0) -> 0 | AF35: =IFERROR(AA35*$P35,0) -> 0 | AG35: =IFERROR(AB35*$P35,0) -> 0 | AH35: =SUM(AC35:AG35) -> 0
P36: =IF(OR(M36="",M36=0),0,M36*(1-N36)*(1+O36)) -> 0 | AC36: =IFERROR(X36*$P36,0) -> 0 | AD36: =IFERROR(Y36*$P36,0) -> 0 | AE36: =IFERROR(Z36*$P36,0) -> 0 | AF36: =IFERROR(AA36*$P36,0) -> 0 | AG36: =IFERROR(AB36*$P36,0) -> 0 | AH36: =SUM(AC36:AG36) -> 0
P37: =IF(OR(M37="",M37=0),0,M37*(1-N37)*(1+O37)) -> 0 | AC37: =IFERROR(X37*$P37,0) -> 0 | AD37: =IFERROR(Y37*$P37,0) -> 0 | AE37: =IFERROR(Z37*$P37,0) -> 0 | AF37: =IFERROR(AA37*$P37,0) -> 0 | AG37: =IFERROR(AB37*$P37,0) -> 0 | AH37: =SUM(AC37:AG37) -> 0
P38: =IF(OR(M38="",M38=0),0,M38*(1-N38)*(1+O38)) -> 0 | AC38: =IFERROR(X38*$P38,0) -> 0 | AD38: =IFERROR(Y38*$P38,0) -> 0 | AE38: =IFERROR(Z38*$P38,0) -> 0 | AF38: =IFERROR(AA38*$P38,0) -> 0 | AG38: =IFERROR(AB38*$P38,0) -> 0 | AH38: =SUM(AC38:AG38) -> 0
P39: =IF(OR(M39="",M39=0),0,M39*(1-N39)*(1+O39)) -> 0 | AC39: =IFERROR(X39*$P39,0) -> 0 | AD39: =IFERROR(Y39*$P39,0) -> 0 | AE39: =IFERROR(Z39*$P39,0) -> 0 | AF39: =IFERROR(AA39*$P39,0) -> 0 | AG39: =IFERROR(AB39*$P39,0) -> 0 | AH39: =SUM(AC39:AG39) -> 0
P40: =IF(OR(M40="",M40=0),0,M40*(1-N40)*(1+O40)) -> 0 | AC40: =IFERROR(X40*$P40,0) -> 0 | AD40: =IFERROR(Y40*$P40,0) -> 0 | AE40: =IFERROR(Z40*$P40,0) -> 0 | AF40: =IFERROR(AA40*$P40,0) -> 0 | AG40: =IFERROR(AB40*$P40,0) -> 0 | AH40: =SUM(AC40:AG40) -> 0
P41: =IF(OR(M41="",M41=0),0,M41*(1-N41)*(1+O41)) -> 0 | AC41: =IFERROR(X41*$P41,0) -> 0 | AD41: =IFERROR(Y41*$P41,0) -> 0 | AE41: =IFERROR(Z41*$P41,0) -> 0 | AF41: =IFERROR(AA41*$P41,0) -> 0 | AG41: =IFERROR(AB41*$P41,0) -> 0 | AH41: =SUM(AC41:AG41) -> 0
P42: =IF(OR(M42="",M42=0),0,M42*(1-N42)*(1+O42)) -> 0 | AC42: =IFERROR(X42*$P42,0) -> 0 | AD42: =IFERROR(Y42*$P42,0) -> 0 | AE42: =IFERROR(Z42*$P42,0) -> 0 | AF42: =IFERROR(AA42*$P42,0) -> 0 | AG42: =IFERROR(AB42*$P42,0) -> 0 | AH42: =SUM(AC42:AG42) -> 0
P43: =IF(OR(M43="",M43=0),0,M43*(1-N43)*(1+O43)) -> 0 | AC43: =IFERROR(X43*$P43,0) -> 0 | AD43: =IFERROR(Y43*$P43,0) -> 0 | AE43: =IFERROR(Z43*$P43,0) -> 0 | AF43: =IFERROR(AA43*$P43,0) -> 0 | AG43: =IFERROR(AB43*$P43,0) -> 0 | AH43: =SUM(AC43:AG43) -> 0
P44: =IF(OR(M44="",M44=0),0,M44*(1-N44)*(1+O44)) -> 0 | AC44: =IFERROR(X44*$P44,0) -> 0 | AD44: =IFERROR(Y44*$P44,0) -> 0 | AE44: =IFERROR(Z44*$P44,0) -> 0 | AF44: =IFERROR(AA44*$P44,0) -> 0 | AG44: =IFERROR(AB44*$P44,0) -> 0 | AH44: =SUM(AC44:AG44) -> 0
P45: =IF(OR(M45="",M45=0),0,M45*(1-N45)*(1+O45)) -> 0 | AC45: =IFERROR(X45*$P45,0) -> 0 | AD45: =IFERROR(Y45*$P45,0) -> 0 | AE45: =IFERROR(Z45*$P45,0) -> 0 | AF45: =IFERROR(AA45*$P45,0) -> 0 | AG45: =IFERROR(AB45*$P45,0) -> 0 | AH45: =SUM(AC45:AG45) -> 0
P46: =IF(OR(M46="",M46=0),0,M46*(1-N46)*(1+O46)) -> 0 | AC46: =IFERROR(X46*$P46,0) -> 0 | AD46: =IFERROR(Y46*$P46,0) -> 0 | AE46: =IFERROR(Z46*$P46,0) -> 0 | AF46: =IFERROR(AA46*$P46,0) -> 0 | AG46: =IFERROR(AB46*$P46,0) -> 0 | AH46: =SUM(AC46:AG46) -> 0
... P504: =IF(OR(M504="",M504=0),0,M504*(1-N504)*(1+O504)) -> 0 | AC504: =IFERROR(X504*$P504,0) -> 0 | AD504: =IFERROR(Y504*$P504,0) -> 0 | AE504: =IFERROR(Z504*$P504,0) -> 0 | AF504: =IFERROR(AA504*$P504,0) -> 0 | AG504: =IFERROR(AB504*$P504,0) -> 0 | AH504: =SUM(AC504:AG504) -> 0

Sheet Infra_Sizing
A1: Partner Model For Agent Cost Estimation
A2: Infrastructure Sizing & Baseline Inputs | J2: BIDDER INPUT: Complete baseline capacity, fixed platform services, and networking/security overhead. Include only in-scope environments and avoid double counting.
A4: Baseline platform volumes (editable)
A5: ADLS baseline storage (GB) | B5: 500
A6: Postgres extra storage growth (GB per 1,000 tickets) | B6: 0.15
A7: Azure Container Registry + artifacts fixed $/month | B7: 150
A8: API Management / gateway fixed $/month | B8: 700
A9: Service Bus / Event Hubs fixed $/month | B9: 250
A10: Key Vault + secrets fixed $/month | B10: 100
A11: Azure Monitor / Log Analytics fixed $/month | B11: 800
A12: Networking & security overhead (% of Azure compute+data) | B12: 0.12
A14: Derived sizing (read‑only)
A15: AKS nodes needed (from monthly model) | B15: =MAX(Model_Monthly!C52:'Model_Monthly'!T52) -> 2

Sheet Staffing
A1: Staffing (Optional) – Operator Team
H2: BIDDER INPUT IF IN SCOPE: Enter total operator FTEs, loaded annual cost, and pod allocation. If staffing is excluded, keep cost at zero and document the exclusion.
A3: Team structure (editable)
A4: Total operator FTEs | B4: 7.5
A5: Loaded cost per FTE per year ($) | B5: 120000
A7: Pod | B7: FTEs | C7: Role focus
A8: AI & Agent Ops | B8: 2.5 | C8: Agent runtime, prompt/skill ops, safe-guarding
A9: Automation | B9: 2 | C9: Scripted automations, runbooks, orchestration
A10: Observability | B10: 1.5 | C10: Dashboards, logging, alerting, SRE practices
A11: ServiceNow | B11: 1.5 | C11: Incident/request flows, catalog, knowledge mgmt
A12: Total | B12: =SUM(B8:B11) -> 7.5
A14: Derived cost (read‑only)
A15: Monthly staffing cost | B15: =$B$4*$B$5/12 -> 75000

Sheet Benefits
A1: AMS RFP | Business Value & Productivity
A2: BIDDER INPUT: One row per Agent ID, scenario and measurable outcome. Document baseline, formula, dependencies and evidence. Do not double count overlapping benefits.
A4: Benefit ID* | B4: Agent ID* | C4: Scenario* | D4: KPI / Outcome* | E4: Baseline Value* | F4: Baseline Unit* | G4: Baseline Date / Source* | H4: Target Value* | I4: Target Unit* | J4: Benefit Formula / Method* | K4: Monthly Volume | L4: Hours Released | M4: Capacity Avoided (FTE) | N4: Cashable Savings Y1 | O4: Noncashable Productivity Y1 | P4: Cost Avoidance Y1 | Q4: One-time Benefit | R4: Recurring Benefit Y1 | S4: Confidence* | T4: Commitment Level* | U4: Measurement System* | V4: Frequency* | W4: Accountable Owner* | X4: Acceptance Threshold | Y4: Dependency / PepsiCo Action | Z4: Overlap / Attribution Control | AA4: Evidence Reference* | AB4: Notes
A5: BEN-001 | B5: AIA-001 | C5: Minimum adoption | D5: Incident handling time | E5: 18 | F5: minutes per unit | G5: Partner benchmark; baseline validation pending | H5: 12 | I5: minutes per unit | J5: Annual hours = monthly in-scope volume × (baseline minutes − target minutes) ÷ 60 × 12 | K5: 3000 | L5: =IFERROR(K5*(E5-H5)/60*12,0) -> 3600 | M5: =IFERROR(L5/(8*21*12),0) -> 1.7857143 | N5: 0 | O5: =L5*50 -> 180000 | P5: 0 | Q5: 0 | R5: =SUM(N5:P5) -> 180000 | S5: Estimated | T5: Target | U5: Source-system timestamps | V5: Monthly | W5: Joint | X5: Target ≤ 12 minutes after 3 stable months | Y5: PepsiCo to provide 12 months of clean volume and timestamp history | Z5: One benefit owner per Agent ID; exclude overlapping incident, problem and staffing claims | AA5: Benefit Model BM-01; source-system extract pending | AB5: Non-cashable productivity only until finance validates redeployment or avoided hiring.
A6: BEN-002 | B6: AIA-001 | C6: Expected case | D6: Incident handling time | E6: 18 | F6: minutes per unit | G6: Partner benchmark; baseline validation pending | H6: 12 | I6: minutes per unit | J6: Annual hours = monthly in-scope volume × (baseline minutes − target minutes) ÷ 60 × 12 | K6: 7200 | L6: =IFERROR(K6*(E6-H6)/60*12,0) -> 8640 | M6: =IFERROR(L6/(8*21*12),0) -> 4.2857143 | N6: 0 | O6: =L6*50 -> 432000 | P6: 0 | Q6: 0 | R6: =SUM(N6:P6) -> 432000 | S6: Estimated | T6: Target | U6: Source-system timestamps | V6: Monthly | W6: Joint | X6: Target ≤ 12 minutes after 3 stable months | Y6: PepsiCo to provide 12 months of clean volume and timestamp history | Z6: One benefit owner per Agent ID; exclude overlapping incident, problem and staffing claims | AA6: Benefit Model BM-01; source-system extract pending | AB6: Non-cashable productivity only until finance validates redeployment or avoided hiring.
A7: BEN-003 | B7: AIA-001 | C7: High adoption | D7: Incident handling time | E7: 18 | F7: minutes per unit | G7: Partner benchmark; baseline validation pending | H7: 12 | I7: minutes per unit | J7: Annual hours = monthly in-scope volume × (baseline minutes − target minutes) ÷ 60 × 12 | K7: 9600 | L7: =IFERROR(K7*(E7-H7)/60*12,0) -> 11520 | M7: =IFERROR(L7/(8*21*12),0) -> 5.7142857 | N7: 0 | O7: =L7*50 -> 576000 | P7: 0 | Q7: 0 | R7: =SUM(N7:P7) -> 576000 | S7: Estimated | T7: Target | U7: Source-system timestamps | V7: Monthly | W7: Joint | X7: Target ≤ 12 minutes after 3 stable months | Y7: PepsiCo to provide 12 months of clean volume and timestamp history | Z7: One benefit owner per Agent ID; exclude overlapping incident, problem and staffing claims | AA7: Benefit Model BM-01; source-system extract pending | AB7: Non-cashable productivity only until finance validates redeployment or avoided hiring.
A8: BEN-004 | B8: AIA-001 | C8: Peak/stress case | D8: Incident handling time | E8: 18 | F8: minutes per unit | G8: Partner benchmark; baseline validation pending | H8: 12 | I8: minutes per unit | J8: Annual hours = monthly in-scope volume × (baseline minutes − target minutes) ÷ 60 × 12 | K8: 10800 | L8: =IFERROR(K8*(E8-H8)/60*12,0) -> 12960 | M8: =IFERROR(L8/(8*21*12),0) -> 6.4285714 | N8: 0 | O8: =L8*50 -> 648000 | P8: 0 | Q8: 0 | R8: =SUM(N8:P8) -> 648000 | S8: Estimated | T8: Target | U8: Source-system timestamps | V8: Monthly | W8: Joint | X8: Target ≤ 12 minutes after 3 stable months | Y8: PepsiCo to provide 12 months of clean volume and timestamp history | Z8: One benefit owner per Agent ID; exclude overlapping incident, problem and staffing claims | AA8: Benefit Model BM-01; source-system extract pending | AB8: Non-cashable productivity only until finance validates redeployment or avoided hiring.
A9: BEN-005 | B9: AIA-001 | C9: PepsiCo standard | D9: Incident handling time | E9: 18 | F9: minutes per unit | G9: Partner benchmark; baseline validation pending | H9: 12 | I9: minutes per unit | J9: Annual hours = monthly in-scope volume × (baseline minutes − target minutes) ÷ 60 × 12 | K9: 7800 | L9: =IFERROR(K9*(E9-H9)/60*12,0) -> 9360 | M9: =IFERROR(L9/(8*21*12),0) -> 4.6428571 | N9: 0 | O9: =L9*50 -> 468000 | P9: 0 | Q9: 0 | R9: =SUM(N9:P9) -> 468000 | S9: Estimated | T9: Target | U9: Source-system timestamps | V9: Monthly | W9: Joint | X9: Target ≤ 12 minutes after 3 stable months | Y9: PepsiCo to provide 12 months of clean volume and timestamp history | Z9: One benefit owner per Agent ID; exclude overlapping incident, problem and staffing claims | AA9: Benefit Model BM-01; source-system extract pending | AB9: Non-cashable productivity only until finance validates redeployment or avoided hiring.
A10: BEN-006 | B10: AIA-002 | C10: Minimum adoption | D10: Remediation elapsed time | E10: 55 | F10: minutes per unit | G10: Partner benchmark; baseline validation pending | H10: 25 | I10: minutes per unit | J10: Annual hours = monthly in-scope volume × (baseline minutes − target minutes) ÷ 60 × 12 | K10: 975 | L10: =IFERROR(K10*(E10-H10)/60*12,0) -> 5850 | M10: =IFERROR(L10/(8*21*12),0) -> 2.9017857 | N10: 0 | O10: =L10*50 -> 292500 | P10: 0 | Q10: 0 | R10: =SUM(N10:P10) -> 292500 | S10: Estimated | T10: Target | U10: Source-system timestamps | V10: Monthly | W10: Joint | X10: Target ≤ 25 minutes after 3 stable months | Y10: PepsiCo to provide 12 months of clean volume and timestamp history | Z10: One benefit owner per Agent ID; exclude overlapping incident, problem and staffing claims | AA10: Benefit Model BM-01; source-system extract pending | AB10: Non-cashable productivity only until finance validates redeployment or avoided hiring.
A11: BEN-007 | B11: AIA-002 | C11: Expected case | D11: Remediation elapsed time | E11: 55 | F11: minutes per unit | G11: Partner benchmark; baseline validation pending | H11: 25 | I11: minutes per unit | J11: Annual hours = monthly in-scope volume × (baseline minutes − target minutes) ÷ 60 × 12 | K11: 2340 | L11: =IFERROR(K11*(E11-H11)/60*12,0) -> 14040 | M11: =IFERROR(L11/(8*21*12),0) -> 6.9642857 | N11: 0 | O11: =L11*50 -> 702000 | P11: 0 | Q11: 0 | R11: =SUM(N11:P11) -> 702000 | S11: Estimated | T11: Target | U11: Source-system timestamps | V11: Monthly | W11: Joint | X11: Target ≤ 25 minutes after 3 stable months | Y11: PepsiCo to provide 12 months of clean volume and timestamp history | Z11: One benefit owner per Agent ID; exclude overlapping incident, problem and staffing claims | AA11: Benefit Model BM-01; source-system extract pending | AB11: Non-cashable productivity only until finance validates redeployment or avoided hiring.
A12: BEN-008 | B12: AIA-002 | C12: High adoption | D12: Remediation elapsed time | E12: 55 | F12: minutes per unit | G12: Partner benchmark; baseline validation pending | H12: 25 | I12: minutes per unit | J12: Annual hours = monthly in-scope volume × (baseline minutes − target minutes) ÷ 60 × 12 | K12: 3120 | L12: =IFERROR(K12*(E12-H12)/60*12,0) -> 18720 | M12: =IFERROR(L12/(8*21*12),0) -> 9.2857143 | N12: 0 | O12: =L12*50 -> 936000 | P12: 0 | Q12: 0 | R12: =SUM(N12:P12) -> 936000 | S12: Estimated | T12: Target | U12: Source-system timestamps | V12: Monthly | W12: Joint | X12: Target ≤ 25 minutes after 3 stable months | Y12: PepsiCo to provide 12 months of clean volume and timestamp history | Z12: One benefit owner per Agent ID; exclude overlapping incident, problem and staffing claims | AA12: Benefit Model BM-01; source-system extract pending | AB12: Non-cashable productivity only until finance validates redeployment or avoided hiring.
A13: BEN-009 | B13: AIA-002 | C13: Peak/stress case | D13: Remediation elapsed time | E13: 55 | F13: minutes per unit | G13: Partner benchmark; baseline validation pending | H13: 25 | I13: minutes per unit | J13: Annual hours = monthly in-scope volume × (baseline minutes − target minutes) ÷ 60 × 12 | K13: 3510 | L13: =IFERROR(K13*(E13-H13)/60*12,0) -> 21060 | M13: =IFERROR(L13/(8*21*12),0) -> 10.446429 | N13: 0 | O13: =L13*50 -> 1053000 | P13: 0 | Q13: 0 | R13: =SUM(N13:P13) -> 1053000 | S13: Estimated | T13: Target | U13: Source-system timestamps | V13: Monthly | W13: Joint | X13: Target ≤ 25 minutes after 3 stable months | Y13: PepsiCo to provide 12 months of clean volume and timestamp history | Z13: One benefit owner per Agent ID; exclude overlapping incident, problem and staffing claims | AA13: Benefit Model BM-01; source-system extract pending | AB13: Non-cashable productivity only until finance validates redeployment or avoided hiring.
A14: BEN-010 | B14: AIA-002 | C14: PepsiCo standard | D14: Remediation elapsed time | E14: 55 | F14: minutes per unit | G14: Partner benchmark; baseline validation pending | H14: 25 | I14: minutes per unit | J14: Annual hours = monthly in-scope volume × (baseline minutes − target minutes) ÷ 60 × 12 | K14: 2535 | L14: =IFERROR(K14*(E14-H14)/60*12,0) -> 15210 | M14: =IFERROR(L14/(8*21*12),0) -> 7.5446429 | N14: 0 | O14: =L14*50 -> 760500 | P14: 0 | Q14: 0 | R14: =SUM(N14:P14) -> 760500 | S14: Estimated | T14: Target | U14: Source-system timestamps | V14: Monthly | W14: Joint | X14: Target ≤ 25 minutes after 3 stable months | Y14: PepsiCo to provide 12 months of clean volume and timestamp history | Z14: One benefit owner per Agent ID; exclude overlapping incident, problem and staffing claims | AA14: Benefit Model BM-01; source-system extract pending | AB14: Non-cashable productivity only until finance validates redeployment or avoided hiring.
A15: BEN-011 | B15: AIA-003 | C15: Minimum adoption | D15: Knowledge resolution time | E15: 15 | F15: minutes per unit | G15: Partner benchmark; baseline validation pending | H15: 7 | I15: minutes per unit | J15: Annual hours = monthly in-scope volume × (baseline minutes − target minutes) ÷ 60 × 12 | K15: 1800 | L15: =IFERROR(K15*(E15-H15)/60*12,0) -> 2880 | M15: =IFERROR(L15/(8*21*12),0) -> 1.4285714 | N15: 0 | O15: =L15*50 -> 144000 | P15: 0 | Q15: 0 | R15: =SUM(N15:P15) -> 144000 | S15: Estimated | T15: Target | U15: Source-system timestamps | V15: Monthly | W15: Joint | X15: Target ≤ 7 minutes after 3 stable months | Y15: PepsiCo to provide 12 months of clean volume and timestamp history | Z15: One benefit owner per Agent ID; exclude overlapping incident, problem and staffing claims | AA15: Benefit Model BM-01; source-system extract pending | AB15: Non-cashable productivity only until finance validates redeployment or avoided hiring.
A16: BEN-012 | B16: AIA-003 | C16: Expected case | D16: Knowledge resolution time | E16: 15 | F16: minutes per unit | G16: Partner benchmark; baseline validation pending | H16: 7 | I16: minutes per unit | J16: Annual hours = monthly in-scope volume × (baseline minutes − target minutes) ÷ 60 × 12 | K16: 4320 | L16: =IFERROR(K16*(E16-H16)/60*12,0) -> 6912 | M16: =IFERROR(L16/(8*21*12),0) -> 3.4285714 | N16: 0 | O16: =L16*50 -> 345600 | P16: 0 | Q16: 0 | R16: =SUM(N16:P16) -> 345600 | S16: Estimated | T16: Target | U16: Source-system timestamps | V16: Monthly | W16: Joint | X16: Target ≤ 7 minutes after 3 stable months | Y16: PepsiCo to provide 12 months of clean volume and timestamp history | Z16: One benefit owner per Agent ID; exclude overlapping incident, problem and staffing claims | AA16: Benefit Model BM-01; source-system extract pending | AB16: Non-cashable productivity only until finance validates redeployment or avoided hiring.
... A54: BEN-050 | B54: AIA-010 | C54: PepsiCo standard | D54: Access request handling time | E54: 30 | F54: minutes per unit | G54: Partner benchmark; baseline validation pending | H54: 15 | I54: minutes per unit | J54: Annual hours = monthly in-scope volume × (baseline minutes − target minutes) ÷ 60 × 12 | K54: 2600 | L54: =IFERROR(K54*(E54-H54)/60*12,0) -> 7800 | M54: =IFERROR(L54/(8*21*12),0) -> 3.8690476 | N54: 0 | O54: =L54*50 -> 390000 | P54: 0 | Q54: 0 | R54: =SUM(N54:P54) -> 390000 | S54: Estimated | T54: Target | U54: Source-system timestamps | V54: Monthly | W54: Joint | X54: Target ≤ 15 minutes after 3 stable months | Y54: PepsiCo to provide 12 months of clean volume and timestamp history | Z54: One benefit owner per Agent ID; exclude overlapping incident, problem and staffing claims | AA54: Benefit Model BM-01; source-system extract pending | AB54: Non-cashable productivity only until finance validates redeployment or avoided hiring.
L55: =IFERROR(K55*(E55-H55)/60*12,0) -> 0 | M55: =IFERROR(L55/(8*21*12),0) -> 0 | O55: =L55*50 -> 0 | R55: =SUM(N55:P55) -> 0
L56: =IFERROR(K56*(E56-H56)/60*12,0) -> 0 | M56: =IFERROR(L56/(8*21*12),0) -> 0 | O56: =L56*50 -> 0 | R56: =SUM(N56:P56) -> 0
L57: =IFERROR(K57*(E57-H57)/60*12,0) -> 0 | M57: =IFERROR(L57/(8*21*12),0) -> 0 | O57: =L57*50 -> 0 | R57: =SUM(N57:P57) -> 0
L58: =IFERROR(K58*(E58-H58)/60*12,0) -> 0 | M58: =IFERROR(L58/(8*21*12),0) -> 0 | O58: =L58*50 -> 0 | R58: =SUM(N58:P58) -> 0
L59: =IFERROR(K59*(E59-H59)/60*12,0) -> 0 | M59: =IFERROR(L59/(8*21*12),0) -> 0 | O59: =L59*50 -> 0 | R59: =SUM(N59:P59) -> 0
L60: =IFERROR(K60*(E60-H60)/60*12,0) -> 0 | M60: =IFERROR(L60/(8*21*12),0) -> 0 | O60: =L60*50 -> 0 | R60: =SUM(N60:P60) -> 0
L61: =IFERROR(K61*(E61-H61)/60*12,0) -> 0 | M61: =IFERROR(L61/(8*21*12),0) -> 0 | O61: =L61*50 -> 0 | R61: =SUM(N61:P61) -> 0
L62: =IFERROR(K62*(E62-H62)/60*12,0) -> 0 | M62: =IFERROR(L62/(8*21*12),0) -> 0 | O62: =L62*50 -> 0 | R62: =SUM(N62:P62) -> 0
L63: =IFERROR(K63*(E63-H63)/60*12,0) -> 0 | M63: =IFERROR(L63/(8*21*12),0) -> 0 | O63: =L63*50 -> 0 | R63: =SUM(N63:P63) -> 0
L64: =IFERROR(K64*(E64-H64)/60*12,0) -> 0 | M64: =IFERROR(L64/(8*21*12),0) -> 0 | O64: =L64*50 -> 0 | R64: =SUM(N64:P64) -> 0
L65: =IFERROR(K65*(E65-H65)/60*12,0) -> 0 | M65: =IFERROR(L65/(8*21*12),0) -> 0 | O65: =L65*50 -> 0 | R65: =SUM(N65:P65) -> 0
L66: =IFERROR(K66*(E66-H66)/60*12,0) -> 0 | M66: =IFERROR(L66/(8*21*12),0) -> 0 | O66: =L66*50 -> 0 | R66: =SUM(N66:P66) -> 0
... L304: =IFERROR(K304*(E304-H304)/60*12,0) -> 0 | M304: =IFERROR(L304/(8*21*12),0) -> 0 | O304: =L304*50 -> 0 | R304: =SUM(N304:P304) -> 0

Sheet LLM_Calc
A1: Partner Model For Agent Cost Estimation
A2: LLM Usage & Cost Calculator (linked to monthly model) | J2: REVIEW ONLY: Formula-driven LLM usage and cost view. Do not overwrite. Confirm selected-month outputs align with Assumptions and Model_Monthly.
A4: Per‑ticket assumptions (from Assumptions tab)
A5: Small calls per ticket | B5: =Assumptions!$B$25 -> 2
A6: Large calls per ticket | B6: =Assumptions!$B$26 -> 0.3
A7: Small input tokens per call | B7: =Assumptions!$B$27 -> 1800
A8: Small output tokens per call | B8: =Assumptions!$B$28 -> 350
A9: Large input tokens per call | B9: =Assumptions!$B$29 -> 5000
A10: Large output tokens per call | B10: =Assumptions!$B$30 -> 900
A11: Cache hit rate | B11: =Assumptions!$B$31 -> 0.25
A12: Retrieval/tool overhead per ticket (input tokens) | B12: =Assumptions!$B$32 -> 700
A13: Small input price ($/1M) | B13: =Assumptions!$B$34 -> 0.4
A14: Small output price ($/1M) | B14: =Assumptions!$B$35 -> 1.6
A15: Large input price ($/1M) | B15: =Assumptions!$B$36 -> 2
A16: Large output price ($/1M) | B16: =Assumptions!$B$37 -> 8
A18: Monthly totals (from Model_Monthly)
A19: Metric | B19: Units | C19: Month 1 | D19: Month 6 | E19: Month 12 | F19: Month 18
A20: Tickets (incl reopens) | B20: # | C20: =Model_Monthly!C7 -> 1772.82 | D20: =Model_Monthly!H7 -> 3982.9062 | E20: =Model_Monthly!N7 -> 6687.099 | F20: =Model_Monthly!T7 -> 6876.5719
A21: Small model tokens (in+out) | B21: tokens | C21: =Model_Monthly!C12+Model_Monthly!C13 -> 6958318.5 | D21: =Model_Monthly!H12+Model_Monthly!H13 -> 15632907 | E21: =Model_Monthly!N12+Model_Monthly!N13 -> 26246863 | F21: =Model_Monthly!T12+Model_Monthly!T13 -> 26990545
A22: Large model tokens (in+out) | B22: tokens | C22: =Model_Monthly!C14+Model_Monthly!C15 -> 2473083.9 | D22: =Model_Monthly!H14+Model_Monthly!H15 -> 5556154.2 | E22: =Model_Monthly!N14+Model_Monthly!N15 -> 9328503.1 | F22: =Model_Monthly!T14+Model_Monthly!T15 -> 9592817.9
A23: Total LLM cost | B23: $ | C23: =Model_Monthly!C50 -> 12.090632 | D23: =Model_Monthly!H50 -> 27.163421 | E23: =Model_Monthly!N50 -> 45.606015 | F23: =Model_Monthly!T50 -> 46.898221
A24: Avg LLM cost per ticket | B24: $ / ticket | C24: =IF(Model_Monthly!C7=0,"-",Model_Monthly!C50/Model_Monthly!C7) -> 0.00682 | D24: =IF(Model_Monthly!H7=0,"-",Model_Monthly!H50/Model_Monthly!H7) -> 0.00682 | E24: =IF(Model_Monthly!N7=0,"-",Model_Monthly!N50/Model_Monthly!N7) -> 0.00682 | F24: =IF(Model_Monthly!T7=0,"-",Model_Monthly!T50/Model_Monthly!T7) -> 0.00682

Sheet Observability
A1: Partner Model For Agent Cost Estimation
A2: Observability, Dashboarding & Tools (linked to model) | J2: REVIEW ONLY: Formula-driven observability and BI costs. Do not overwrite. Confirm outputs reconcile to Unit_Costs and monthly demand.
A4: Unit assumptions (from Assumptions tab)
A5: Splunk/log cost ($/GB ingested) | B5: =Unit_Costs!$B$21 -> 2.5
A6: Grafana fixed ($/month) | B6: =Unit_Costs!$B$22 -> 500
A7: Power BI Pro users | B7: =Unit_Costs!$B$23 -> 15
A8: Power BI Pro $/user/month | B8: =Unit_Costs!$B$24 -> 14
A10: Monthly costs (selected months)
A11: Metric | B11: Units | C11: M1 | D11: M6 | E11: M12 | F11: M18
A12: Logs ingested | B12: GB | C12: =Model_Monthly!C66 -> 0.443205 | D12: =Model_Monthly!H66 -> 0.99572656 | E12: =Model_Monthly!N66 -> 1.6717747 | F12: =Model_Monthly!T66 -> 1.719143
A13: Splunk/log cost | B13: $ | C13: =Model_Monthly!C67 -> 1.1080125 | D13: =Model_Monthly!H67 -> 2.4893164 | E13: =Model_Monthly!N67 -> 4.1794369 | F13: =Model_Monthly!T67 -> 4.2978575
A14: Grafana fixed | B14: $ | C14: =Model_Monthly!C68 -> 500 | D14: =Model_Monthly!H68 -> 500 | E14: =Model_Monthly!N68 -> 500 | F14: =Model_Monthly!T68 -> 500
A15: Power BI | B15: $ | C15: =Model_Monthly!C69 -> 210 | D15: =Model_Monthly!H69 -> 210 | E15: =Model_Monthly!N69 -> 210 | F15: =Model_Monthly!T69 -> 210
A16: Total obs & BI | B16: $ | C16: =Model_Monthly!C70 -> 711.10801 | D16: =Model_Monthly!H70 -> 712.48932 | E16: =Model_Monthly!N70 -> 714.17944 | F16: =Model_Monthly!T70 -> 714.29786

Sheet Model_Monthly
A1: PEP DEVX Model For Agent Cost Estimation
A2: Agents & Ticket Volumes | F2: Year1 | G2: Y | L2: Year 2 | P2: Year 3 | T2: Year 4 | U2: Year 5
A3: New agents built (this month) | B3: # | C3: =IFERROR(INDEX(Assumptions!$G$6:$G$11,INT((COLUMN()-3)/3)+1)/INDEX(Assumptions!$H$6:$H$11,INT((COLUMN()-3)/3)+1),0) -> 0.66666667 | D3: =IFERROR(INDEX(Assumptions!$G$6:$G$11,INT((COLUMN()-3)/3)+1)/INDEX(Assumptions!$H$6:$H$11,INT((COLUMN()-3)/3)+1),0) -> 0.66666667 | E3: =IFERROR(INDEX(Assumptions!$G$6:$G$11,INT((COLUMN()-3)/3)+1)/INDEX(Assumptions!$H$6:$H$11,INT((COLUMN()-3)/3)+1),0) -> 0.66666667 | F3: =IFERROR(INDEX(Assumptions!$G$6:$G$11,INT((COLUMN()-3)/3)+1)/INDEX(Assumptions!$H$6:$H$11,INT((COLUMN()-3)/3)+1),0) -> 0.66666667 | G3: =IFERROR(INDEX(Assumptions!$G$6:$G$11,INT((COLUMN()-3)/3)+1)/INDEX(Assumptions!$H$6:$H$11,INT((COLUMN()-3)/3)+1),0) -> 0.66666667 | H3: =IFERROR(INDEX(Assumptions!$G$6:$G$11,INT((COLUMN()-3)/3)+1)/INDEX(Assumptions!$H$6:$H$11,INT((COLUMN()-3)/3)+1),0) -> 0.66666667 | I3: =IFERROR(INDEX(Assumptions!$G$6:$G$11,INT((COLUMN()-3)/3)+1)/INDEX(Assumptions!$H$6:$H$11,INT((COLUMN()-3)/3)+1),0) -> 0.66666667 | J3: =IFERROR(INDEX(Assumptions!$G$6:$G$11,INT((COLUMN()-3)/3)+1)/INDEX(Assumptions!$H$6:$H$11,INT((COLUMN()-3)/3)+1),0) -> 0.66666667 | ... T3: =IFERROR(INDEX(Assumptions!$G$6:$G$11,INT((COLUMN()-3)/3)+1)/INDEX(Assumptions!$H$6:$H$11,INT((COLUMN()-3)/3)+1),0) -> 0 | U3: =T3*(1-Assumptions!$B$16)+U1*Assumptions!$B$13+T1*(Assumptions!$B$14-Assumptions!$B$13)+S1*(Assumptions!$B$15-Assumptions!$B$14) -> 0
A4: Installed agents (end of month) | B4: # | C4: =Assumptions!$B$11*(1-Assumptions!$B$16)+C3 -> 2.6566667 | D4: =C4*(1-Assumptions!$B$16)+D3 -> 3.31005 | E4: =D4*(1-Assumptions!$B$16)+E3 -> 3.9601664 | F4: =E4*(1-Assumptions!$B$16)+F3 -> 4.6070323 | G4: =F4*(1-Assumptions!$B$16)+G3 -> 5.2506638 | H4: =G4*(1-Assumptions!$B$16)+H3 -> 5.8910771 | I4: =H4*(1-Assumptions!$B$16)+I3 -> 6.5282884 | J4: =I4*(1-Assumptions!$B$16)+J3 -> 7.1623136 | K4: =J4*(1-Assumptions!$B$16)+K3 -> 7.7931687 | ... U4: =T4*(1-Assumptions!$B$16)+U3 -> 9.3335639
A5: Active agents (effective) | B5: # | C5: =Assumptions!$B$11+C3*Assumptions!$B$13 -> 2.2333333 | D5: =C5*(1-Assumptions!$B$16)+D3*Assumptions!$B$13+C3*(Assumptions!$B$14-Assumptions!$B$13) -> 2.6888333 | E5: =D5*(1-Assumptions!$B$16)+E3*Assumptions!$B$13+D3*(Assumptions!$B$14-Assumptions!$B$13)+C3*(Assumptions!$B$15-Assumptions!$B$14) -> 3.2753892 | F5: =E5*(1-Assumptions!$B$16)+F3*Assumptions!$B$13+E3*(Assumptions!$B$14-Assumptions!$B$13)+D3*(Assumptions!$B$15-Assumptions!$B$14) -> 3.8590122 | G5: =F5*(1-Assumptions!$B$16)+G3*Assumptions!$B$13+F3*(Assumptions!$B$14-Assumptions!$B$13)+E3*(Assumptions!$B$15-Assumptions!$B$14) -> 4.4397172 | H5: =G5*(1-Assumptions!$B$16)+H3*Assumptions!$B$13+G3*(Assumptions!$B$14-Assumptions!$B$13)+F3*(Assumptions!$B$15-Assumptions!$B$14) -> 5.0175186 | I5: =H5*(1-Assumptions!$B$16)+I3*Assumptions!$B$13+H3*(Assumptions!$B$14-Assumptions!$B$13)+G3*(Assumptions!$B$15-Assumptions!$B$14) -> 5.592431 | J5: =I5*(1-Assumptions!$B$16)+J3*Assumptions!$B$13+I3*(Assumptions!$B$14-Assumptions!$B$13)+H3*(Assumptions!$B$15-Assumptions!$B$14) -> 6.1644688 | K5: =J5*(1-Assumptions!$B$16)+K3*Assumptions!$B$13+J3*(Assumptions!$B$14-Assumptions!$B$13)+I3*(Assumptions!$B$15-Assumptions!$B$14) -> 6.7336465 | L5: =K5*(1-Assumptions!$B$16)+L3*Assumptions!$B$13+K3*(Assumptions!$B$14-Assumptions!$B$13)+J3*(Assumptions!$B$15-Assumptions!$B$14) -> 7.2999782 | ... U5: =T5*(1-Assumptions!$B$16)+U3*Assumptions!$B$13+T3*(Assumptions!$B$14-Assumptions!$B$13)+S3*(Assumptions!$B$15-Assumptions!$B$14) -> 8.6195378
A6: Tickets handled (base) | B6: # | C6: =C5*Assumptions!$B$19*Assumptions!$B$7 -> 1641.5 | D6: =D5*Assumptions!$B$19*Assumptions!$B$7 -> 1976.2925 | E6: =E5*Assumptions!$B$19*Assumptions!$B$7 -> 2407.411 | F6: =F5*Assumptions!$B$19*Assumptions!$B$7 -> 2836.374 | G6: =G5*Assumptions!$B$19*Assumptions!$B$7 -> 3263.1921 | H6: =H5*Assumptions!$B$19*Assumptions!$B$7 -> 3687.8762 | I6: =I5*Assumptions!$B$19*Assumptions!$B$7 -> 4110.4368 | J6: =J5*Assumptions!$B$19*Assumptions!$B$7 -> 4530.8846 | ... U6: =U5*Assumptions!$B$19*Assumptions!$B$7 -> 6335.3603
A7: Tickets incl. reopens/follow‑ups | B7: # | C7: =C6*(1+Assumptions!$B$21) -> 1772.82 | D7: =D6*(1+Assumptions!$B$21) -> 2134.3959 | E7: =E6*(1+Assumptions!$B$21) -> 2600.0039 | F7: =F6*(1+Assumptions!$B$21) -> 3063.2839 | G7: =G6*(1+Assumptions!$B$21) -> 3524.2475 | H7: =H6*(1+Assumptions!$B$21) -> 3982.9062 | I7: =I6*(1+Assumptions!$B$21) -> 4439.2717 | J7: =J6*(1+Assumptions!$B$21) -> 4893.3554 | ... U7: =U6*(1+Assumptions!$B$21) -> 6842.1891
A8: Tickets that are self‑healing (subset) | B8: # | C8: =C7*Assumptions!$B$20 -> 709.128 | D8: =D7*Assumptions!$B$20 -> 853.75836 | E8: =E7*Assumptions!$B$20 -> 1040.0016 | F8: =F7*Assumptions!$B$20 -> 1225.3136 | G8: =G7*Assumptions!$B$20 -> 1409.699 | H8: =H7*Assumptions!$B$20 -> 1593.1625 | I8: =I7*Assumptions!$B$20 -> 1775.7087 | J8: =J7*Assumptions!$B$20 -> 1957.3421 | ... U8: =U7*Assumptions!$B$20 -> 2736.8756
A9: LLM calls – small model | B9: # | C9: =C7*Assumptions!$B$25 -> 3545.64 | D9: =D7*Assumptions!$B$25 -> 4268.7918 | E9: =E7*Assumptions!$B$25 -> 5200.0078 | F9: =F7*Assumptions!$B$25 -> 6126.5678 | G9: =G7*Assumptions!$B$25 -> 7048.495 | H9: =H7*Assumptions!$B$25 -> 7965.8125 | I9: =I7*Assumptions!$B$25 -> 8878.5434 | J9: =J7*Assumptions!$B$25 -> 9786.7107 | ... U9: =U7*Assumptions!$B$25 -> 13684.378
A10: LLM calls – large/reasoning model | B10: # | C10: =C7*Assumptions!$B$26 -> 531.846 | D10: =D7*Assumptions!$B$26 -> 640.31877 | E10: =E7*Assumptions!$B$26 -> 780.00118 | F10: =F7*Assumptions!$B$26 -> 918.98517 | G10: =G7*Assumptions!$B$26 -> 1057.2742 | H10: =H7*Assumptions!$B$26 -> 1194.8719 | I10: =I7*Assumptions!$B$26 -> 1331.7815 | J10: =J7*Assumptions!$B$26 -> 1468.0066 | ... U10: =U7*Assumptions!$B$26 -> 2052.6567
A11: LLM Tokens
A12: Small model input tokens | B12: tokens | C12: =C9*Assumptions!$B$27*(1-Assumptions!$B$31)+C7*Assumptions!$B$32*(1-Assumptions!$B$31) -> 5717344.5 | D12: =D9*Assumptions!$B$27*(1-Assumptions!$B$31)+D7*Assumptions!$B$32*(1-Assumptions!$B$31) -> 6883426.8 | E12: =E9*Assumptions!$B$27*(1-Assumptions!$B$31)+E7*Assumptions!$B$32*(1-Assumptions!$B$31) -> 8385012.6 | F12: =F9*Assumptions!$B$27*(1-Assumptions!$B$31)+F7*Assumptions!$B$32*(1-Assumptions!$B$31) -> 9879090.6 | G12: =G9*Assumptions!$B$27*(1-Assumptions!$B$31)+G7*Assumptions!$B$32*(1-Assumptions!$B$31) -> 11365698 | H12: =H9*Assumptions!$B$27*(1-Assumptions!$B$31)+H7*Assumptions!$B$32*(1-Assumptions!$B$31) -> 12844873 | I12: =I9*Assumptions!$B$27*(1-Assumptions!$B$31)+I7*Assumptions!$B$32*(1-Assumptions!$B$31) -> 14316651 | J12: =J9*Assumptions!$B$27*(1-Assumptions!$B$31)+J7*Assumptions!$B$32*(1-Assumptions!$B$31) -> 15781071 | ... U12: =U9*Assumptions!$B$27*(1-Assumptions!$B$31)+U7*Assumptions!$B$32*(1-Assumptions!$B$31) -> 22066060
A13: Small model output tokens | B13: tokens | C13: =C9*Assumptions!$B$28 -> 1240974 | D13: =D9*Assumptions!$B$28 -> 1494077.1 | E13: =E9*Assumptions!$B$28 -> 1820002.7 | F13: =F9*Assumptions!$B$28 -> 2144298.7 | G13: =G9*Assumptions!$B$28 -> 2466973.2 | H13: =H9*Assumptions!$B$28 -> 2788034.4 | I13: =I9*Assumptions!$B$28 -> 3107490.2 | J13: =J9*Assumptions!$B$28 -> 3425348.7 | ... U13: =U9*Assumptions!$B$28 -> 4789532.4
A14: Large model input tokens | B14: tokens | C14: =C10*Assumptions!$B$29*(1-Assumptions!$B$31) -> 1994422.5 | D14: =D10*Assumptions!$B$29*(1-Assumptions!$B$31) -> 2401195.4 | E14: =E10*Assumptions!$B$29*(1-Assumptions!$B$31) -> 2925004.4 | F14: =F10*Assumptions!$B$29*(1-Assumptions!$B$31) -> 3446194.4 | G14: =G10*Assumptions!$B$29*(1-Assumptions!$B$31) -> 3964778.4 | H14: =H10*Assumptions!$B$29*(1-Assumptions!$B$31) -> 4480769.5 | I14: =I10*Assumptions!$B$29*(1-Assumptions!$B$31) -> 4994180.7 | J14: =J10*Assumptions!$B$29*(1-Assumptions!$B$31) -> 5505024.8 | ... U14: =U10*Assumptions!$B$29*(1-Assumptions!$B$31) -> 7697462.7
A15: Large model output tokens | B15: tokens | C15: =C10*Assumptions!$B$30 -> 478661.4 | D15: =D10*Assumptions!$B$30 -> 576286.89 | E15: =E10*Assumptions!$B$30 -> 702001.06 | F15: =F10*Assumptions!$B$30 -> 827086.65 | G15: =G10*Assumptions!$B$30 -> 951546.82 | H15: =H10*Assumptions!$B$30 -> 1075384.7 | I15: =I10*Assumptions!$B$30 -> 1198603.4 | J15: =J10*Assumptions!$B$30 -> 1321205.9 | ... U15: =U10*Assumptions!$B$30 -> 1847391.1
A16: Total tokens (all models) | B16: tokens | C16: =SUM(C12:C15) -> 9431402.4 | D16: =SUM(D12:D15) -> 11354986 | E16: =SUM(E12:E15) -> 13832021 | F16: =SUM(F12:F15) -> 16296670 | G16: =SUM(G12:G15) -> 18748997 | H16: =SUM(H12:H15) -> 21189061 | I16: =SUM(I12:I15) -> 23616926 | J16: =SUM(J12:J15) -> 26032650 | ... U16: =SUM(U12:U15) -> 36400446
C17: =C16/30 -> 314380.08 | D17: =D16/30 -> 378499.54 | E17: =E16/30 -> 461067.36 | F17: =F16/30 -> 543222.35 | G17: =G16/30 -> 624966.55 | H17: =H16/30 -> 706302.04 | I17: =I16/30 -> 787230.85 | J17: =J16/30 -> 867755.02 | ... U17: =U16/30 -> 1213348.2
A18: Translated to yearly estimation | B18: Assumption | F18: Year1 | G18: Y | L18: Year 2 | P18: Year 3 | T18: Year 4 | U18: Year 5
A19: Approximation of ticket hanlded per month | B19: as this are headless agents, number of tickets handled would be equivalent to agent invocation not necessarily runs | F19: =F7 -> 3063.2839 | G19: =G7 -> 3524.2475 | H19: =H7 -> 3982.9062 | I19: =I7 -> 4439.2717 | J19: =J7 -> 4893.3554 | K19: =K7 -> 5345.1686 | L19: =L7 -> 5794.7227 | M19: =M7 -> 6242.0291 | ... U19: =U7 -> 6842.1891
A20: AISP Infra (monthly)
A21: Preferred Deployment Model | F21: Hybrid | G21: Hybrid | H21: Hybrid | I21: Hybrid | J21: Hybrid | K21: Hybrid | L21: Hybrid | M21: Hybrid | N21: Hybrid | O21: Hybrid | P21: Hybrid | Q21: Hybrid | R21: Hybrid | S21: Hybrid | T21: Hybrid | U21: Hybrid
A22: Foundation Support Level | F22: High | G22: High | H22: High | I22: High | J22: High | K22: High | L22: High | M22: High | N22: High | O22: High | P22: High | Q22: High | R22: High | S22: High | T22: High | U22: High
A23: Monthly Premium Support run cost | B23: $ | F23: 0 | G23: 1500 | H23: 1500 | I23: 1500 | J23: 1500 | K23: 1500 | L23: 0 | M23: 1500 | N23: 1500 | O23: 1500 | P23: 0 | Q23: 1500 | R23: 1500 | S23: 1500 | T23: 0 | U23: 0
A24: Token consumption (LLM and Usage) (Monthly)
A25: Estimation of LLM call per month based on ticket trigger | B25: Per agent 15 LLM calls | F25: =F9+F10 -> 7045.553 | G25: =G9+G10 -> 8105.7692 | H25: =H9+H10 -> 9160.6844 | I25: =I9+I10 -> 10210.325 | J25: =J9+J10 -> 11254.717 | K25: =K9+K10 -> 12293.888 | L25: =L9+L10 -> 13327.862 | M25: =M9+M10 -> 14356.667 | ... U25: =U9+U10 -> 15737.035
A26: Average Queries(LLM calls) Per Day Per User | B26: LLM calls per day = queries per day as ticket would be invoking agent (Estimation of LLM calls/30) | F26: =F25/30 -> 234.85177 | G26: =G25/30 -> 270.19231 | H26: =H25/30 -> 305.35615 | I26: =I25/30 -> 340.34416 | J26: =J25/30 -> 375.15724 | K26: =K25/30 -> 409.79626 | L26: =L25/30 -> 444.26208 | M26: =M25/30 -> 478.55557 | ... U26: =U25/30 -> 524.56783
A27: Average Number of Users Per Day | B27: we can assume 1 as we have covered everything in queries | F27: 0 | G27: 2 | H27: 3 | I27: 4 | J27: 5 | K27: 6 | L27: 0 | M27: 8 | N27: 9 | O27: 10 | P27: 0 | Q27: 12 | R27: 13 | S27: 14 | T27: 0 | U27: 0
A28: Average Input Tokens Per Query | F28: =(F12+F14)/F25 -> 1891.3043 | G28: =(G12+G14)/G25 -> 1891.3043 | H28: =(H12+H14)/H25 -> 1891.3043 | I28: =(I12+I14)/I25 -> 1891.3043 | J28: =(J12+J14)/J25 -> 1891.3043 | K28: =(K12+K14)/K25 -> 1891.3043 | L28: =(L12+L14)/L25 -> 1891.3043 | M28: =(M12+M14)/M25 -> 1891.3043 | ... U28: =(U12+U14)/U25 -> 1891.3043
A29: Average Output Tokens Per Response | F29: =(F13+F15)/F25 -> 421.73913 | G29: =(G13+G15)/G25 -> 421.73913 | H29: =(H13+H15)/H25 -> 421.73913 | I29: =(I13+I15)/I25 -> 421.73913 | J29: =(J13+J15)/J25 -> 421.73913 | K29: =(K13+K15)/K25 -> 421.73913 | L29: =(L13+L15)/L25 -> 421.73913 | M29: =(M13+M15)/M25 -> 421.73913 | ... U29: =(U13+U15)/U25 -> 421.73913
A30: System Prompt Tokens per call | F30: 0 | G30: 301 | H30: 302 | I30: 303 | J30: 304 | K30: 305 | L30: 0 | M30: 307 | N30: 308 | O30: 309 | P30: 0 | Q30: 311 | R30: 312 | S30: 313 | T30: 0 | U30: 0
A31: Monthly Token consumption Run cost | B31: $ | F31: 0 | L31: 0 | P31: 0 | T31: 0 | U31: 0
A33: Knowledge Base (Monthly)
A34: Size of Knowledge base | D34: \] | F34: GB | G34: 10GB | H34: 10GB | I34: 10GB | J34: 10GB | K34: 10GB | L34: GB | M34: 10GB | N34: 10GB | O34: 10GB | P34: GB | Q34: 10GB | R34: 10GB | S34: 10GB | T34: GB | U34: GB
A35: Context token per query | B35: Removed web search cost as this is for only SOP embeddings | F35: 0 | G35: 501 | H35: 502 | I35: 503 | J35: 504 | K35: 505 | L35: 0 | M35: 507 | N35: 508 | O35: 509 | P35: 0 | Q35: 511 | R35: 512 | S35: 513 | T35: 0 | U35: 0
A36: Monthly KB Run cost | B36: $ | F36: 0 | L36: 0 | P36: 0 | T36: 0 | U36: 0
A37: Multimedia Processing (Monthly) | B37: No MM processing
A38: Agentic Features (Monthly)
A39: Number of Monthly Domain Agent Runs | B39: Assumption every ticket would need 3 runs | F39: =F19*3 -> 9189.8517 | G39: =G19*3 -> 10572.742 | H39: =H19*3 -> 11948.719 | I39: =I19*3 -> 13317.815 | J39: =J19*3 -> 14680.066 | K39: =K19*3 -> 16035.506 | L39: =L19*3 -> 17384.168 | M39: =M19*3 -> 18726.087 | ... U39: =U19*3 -> 20526.567
A40: Average Agent Interactions per Query | F40: 0 | G40: 4 | H40: 5 | I40: 6 | J40: 7 | K40: 8 | L40: 0 | M40: 10 | N40: 11 | O40: 12 | P40: 0 | Q40: 14 | R40: 15 | S40: 16 | T40: 0 | U40: 0
A41: Average Input Tokens (System prompt, Context, User Prompt) | B41: Total token consumption/workflow runs | F41: =(F12+F15)/F39/3 -> 388.33333 | G41: =(G12+G15)/G39/3 -> 388.33333 | H41: =(H12+H15)/H39/3 -> 388.33333 | I41: =(I12+I15)/I39/3 -> 388.33333 | J41: =(J12+J15)/J39/3 -> 388.33333 | K41: =(K12+K15)/K39/3 -> 388.33333 | L41: =(L12+L15)/L39/3 -> 388.33333 | M41: =(M12+M15)/M39/3 -> 388.33333 | ... U41: =(U12+U15)/U39/3 -> 388.33333
A42: Average Output Tokens | B42: Total token consumption/workflow runs | F42: =IFERROR((F13+F15)/F39/F40,0) -> 0 | G42: =IFERROR((G13+G15)/G39/G40,0) -> 80.833333 | H42: =IFERROR((H13+H15)/H39/H40,0) -> 64.666667 | I42: =IFERROR((I13+I15)/I39/I40,0) -> 53.888889 | J42: =IFERROR((J13+J15)/J39/J40,0) -> 46.190476 | K42: =IFERROR((K13+K15)/K39/K40,0) -> 40.416667 | L42: =IFERROR((L13+L15)/L39/L40,0) -> 0 | M42: =IFERROR((M13+M15)/M39/M40,0) -> 32.333333 | ... U42: =IFERROR((U13+U15)/U39/U40,0) -> 0
A43: Run cost (monthly) | B43: $ | F43: 0 | L43: 0 | P43: 0 | T43: 0 | U43: 0
A44: Total run cost Monthly | F44: =F23+F31+F36+F43 -> 0 | G44: =G23+G31+G36+G43 -> 1500 | H44: =H23+H31+H36+H43 -> 1500 | I44: =I23+I31+I36+I43 -> 1500 | J44: =J23+J31+J36+J43 -> 1500 | K44: =K23+K31+K36+K43 -> 1500 | L44: =L23+L31+L36+L43 -> 0 | M44: =M23+M31+M36+M43 -> 1500 | ... U44: =U23+U31+U36+U43 -> 0
A45: Legacy annual support run-cost view (period markers only; excluded from normalized final run cost) | B45: $ | F45: =F44*12 -> 0 | G45: =G44*12 -> 18000 | H45: =H44*12 -> 18000 | I45: =I44*12 -> 18000 | J45: =J44*12 -> 18000 | K45: =K44*12 -> 18000 | L45: =L44*12 -> 0 | M45: =M44*12 -> 18000 | ... U45: =U44*12 -> 0
A46: Legacy custom-agent comparison (excluded from normalized final run cost) | F46: =F45 -> 0 | G46: =G45 -> 18000 | H46: =H45 -> 18000 | I46: =I45 -> 18000 | J46: =J45 -> 18000 | K46: =K45 -> 18000 | L46: =L45 -> 0 | M46: =M45 -> 18000 | ... U46: =U45 -> 0
A47: LLM Cost
A48: Small model cost | B48: $ | C48: =(C12/1000000)*Assumptions!$B$34+(C13/1000000)*Assumptions!$B$35 -> 4.2724962 | D48: =(D12/1000000)*Assumptions!$B$34+(D13/1000000)*Assumptions!$B$35 -> 5.1438941 | E48: =(E12/1000000)*Assumptions!$B$34+(E13/1000000)*Assumptions!$B$35 -> 6.2660094 | F48: =(F12/1000000)*Assumptions!$B$34+(F13/1000000)*Assumptions!$B$35 -> 7.3825142 | G48: =(G12/1000000)*Assumptions!$B$34+(G13/1000000)*Assumptions!$B$35 -> 8.4934364 | H48: =(H12/1000000)*Assumptions!$B$34+(H13/1000000)*Assumptions!$B$35 -> 9.598804 | I48: =(I12/1000000)*Assumptions!$B$34+(I13/1000000)*Assumptions!$B$35 -> 10.698645 | J48: =(J12/1000000)*Assumptions!$B$34+(J13/1000000)*Assumptions!$B$35 -> 11.792986 | ... U48: =(U12/1000000)*Assumptions!$B$34+(U13/1000000)*Assumptions!$B$35 -> 16.489676
A49: Large model cost | B49: $ | C49: =(C14/1000000)*Assumptions!$B$36+(C15/1000000)*Assumptions!$B$37 -> 7.8181362 | D49: =(D14/1000000)*Assumptions!$B$36+(D15/1000000)*Assumptions!$B$37 -> 9.4126859 | E49: =(E14/1000000)*Assumptions!$B$36+(E15/1000000)*Assumptions!$B$37 -> 11.466017 | F49: =(F14/1000000)*Assumptions!$B$36+(F15/1000000)*Assumptions!$B$37 -> 13.509082 | G49: =(G14/1000000)*Assumptions!$B$36+(G15/1000000)*Assumptions!$B$37 -> 15.541931 | H49: =(H14/1000000)*Assumptions!$B$36+(H15/1000000)*Assumptions!$B$37 -> 17.564617 | I49: =(I14/1000000)*Assumptions!$B$36+(I15/1000000)*Assumptions!$B$37 -> 19.577188 | J49: =(J14/1000000)*Assumptions!$B$36+(J15/1000000)*Assumptions!$B$37 -> 21.579697 | ... U49: =(U14/1000000)*Assumptions!$B$36+(U15/1000000)*Assumptions!$B$37 -> 30.174054
A50: Total LLM cost | B50: $ | C50: =SUM(C48:C49) -> 12.090632 | D50: =SUM(D48:D49) -> 14.55658 | E50: =SUM(E48:E49) -> 17.732027 | F50: =SUM(F48:F49) -> 20.891596 | G50: =SUM(G48:G49) -> 24.035368 | H50: =SUM(H48:H49) -> 27.163421 | I50: =SUM(I48:I49) -> 30.275833 | J50: =SUM(J48:J49) -> 33.372684 | ... U50: =SUM(U48:U49) -> 46.66373
A51: Compute & Data Platform | B51: Indicative AKS cost
A52: AKS nodes (estimated) | B52: # | C52: =CEILING(C5/10*Unit_Costs!$B$7,1) -> 1 | D52: =CEILING(D5/10*Unit_Costs!$B$7,1) -> 1 | E52: =CEILING(E5/10*Unit_Costs!$B$7,1) -> 1 | F52: =CEILING(F5/10*Unit_Costs!$B$7,1) -> 1 | G52: =CEILING(G5/10*Unit_Costs!$B$7,1) -> 1 | H52: =CEILING(H5/10*Unit_Costs!$B$7,1) -> 1 | I52: =CEILING(I5/10*Unit_Costs!$B$7,1) -> 1 | J52: =CEILING(J5/10*Unit_Costs!$B$7,1) -> 1 | ... U52: =CEILING(U5/10*Unit_Costs!$B$7,1) -> 2
A53: AKS cost | B53: $ | C53: =C52*Unit_Costs!$B$6 -> 350 | D53: =D52*Unit_Costs!$B$6 -> 350 | E53: =E52*Unit_Costs!$B$6 -> 350 | F53: =F52*Unit_Costs!$B$6 -> 350 | G53: =G52*Unit_Costs!$B$6 -> 350 | H53: =H52*Unit_Costs!$B$6 -> 350 | I53: =I52*Unit_Costs!$B$6 -> 350 | J53: =J52*Unit_Costs!$B$6 -> 350 | ... U53: =U52*Unit_Costs!$B$6 -> 700
A54: Functions executions | B54: # | C54: =C7*Unit_Costs!$B$8 -> 5318.46 | D54: =D7*Unit_Costs!$B$8 -> 6403.1877 | E54: =E7*Unit_Costs!$B$8 -> 7800.0118 | F54: =F7*Unit_Costs!$B$8 -> 9189.8517 | G54: =G7*Unit_Costs!$B$8 -> 10572.742 | H54: =H7*Unit_Costs!$B$8 -> 11948.719 | I54: =I7*Unit_Costs!$B$8 -> 13317.815 | J54: =J7*Unit_Costs!$B$8 -> 14680.066 | ... U54: =U7*Unit_Costs!$B$8 -> 20526.567
A55: Functions GB‑seconds | B55: GB‑s | C55: =C54*Unit_Costs!$B$9 -> 1329.615 | D55: =D54*Unit_Costs!$B$9 -> 1600.7969 | E55: =E54*Unit_Costs!$B$9 -> 1950.0029 | F55: =F54*Unit_Costs!$B$9 -> 2297.4629 | G55: =G54*Unit_Costs!$B$9 -> 2643.1856 | H55: =H54*Unit_Costs!$B$9 -> 2987.1797 | I55: =I54*Unit_Costs!$B$9 -> 3329.4538 | J55: =J54*Unit_Costs!$B$9 -> 3670.0165 | ... U55: =U54*Unit_Costs!$B$9 -> 5131.6418
A56: Functions cost | B56: $ | C56: =MAX(0,C54-Unit_Costs!$B$12)/1000000*Unit_Costs!$B$10+MAX(0,C55-Unit_Costs!$B$13)*Unit_Costs!$B$11 -> 0 | D56: =MAX(0,D54-Unit_Costs!$B$12)/1000000*Unit_Costs!$B$10+MAX(0,D55-Unit_Costs!$B$13)*Unit_Costs!$B$11 -> 0 | E56: =MAX(0,E54-Unit_Costs!$B$12)/1000000*Unit_Costs!$B$10+MAX(0,E55-Unit_Costs!$B$13)*Unit_Costs!$B$11 -> 0 | F56: =MAX(0,F54-Unit_Costs!$B$12)/1000000*Unit_Costs!$B$10+MAX(0,F55-Unit_Costs!$B$13)*Unit_Costs!$B$11 -> 0 | G56: =MAX(0,G54-Unit_Costs!$B$12)/1000000*Unit_Costs!$B$10+MAX(0,G55-Unit_Costs!$B$13)*Unit_Costs!$B$11 -> 0 | H56: =MAX(0,H54-Unit_Costs!$B$12)/1000000*Unit_Costs!$B$10+MAX(0,H55-Unit_Costs!$B$13)*Unit_Costs!$B$11 -> 0 | I56: =MAX(0,I54-Unit_Costs!$B$12)/1000000*Unit_Costs!$B$10+MAX(0,I55-Unit_Costs!$B$13)*Unit_Costs!$B$11 -> 0 | J56: =MAX(0,J54-Unit_Costs!$B$12)/1000000*Unit_Costs!$B$10+MAX(0,J55-Unit_Costs!$B$13)*Unit_Costs!$B$11 -> 0 | ... U56: =MAX(0,U54-Unit_Costs!$B$12)/1000000*Unit_Costs!$B$10+MAX(0,U55-Unit_Costs!$B$13)*Unit_Costs!$B$11 -> 0
A57: ADLS storage (end of month) | B57: GB | C57: =Infra_Sizing!$B$5+(C7/1000)*Unit_Costs!$B$15 -> 501.06369 | D57: =C57+(D7/1000)*Unit_Costs!$B$15 -> 502.34433 | E57: =D57+(E7/1000)*Unit_Costs!$B$15 -> 503.90433 | F57: =E57+(F7/1000)*Unit_Costs!$B$15 -> 505.7423 | G57: =F57+(G7/1000)*Unit_Costs!$B$15 -> 507.85685 | H57: =G57+(H7/1000)*Unit_Costs!$B$15 -> 510.24659 | I57: =H57+(I7/1000)*Unit_Costs!$B$15 -> 512.91016 | J57: =I57+(J7/1000)*Unit_Costs!$B$15 -> 515.84617 | K57: =J57+(K7/1000)*Unit_Costs!$B$15 -> 519.05327 | ... U57: =T57+(U7/1000)*Unit_Costs!$B$15 -> 559.39782
A58: ADLS storage cost | B58: $ | C58: =C57*Unit_Costs!$B$14 -> 10.021274 | D58: =D57*Unit_Costs!$B$14 -> 10.046887 | E58: =E57*Unit_Costs!$B$14 -> 10.078087 | F58: =F57*Unit_Costs!$B$14 -> 10.114846 | G58: =G57*Unit_Costs!$B$14 -> 10.157137 | H58: =H57*Unit_Costs!$B$14 -> 10.204932 | I58: =I57*Unit_Costs!$B$14 -> 10.258203 | J58: =J57*Unit_Costs!$B$14 -> 10.316923 | ... U58: =U57*Unit_Costs!$B$14 -> 11.187956
A59: Postgres vCore‑hours | B59: vCore‑hrs | C59: =Unit_Costs!$B$18*730 -> 2920 | D59: =Unit_Costs!$B$18*730 -> 2920 | E59: =Unit_Costs!$B$18*730 -> 2920 | F59: =Unit_Costs!$B$18*730 -> 2920 | G59: =Unit_Costs!$B$18*730 -> 2920 | H59: =Unit_Costs!$B$18*730 -> 2920 | I59: =Unit_Costs!$B$18*730 -> 2920 | J59: =Unit_Costs!$B$18*730 -> 2920 | ... U59: =Unit_Costs!$B$18*730 -> 2920
A60: Postgres compute cost | B60: $ | C60: =C59*Unit_Costs!$B$16 -> 1022 | D60: =D59*Unit_Costs!$B$16 -> 1022 | E60: =E59*Unit_Costs!$B$16 -> 1022 | F60: =F59*Unit_Costs!$B$16 -> 1022 | G60: =G59*Unit_Costs!$B$16 -> 1022 | H60: =H59*Unit_Costs!$B$16 -> 1022 | I60: =I59*Unit_Costs!$B$16 -> 1022 | J60: =J59*Unit_Costs!$B$16 -> 1022 | ... U60: =U59*Unit_Costs!$B$16 -> 1022
A61: Postgres storage (end of month) | B61: GB | C61: =Unit_Costs!$B$19+(C7/1000)*Infra_Sizing!$B$6 -> 250.26592 | D61: =C61+(D7/1000)*Infra_Sizing!$B$6 -> 250.58608 | E61: =D61+(E7/1000)*Infra_Sizing!$B$6 -> 250.97608 | F61: =E61+(F7/1000)*Infra_Sizing!$B$6 -> 251.43558 | G61: =F61+(G7/1000)*Infra_Sizing!$B$6 -> 251.96421 | H61: =G61+(H7/1000)*Infra_Sizing!$B$6 -> 252.56165 | I61: =H61+(I7/1000)*Infra_Sizing!$B$6 -> 253.22754 | J61: =I61+(J7/1000)*Infra_Sizing!$B$6 -> 253.96154 | K61: =J61+(K7/1000)*Infra_Sizing!$B$6 -> 254.76332 | ... U61: =T61+(U7/1000)*Infra_Sizing!$B$6 -> 264.84946
A62: Postgres storage cost | B62: $ | C62: =C61*Unit_Costs!$B$17 -> 30.031911 | D62: =D61*Unit_Costs!$B$17 -> 30.07033 | E62: =E61*Unit_Costs!$B$17 -> 30.11713 | F62: =F61*Unit_Costs!$B$17 -> 30.172269 | G62: =G61*Unit_Costs!$B$17 -> 30.235706 | H62: =H61*Unit_Costs!$B$17 -> 30.307398 | I62: =I61*Unit_Costs!$B$17 -> 30.387305 | J62: =J61*Unit_Costs!$B$17 -> 30.475385 | ... U62: =U61*Unit_Costs!$B$17 -> 31.781935
A63: Other Azure fixed services | B63: $ | C63: =SUM(Infra_Sizing!$B$7:$B$11) -> 2000 | D63: =SUM(Infra_Sizing!$B$7:$B$11) -> 2000 | E63: =SUM(Infra_Sizing!$B$7:$B$11) -> 2000 | F63: =SUM(Infra_Sizing!$B$7:$B$11) -> 2000 | G63: =SUM(Infra_Sizing!$B$7:$B$11) -> 2000 | H63: =SUM(Infra_Sizing!$B$7:$B$11) -> 2000 | I63: =SUM(Infra_Sizing!$B$7:$B$11) -> 2000 | J63: =SUM(Infra_Sizing!$B$7:$B$11) -> 2000 | ... U63: =SUM(Infra_Sizing!$B$7:$B$11) -> 2000
A64: Networking & security overhead | B64: $ | C64: =Infra_Sizing!$B$12*(C53+C56+C58+C60+C62+C63) -> 409.44638 | D64: =Infra_Sizing!$B$12*(D53+D56+D58+D60+D62+D63) -> 409.45407 | E64: =Infra_Sizing!$B$12*(E53+E56+E58+E60+E62+E63) -> 409.46343 | F64: =Infra_Sizing!$B$12*(F53+F56+F58+F60+F62+F63) -> 409.47445 | G64: =Infra_Sizing!$B$12*(G53+G56+G58+G60+G62+G63) -> 409.48714 | H64: =Infra_Sizing!$B$12*(H53+H56+H58+H60+H62+H63) -> 409.50148 | I64: =Infra_Sizing!$B$12*(I53+I56+I58+I60+I62+I63) -> 409.51746 | J64: =Infra_Sizing!$B$12*(J53+J56+J58+J60+J62+J63) -> 409.53508 | ... U64: =Infra_Sizing!$B$12*(U53+U56+U58+U60+U62+U63) -> 451.79639
A65: Observability & BI
A66: Logs ingested (GB) | B66: GB | C66: =(C7/1000)*Unit_Costs!$B$20 -> 0.443205 | D66: =(D7/1000)*Unit_Costs!$B$20 -> 0.53359898 | E66: =(E7/1000)*Unit_Costs!$B$20 -> 0.65000098 | F66: =(F7/1000)*Unit_Costs!$B$20 -> 0.76582098 | G66: =(G7/1000)*Unit_Costs!$B$20 -> 0.88106187 | H66: =(H7/1000)*Unit_Costs!$B$20 -> 0.99572656 | I66: =(I7/1000)*Unit_Costs!$B$20 -> 1.1098179 | J66: =(J7/1000)*Unit_Costs!$B$20 -> 1.2233388 | ... U66: =(U7/1000)*Unit_Costs!$B$20 -> 1.7105473
A67: Splunk / log platform cost | B67: $ | C67: =C66*Unit_Costs!$B$21 -> 1.1080125 | D67: =D66*Unit_Costs!$B$21 -> 1.3339974 | E67: =E66*Unit_Costs!$B$21 -> 1.6250025 | F67: =F66*Unit_Costs!$B$21 -> 1.9145524 | G67: =G66*Unit_Costs!$B$21 -> 2.2026547 | H67: =H66*Unit_Costs!$B$21 -> 2.4893164 | I67: =I66*Unit_Costs!$B$21 -> 2.7745448 | J67: =J66*Unit_Costs!$B$21 -> 3.0583471 | ... U67: =U66*Unit_Costs!$B$21 -> 4.2763682
A68: Grafana / dashboards fixed | B68: $ | C68: =Unit_Costs!$B$22 -> 500 | D68: =Unit_Costs!$B$22 -> 500 | E68: =Unit_Costs!$B$22 -> 500 | F68: =Unit_Costs!$B$22 -> 500 | G68: =Unit_Costs!$B$22 -> 500 | H68: =Unit_Costs!$B$22 -> 500 | I68: =Unit_Costs!$B$22 -> 500 | J68: =Unit_Costs!$B$22 -> 500 | ... U68: =Unit_Costs!$B$22 -> 500
A69: Power BI licenses cost | B69: $ | C69: =Unit_Costs!$B$23*Unit_Costs!$B$24 -> 210 | D69: =Unit_Costs!$B$23*Unit_Costs!$B$24 -> 210 | E69: =Unit_Costs!$B$23*Unit_Costs!$B$24 -> 210 | F69: =Unit_Costs!$B$23*Unit_Costs!$B$24 -> 210 | G69: =Unit_Costs!$B$23*Unit_Costs!$B$24 -> 210 | H69: =Unit_Costs!$B$23*Unit_Costs!$B$24 -> 210 | I69: =Unit_Costs!$B$23*Unit_Costs!$B$24 -> 210 | J69: =Unit_Costs!$B$23*Unit_Costs!$B$24 -> 210 | ... U69: =Unit_Costs!$B$23*Unit_Costs!$B$24 -> 210
A70: Total observability & BI | B70: $ | C70: =SUM(C67:C69) -> 711.10801 | D70: =SUM(D67:D69) -> 711.334 | E70: =SUM(E67:E69) -> 711.625 | F70: =SUM(F67:F69) -> 711.91455 | G70: =SUM(G67:G69) -> 712.20265 | H70: =SUM(H67:H69) -> 712.48932 | I70: =SUM(I67:I69) -> 712.77454 | J70: =SUM(J67:J69) -> 713.05835 | ... U70: =SUM(U67:U69) -> 714.27637
A71: Totals
A72: Total platform cost (ex‑labor) | B72: $ | C72: =C50+C53+C56+C58+C60+C62+C63+C64+C70 -> 4544.6982 | D72: =D50+D53+D56+D58+D60+D62+D63+D64+D70 -> 4547.4619 | E72: =E50+E53+E56+E58+E60+E62+E63+E64+E70 -> 4551.0157 | F72: =F50+F53+F56+F58+F60+F62+F63+F64+F70 -> 4554.5677 | G72: =G50+G53+G56+G58+G60+G62+G63+G64+G70 -> 4558.118 | H72: =H50+H53+H56+H58+H60+H62+H63+H64+H70 -> 4561.6665 | I72: =I50+I53+I56+I58+I60+I62+I63+I64+I70 -> 4565.2133 | J72: =J50+J53+J56+J58+J60+J62+J63+J64+J70 -> 4568.7584 | ... U72: =U50+U53+U56+U58+U60+U62+U63+U64+U70 -> 4977.7064
A73: Staffing cost (optional) | B73: $ | C73: =Staffing!$B$15 -> 75000 | D73: =Staffing!$B$15 -> 75000 | E73: =Staffing!$B$15 -> 75000 | F73: =Staffing!$B$15 -> 75000 | G73: =Staffing!$B$15 -> 75000 | H73: =Staffing!$B$15 -> 75000 | I73: =Staffing!$B$15 -> 75000 | J73: =Staffing!$B$15 -> 75000 | ... U73: =Staffing!$B$15 -> 75000
A74: Total incl. staffing | B74: $ | C74: =C72+C73 -> 79544.698 | D74: =D72+D73 -> 79547.462 | E74: =E72+E73 -> 79551.016 | F74: =F72+F73 -> 79554.568 | G74: =G72+G73 -> 79558.118 | H74: =H72+H73 -> 79561.667 | I74: =I72+I73 -> 79565.213 | J74: =J72+J73 -> 79568.758 | ... U74: =U72+U73 -> 79977.706
A75: Legacy ServiceNow token comparison (excluded from normalized final run cost) | F75: 0 | L75: 0 | M75: 50000 | N75: 50000 | O75: 50000 | P75: 0 | Q75: 50000 | R75: 50000 | S75: 50000 | T75: 0 | U75: 0
A76: Final run cost (annualized, incl. staffing) | B76: $ / year | C76: =C74*12 -> 954536.38 | D76: =D74*12 -> 954569.54 | E76: =E74*12 -> 954612.19 | F76: =F74*12 -> 954654.81 | G76: =G74*12 -> 954697.42 | H76: =H74*12 -> 954740 | I76: =I74*12 -> 954782.56 | J76: =J74*12 -> 954825.1 | ... U76: =U74*12 -> 959732.48
A78: Approx. cost per active agent (annual) | B78: $ / active agent / year | C78: =IFERROR(C76/C5,0) -> 427404.35 | D78: =IFERROR(D76/D5,0) -> 355012.54 | E78: =IFERROR(E76/E5,0) -> 291450 | F78: =IFERROR(F76/F5,0) -> 247383.21 | G78: =IFERROR(G76/G5,0) -> 215035.64 | H78: =IFERROR(H76/H5,0) -> 190281.31 | I78: =IFERROR(I76/I5,0) -> 170727.64 | J78: =IFERROR(J76/J5,0) -> 154891.71 | ... U78: =IFERROR(U76/U5,0) -> 111343.84
A80: PRIMARY SUMMARY | REVIEW ONLY: This sheet must be populated by formulas from Assumptions, Unit_Costs, Infra_Sizing, Staffing, and supporting calculations. Do not manually enter values in calculated cells.

Sheet Charts
A1: Partner Model For Agent Cost Estimation
A2: Charts | O2: REVIEW ONLY: Charts are linked to Summary. Do not change source ranges or manually overwrite linked data.
A3: Charts are linked to the Summary sheet.

Sheet Summary
A1: Partner Model For Agent Cost Estimation
A2: Executive Summary (Monthly) | O2: EXECUTIVE REVIEW ONLY: Simplified output linked to Model_Monthly. Do not overwrite formulas. Confirm monthly totals reconcile to the primary summary.
A3: Month | B3: Active agents | C3: Tickets | D3: LLM cost | E3: AKS cost | F3: Functions cost | G3: ADLS cost | H3: Postgres cost | I3: Obs & BI | J3: Other+Overhead | K3: Platform ex-labor | L3: Staffing | M3: Total incl staffing
A4: =EDATE(Assumptions!$B$5,ROW()-4) -> 46235 | B4: =Model_Monthly!C5 -> 2.2333333 | C4: =Model_Monthly!C7 -> 1772.82 | D4: =Model_Monthly!C50 -> 12.090632 | E4: =Model_Monthly!C53 -> 350 | F4: =Model_Monthly!C56 -> 0 | G4: =Model_Monthly!C58 -> 10.021274 | H4: =Model_Monthly!C60+Model_Monthly!C62 -> 1052.0319 | I4: =Model_Monthly!C70 -> 711.10801 | J4: =Model_Monthly!C63+Model_Monthly!C64 -> 2409.4464 | K4: =Model_Monthly!C72 -> 4544.6982 | L4: =Model_Monthly!C73 -> 75000 | M4: =Model_Monthly!C74 -> 79544.698
A5: =EDATE(Assumptions!$B$5,ROW()-4) -> 46266 | B5: =Model_Monthly!D5 -> 2.6888333 | C5: =Model_Monthly!D7 -> 2134.3959 | D5: =Model_Monthly!D50 -> 14.55658 | E5: =Model_Monthly!D53 -> 350 | F5: =Model_Monthly!D56 -> 0 | G5: =Model_Monthly!D58 -> 10.046887 | H5: =Model_Monthly!D60+Model_Monthly!D62 -> 1052.0703 | I5: =Model_Monthly!D70 -> 711.334 | J5: =Model_Monthly!D63+Model_Monthly!D64 -> 2409.4541 | K5: =Model_Monthly!D72 -> 4547.4619 | L5: =Model_Monthly!D73 -> 75000 | M5: =Model_Monthly!D74 -> 79547.462
A6: =EDATE(Assumptions!$B$5,ROW()-4) -> 46296 | B6: =Model_Monthly!E5 -> 3.2753892 | C6: =Model_Monthly!E7 -> 2600.0039 | D6: =Model_Monthly!E50 -> 17.732027 | E6: =Model_Monthly!E53 -> 350 | F6: =Model_Monthly!E56 -> 0 | G6: =Model_Monthly!E58 -> 10.078087 | H6: =Model_Monthly!E60+Model_Monthly!E62 -> 1052.1171 | I6: =Model_Monthly!E70 -> 711.625 | J6: =Model_Monthly!E63+Model_Monthly!E64 -> 2409.4634 | K6: =Model_Monthly!E72 -> 4551.0157 | L6: =Model_Monthly!E73 -> 75000 | M6: =Model_Monthly!E74 -> 79551.016
A7: =EDATE(Assumptions!$B$5,ROW()-4) -> 46327 | B7: =Model_Monthly!F5 -> 3.8590122 | C7: =Model_Monthly!F7 -> 3063.2839 | D7: =Model_Monthly!F50 -> 20.891596 | E7: =Model_Monthly!F53 -> 350 | F7: =Model_Monthly!F56 -> 0 | G7: =Model_Monthly!F58 -> 10.114846 | H7: =Model_Monthly!F60+Model_Monthly!F62 -> 1052.1723 | I7: =Model_Monthly!F70 -> 711.91455 | J7: =Model_Monthly!F63+Model_Monthly!F64 -> 2409.4745 | K7: =Model_Monthly!F72 -> 4554.5677 | L7: =Model_Monthly!F73 -> 75000 | M7: =Model_Monthly!F74 -> 79554.568
A8: =EDATE(Assumptions!$B$5,ROW()-4) -> 46357 | B8: =Model_Monthly!G5 -> 4.4397172 | C8: =Model_Monthly!G7 -> 3524.2475 | D8: =Model_Monthly!G50 -> 24.035368 | E8: =Model_Monthly!G53 -> 350 | F8: =Model_Monthly!G56 -> 0 | G8: =Model_Monthly!G58 -> 10.157137 | H8: =Model_Monthly!G60+Model_Monthly!G62 -> 1052.2357 | I8: =Model_Monthly!G70 -> 712.20265 | J8: =Model_Monthly!G63+Model_Monthly!G64 -> 2409.4871 | K8: =Model_Monthly!G72 -> 4558.118 | L8: =Model_Monthly!G73 -> 75000 | M8: =Model_Monthly!G74 -> 79558.118
A9: =EDATE(Assumptions!$B$5,ROW()-4) -> 46388 | B9: =Model_Monthly!H5 -> 5.0175186 | C9: =Model_Monthly!H7 -> 3982.9062 | D9: =Model_Monthly!H50 -> 27.163421 | E9: =Model_Monthly!H53 -> 350 | F9: =Model_Monthly!H56 -> 0 | G9: =Model_Monthly!H58 -> 10.204932 | H9: =Model_Monthly!H60+Model_Monthly!H62 -> 1052.3074 | I9: =Model_Monthly!H70 -> 712.48932 | J9: =Model_Monthly!H63+Model_Monthly!H64 -> 2409.5015 | K9: =Model_Monthly!H72 -> 4561.6665 | L9: =Model_Monthly!H73 -> 75000 | M9: =Model_Monthly!H74 -> 79561.667
A10: =EDATE(Assumptions!$B$5,ROW()-4) -> 46419 | B10: =Model_Monthly!I5 -> 5.592431 | C10: =Model_Monthly!I7 -> 4439.2717 | D10: =Model_Monthly!I50 -> 30.275833 | E10: =Model_Monthly!I53 -> 350 | F10: =Model_Monthly!I56 -> 0 | G10: =Model_Monthly!I58 -> 10.258203 | H10: =Model_Monthly!I60+Model_Monthly!I62 -> 1052.3873 | I10: =Model_Monthly!I70 -> 712.77454 | J10: =Model_Monthly!I63+Model_Monthly!I64 -> 2409.5175 | K10: =Model_Monthly!I72 -> 4565.2133 | L10: =Model_Monthly!I73 -> 75000 | M10: =Model_Monthly!I74 -> 79565.213
A11: =EDATE(Assumptions!$B$5,ROW()-4) -> 46447 | B11: =Model_Monthly!J5 -> 6.1644688 | C11: =Model_Monthly!J7 -> 4893.3554 | D11: =Model_Monthly!J50 -> 33.372684 | E11: =Model_Monthly!J53 -> 350 | F11: =Model_Monthly!J56 -> 0 | G11: =Model_Monthly!J58 -> 10.316923 | H11: =Model_Monthly!J60+Model_Monthly!J62 -> 1052.4754 | I11: =Model_Monthly!J70 -> 713.05835 | J11: =Model_Monthly!J63+Model_Monthly!J64 -> 2409.5351 | K11: =Model_Monthly!J72 -> 4568.7584 | L11: =Model_Monthly!J73 -> 75000 | M11: =Model_Monthly!J74 -> 79568.758
A12: =EDATE(Assumptions!$B$5,ROW()-4) -> 46478 | B12: =Model_Monthly!K5 -> 6.7336465 | C12: =Model_Monthly!K7 -> 5345.1686 | D12: =Model_Monthly!K50 -> 36.45405 | E12: =Model_Monthly!K53 -> 700 | F12: =Model_Monthly!K56 -> 0 | G12: =Model_Monthly!K58 -> 10.381065 | H12: =Model_Monthly!K60+Model_Monthly!K62 -> 1052.5716 | I12: =Model_Monthly!K70 -> 713.34073 | J12: =Model_Monthly!K63+Model_Monthly!K64 -> 2451.5543 | K12: =Model_Monthly!K72 -> 4964.3018 | L12: =Model_Monthly!K73 -> 75000 | M12: =Model_Monthly!K74 -> 79964.302
A13: =EDATE(Assumptions!$B$5,ROW()-4) -> 46508 | B13: =Model_Monthly!L5 -> 7.2999782 | C13: =Model_Monthly!L7 -> 5794.7227 | D13: =Model_Monthly!L50 -> 39.520009 | E13: =Model_Monthly!L53 -> 700 | F13: =Model_Monthly!L56 -> 0 | G13: =Model_Monthly!L58 -> 10.450602 | H13: =Model_Monthly!L60+Model_Monthly!L62 -> 1052.6759 | I13: =Model_Monthly!L70 -> 713.6217 | J13: =Model_Monthly!L63+Model_Monthly!L64 -> 2451.5752 | K13: =Model_Monthly!L72 -> 4967.8434 | L13: =Model_Monthly!L73 -> 75000 | M13: =Model_Monthly!L74 -> 79967.843
A14: =EDATE(Assumptions!$B$5,ROW()-4) -> 46539 | B14: =Model_Monthly!M5 -> 7.8634784 | C14: =Model_Monthly!M7 -> 6242.0291 | D14: =Model_Monthly!M50 -> 42.570639 | E14: =Model_Monthly!M53 -> 700 | F14: =Model_Monthly!M56 -> 0 | G14: =Model_Monthly!M58 -> 10.525506 | H14: =Model_Monthly!M60+Model_Monthly!M62 -> 1052.7883 | I14: =Model_Monthly!M70 -> 713.90127 | J14: =Model_Monthly!M63+Model_Monthly!M64 -> 2451.5977 | K14: =Model_Monthly!M72 -> 4971.3833 | L14: =Model_Monthly!M73 -> 75000 | M14: =Model_Monthly!M74 -> 79971.383
A15: =EDATE(Assumptions!$B$5,ROW()-4) -> 46569 | B15: =Model_Monthly!N5 -> 8.424161 | C15: =Model_Monthly!N7 -> 6687.099 | D15: =Model_Monthly!N50 -> 45.606015 | E15: =Model_Monthly!N53 -> 700 | F15: =Model_Monthly!N56 -> 0 | G15: =Model_Monthly!N58 -> 10.605752 | H15: =Model_Monthly!N60+Model_Monthly!N62 -> 1052.9086 | I15: =Model_Monthly!N70 -> 714.17944 | J15: =Model_Monthly!N63+Model_Monthly!N64 -> 2451.6217 | K15: =Model_Monthly!N72 -> 4974.9216 | L15: =Model_Monthly!N73 -> 75000 | M15: =Model_Monthly!N74 -> 79974.922
A16: =EDATE(Assumptions!$B$5,ROW()-4) -> 46600 | B16: =Model_Monthly!O5 -> 8.7487068 | C16: =Model_Monthly!O7 -> 6944.7235 | D16: =Model_Monthly!O50 -> 47.363014 | E16: =Model_Monthly!O53 -> 700 | F16: =Model_Monthly!O56 -> 0 | G16: =Model_Monthly!O58 -> 10.689088 | H16: =Model_Monthly!O60+Model_Monthly!O62 -> 1053.0336 | I16: =Model_Monthly!O70 -> 714.34045 | J16: =Model_Monthly!O63+Model_Monthly!O64 -> 2451.6467 | K16: =Model_Monthly!O72 -> 4977.0729 | L16: =Model_Monthly!O73 -> 75000 | M16: =Model_Monthly!O74 -> 79977.073
A17: =EDATE(Assumptions!$B$5,ROW()-4) -> 46631 | B17: =Model_Monthly!P5 -> 8.8382966 | C17: =Model_Monthly!P7 -> 7015.8399 | D17: =Model_Monthly!P50 -> 47.848028 | E17: =Model_Monthly!P53 -> 700 | F17: =Model_Monthly!P56 -> 0 | G17: =Model_Monthly!P58 -> 10.773278 | H17: =Model_Monthly!P60+Model_Monthly!P62 -> 1053.1599 | I17: =Model_Monthly!P70 -> 714.3849 | J17: =Model_Monthly!P63+Model_Monthly!P64 -> 2451.672 | K17: =Model_Monthly!P72 -> 4977.8381 | L17: =Model_Monthly!P73 -> 75000 | M17: =Model_Monthly!P74 -> 79977.838
A18: =EDATE(Assumptions!$B$5,ROW()-4) -> 46661 | B18: =Model_Monthly!Q5 -> 8.7941051 | C18: =Model_Monthly!Q7 -> 6980.7607 | D18: =Model_Monthly!Q50 -> 47.608788 | E18: =Model_Monthly!Q53 -> 700 | F18: =Model_Monthly!Q56 -> 0 | G18: =Model_Monthly!Q58 -> 10.857048 | H18: =Model_Monthly!Q60+Model_Monthly!Q62 -> 1053.2856 | I18: =Model_Monthly!Q70 -> 714.36298 | J18: =Model_Monthly!Q63+Model_Monthly!Q64 -> 2451.6971 | K18: =Model_Monthly!Q72 -> 4977.8115 | L18: =Model_Monthly!Q73 -> 75000 | M18: =Model_Monthly!Q74 -> 79977.811
A19: =EDATE(Assumptions!$B$5,ROW()-4) -> 46692 | B19: =Model_Monthly!R5 -> 8.7501346 | C19: =Model_Monthly!R7 -> 6945.8569 | D19: =Model_Monthly!R50 -> 47.370744 | E19: =Model_Monthly!R53 -> 700 | F19: =Model_Monthly!R56 -> 0 | G19: =Model_Monthly!R58 -> 10.940398 | H19: =Model_Monthly!R60+Model_Monthly!R62 -> 1053.4106 | I19: =Model_Monthly!R70 -> 714.34116 | J19: =Model_Monthly!R63+Model_Monthly!R64 -> 2451.7221 | K19: =Model_Monthly!R72 -> 4977.785 | L19: =Model_Monthly!R73 -> 75000 | M19: =Model_Monthly!R74 -> 79977.785
A20: =EDATE(Assumptions!$B$5,ROW()-4) -> 46722 | B20: =Model_Monthly!S5 -> 8.7063839 | C20: =Model_Monthly!S7 -> 6911.1276 | D20: =Model_Monthly!S50 -> 47.13389 | E20: =Model_Monthly!S53 -> 700 | F20: =Model_Monthly!S56 -> 0 | G20: =Model_Monthly!S58 -> 11.023331 | H20: =Model_Monthly!S60+Model_Monthly!S62 -> 1053.535 | I20: =Model_Monthly!S70 -> 714.31945 | J20: =Model_Monthly!S63+Model_Monthly!S64 -> 2451.747 | K20: =Model_Monthly!S72 -> 4977.7587 | L20: =Model_Monthly!S73 -> 75000 | M20: =Model_Monthly!S74 -> 79977.759
A21: =EDATE(Assumptions!$B$5,ROW()-4) -> 46753 | B21: =Model_Monthly!T5 -> 8.662852 | C21: =Model_Monthly!T7 -> 6876.5719 | D21: =Model_Monthly!T50 -> 46.898221 | E21: =Model_Monthly!T53 -> 700 | F21: =Model_Monthly!T56 -> 0 | G21: =Model_Monthly!T58 -> 11.10585 | H21: =Model_Monthly!T60+Model_Monthly!T62 -> 1053.6588 | I21: =Model_Monthly!T70 -> 714.29786 | J21: =Model_Monthly!T63+Model_Monthly!T64 -> 2451.7718 | K21: =Model_Monthly!T72 -> 4977.7325 | L21: =Model_Monthly!T73 -> 75000 | M21: =Model_Monthly!T74 -> 79977.732
A22: Total | B22: =SUM(B4:B21) -> 116.09245 | C22: =SUM(C4:C21) -> 92154.184 | D22: =SUM(D4:D21) -> 628.49154 | E22: =SUM(E4:E21) -> 9800 | F22: =SUM(F4:F21) -> 0 | G22: =SUM(G4:G21) -> 188.55021 | H22: =SUM(H4:H21) -> 18948.825 | I22: =SUM(I4:I21) -> 12837.596 | ... M22: =SUM(M4:M21) -> 1436195.9

Sheet Five_Year_TCO
A1: AMS RFP | Five-Year TCO & Value Summary
A2: FORMULA-DRIVEN REVIEW: Consolidates the AI Cost Register and Benefits by required scenario and mandatory classification. Do not overwrite formula cells.
A4: Scenario | B4: Cost Classification | C4: Year 1 | D4: Year 2 | E4: Year 3 | F4: Year 4 | G4: Year 5 | H4: Five-Year TCO | I4: Y1 Benefit | J4: Five-Year Benefit | K4: Net Benefit | L4: Approx. Cost / Agent (Annual) | M4: Avg Annual Cost / Execution | N4: Avg Annual Cost / Successful Outcome | O4: Variance vs PepsiCo Standard
A5: Minimum adoption | B5: One-time | C5: =SUMIFS(Cost_Register!$AC$5:$AC$504,Cost_Register!$C$5:$C$504,$A5,Cost_Register!$F$5:$F$504,$B5) -> 270000 | D5: =SUMIFS(Cost_Register!$AD$5:$AD$504,Cost_Register!$C$5:$C$504,$A5,Cost_Register!$F$5:$F$504,$B5) -> 0 | E5: =SUMIFS(Cost_Register!$AE$5:$AE$504,Cost_Register!$C$5:$C$504,$A5,Cost_Register!$F$5:$F$504,$B5) -> 0 | F5: =SUMIFS(Cost_Register!$AF$5:$AF$504,Cost_Register!$C$5:$C$504,$A5,Cost_Register!$F$5:$F$504,$B5) -> 0 | G5: =SUMIFS(Cost_Register!$AG$5:$AG$504,Cost_Register!$C$5:$C$504,$A5,Cost_Register!$F$5:$F$504,$B5) -> 0 | H5: =SUM(C5:G5) -> 270000 | I5: =SUMIFS(Benefits!$Q$5:$Q$304,Benefits!$C$5:$C$304,$A5)+SUMIFS(Benefits!$R$5:$R$304,Benefits!$C$5:$C$304,$A5) -> 3158375 | J5: =SUMIFS(Benefits!$Q$5:$Q$304,Benefits!$C$5:$C$304,$A5)+SUMIFS(Benefits!$R$5:$R$304,Benefits!$C$5:$C$304,$A5)*5 -> 15791875 | K5: =J5-H5 -> 15521875 | L5: =IFERROR(H5/5/COUNTA(AI_Agent_Inventory!$A$5:$A$201),0) -> 3176.4706 | M5: {=IFERROR((H5/5)/SUMPRODUCT((Demand_Scenarios!$B$5:$B$504=$A5)*Demand_Scenarios!$D$5:$D$504*Demand_Scenarios!$E$5:$E$504*Demand_Scenarios!$F$5:$F$504*Demand_Scenarios!$G$5:$G$504*12),0)} -> 0.93596443 | N5: {=IFERROR((H5/5)/SUMPRODUCT((Demand_Scenarios!$B$5:$B$504=$A5)*Demand_Scenarios!$D$5:$D$504*Demand_Scenarios!$E$5:$E$504*Demand_Scenarios!$F$5:$F$504*Demand_Scenarios!$G$5:$G$504*Demand_Scenarios!$I$5:$I$504*12),0)} -> 1.0173526 | O5: =IFERROR(H5/SUMIFS($H$5:$H$44,$A$5:$A$44,"PepsiCo standard")-1,0) -> -0.95166314
A6: Minimum adoption | B6: Recurring fixed | C6: =SUMIFS(Cost_Register!$AC$5:$AC$504,Cost_Register!$C$5:$C$504,$A6,Cost_Register!$F$5:$F$504,$B6) -> 646391.88 | D6: =SUMIFS(Cost_Register!$AD$5:$AD$504,Cost_Register!$C$5:$C$504,$A6,Cost_Register!$F$5:$F$504,$B6) -> 665783.64 | E6: =SUMIFS(Cost_Register!$AE$5:$AE$504,Cost_Register!$C$5:$C$504,$A6,Cost_Register!$F$5:$F$504,$B6) -> 685757.15 | F6: =SUMIFS(Cost_Register!$AF$5:$AF$504,Cost_Register!$C$5:$C$504,$A6,Cost_Register!$F$5:$F$504,$B6) -> 706329.86 | G6: =SUMIFS(Cost_Register!$AG$5:$AG$504,Cost_Register!$C$5:$C$504,$A6,Cost_Register!$F$5:$F$504,$B6) -> 727519.76 | H6: =SUM(C6:G6) -> 3431782.3 | I6: =SUMIFS(Benefits!$Q$5:$Q$304,Benefits!$C$5:$C$304,$A6)+SUMIFS(Benefits!$R$5:$R$304,Benefits!$C$5:$C$304,$A6) -> 3158375 | J6: =SUMIFS(Benefits!$Q$5:$Q$304,Benefits!$C$5:$C$304,$A6)+SUMIFS(Benefits!$R$5:$R$304,Benefits!$C$5:$C$304,$A6)*5 -> 15791875 | K6: =J6-H6 -> 12360093 | L6: =IFERROR(H6/5/COUNTA(AI_Agent_Inventory!$A$5:$A$201),0) -> 40373.909 | M6: {=IFERROR((H6/5)/SUMPRODUCT((Demand_Scenarios!$B$5:$B$504=$A6)*Demand_Scenarios!$D$5:$D$504*Demand_Scenarios!$E$5:$E$504*Demand_Scenarios!$F$5:$F$504*Demand_Scenarios!$G$5:$G$504*12),0)} -> 11.896393 | N6: {=IFERROR((H6/5)/SUMPRODUCT((Demand_Scenarios!$B$5:$B$504=$A6)*Demand_Scenarios!$D$5:$D$504*Demand_Scenarios!$E$5:$E$504*Demand_Scenarios!$F$5:$F$504*Demand_Scenarios!$G$5:$G$504*Demand_Scenarios!$I$5:$I$504*12),0)} -> 12.930862 | O6: =IFERROR(H6/SUMIFS($H$5:$H$44,$A$5:$A$44,"PepsiCo standard")-1,0) -> -0.38562381
A7: Minimum adoption | B7: Recurring variable | C7: =SUMIFS(Cost_Register!$AC$5:$AC$504,Cost_Register!$C$5:$C$504,$A7,Cost_Register!$F$5:$F$504,$B7) -> 750 | D7: =SUMIFS(Cost_Register!$AD$5:$AD$504,Cost_Register!$C$5:$C$504,$A7,Cost_Register!$F$5:$F$504,$B7) -> 825 | E7: =SUMIFS(Cost_Register!$AE$5:$AE$504,Cost_Register!$C$5:$C$504,$A7,Cost_Register!$F$5:$F$504,$B7) -> 907.5 | F7: =SUMIFS(Cost_Register!$AF$5:$AF$504,Cost_Register!$C$5:$C$504,$A7,Cost_Register!$F$5:$F$504,$B7) -> 998.25 | G7: =SUMIFS(Cost_Register!$AG$5:$AG$504,Cost_Register!$C$5:$C$504,$A7,Cost_Register!$F$5:$F$504,$B7) -> 1098.075 | H7: =SUM(C7:G7) -> 4578.825 | I7: =SUMIFS(Benefits!$Q$5:$Q$304,Benefits!$C$5:$C$304,$A7)+SUMIFS(Benefits!$R$5:$R$304,Benefits!$C$5:$C$304,$A7) -> 3158375 | J7: =SUMIFS(Benefits!$Q$5:$Q$304,Benefits!$C$5:$C$304,$A7)+SUMIFS(Benefits!$R$5:$R$304,Benefits!$C$5:$C$304,$A7)*5 -> 15791875 | K7: =J7-H7 -> 15787296 | L7: =IFERROR(H7/5/COUNTA(AI_Agent_Inventory!$A$5:$A$201),0) -> 53.868529 | M7: {=IFERROR((H7/5)/SUMPRODUCT((Demand_Scenarios!$B$5:$B$504=$A7)*Demand_Scenarios!$D$5:$D$504*Demand_Scenarios!$E$5:$E$504*Demand_Scenarios!$F$5:$F$504*Demand_Scenarios!$G$5:$G$504*12),0)} -> 0.015872657 | N7: {=IFERROR((H7/5)/SUMPRODUCT((Demand_Scenarios!$B$5:$B$504=$A7)*Demand_Scenarios!$D$5:$D$504*Demand_Scenarios!$E$5:$E$504*Demand_Scenarios!$F$5:$F$504*Demand_Scenarios!$G$5:$G$504*Demand_Scenarios!$I$5:$I$504*12),0)} -> 0.017252888 | O7: =IFERROR(H7/SUMIFS($H$5:$H$44,$A$5:$A$44,"PepsiCo standard")-1,0) -> -0.99918027
A8: Minimum adoption | B8: Pass-through | C8: =SUMIFS(Cost_Register!$AC$5:$AC$504,Cost_Register!$C$5:$C$504,$A8,Cost_Register!$F$5:$F$504,$B8) -> 0 | D8: =SUMIFS(Cost_Register!$AD$5:$AD$504,Cost_Register!$C$5:$C$504,$A8,Cost_Register!$F$5:$F$504,$B8) -> 0 | E8: =SUMIFS(Cost_Register!$AE$5:$AE$504,Cost_Register!$C$5:$C$504,$A8,Cost_Register!$F$5:$F$504,$B8) -> 0 | F8: =SUMIFS(Cost_Register!$AF$5:$AF$504,Cost_Register!$C$5:$C$504,$A8,Cost_Register!$F$5:$F$504,$B8) -> 0 | G8: =SUMIFS(Cost_Register!$AG$5:$AG$504,Cost_Register!$C$5:$C$504,$A8,Cost_Register!$F$5:$F$504,$B8) -> 0 | H8: =SUM(C8:G8) -> 0 | I8: =SUMIFS(Benefits!$Q$5:$Q$304,Benefits!$C$5:$C$304,$A8)+SUMIFS(Benefits!$R$5:$R$304,Benefits!$C$5:$C$304,$A8) -> 3158375 | J8: =SUMIFS(Benefits!$Q$5:$Q$304,Benefits!$C$5:$C$304,$A8)+SUMIFS(Benefits!$R$5:$R$304,Benefits!$C$5:$C$304,$A8)*5 -> 15791875 | K8: =J8-H8 -> 15791875 | L8: =IFERROR(H8/5/COUNTA(AI_Agent_Inventory!$A$5:$A$201),0) -> 0 | M8: {=IFERROR((H8/5)/SUMPRODUCT((Demand_Scenarios!$B$5:$B$504=$A8)*Demand_Scenarios!$D$5:$D$504*Demand_Scenarios!$E$5:$E$504*Demand_Scenarios!$F$5:$F$504*Demand_Scenarios!$G$5:$G$504*12),0)} -> 0 | N8: {=IFERROR((H8/5)/SUMPRODUCT((Demand_Scenarios!$B$5:$B$504=$A8)*Demand_Scenarios!$D$5:$D$504*Demand_Scenarios!$E$5:$E$504*Demand_Scenarios!$F$5:$F$504*Demand_Scenarios!$G$5:$G$504*Demand_Scenarios!$I$5:$I$504*12),0)} -> 0 | O8: =IFERROR(H8/SUMIFS($H$5:$H$44,$A$5:$A$44,"PepsiCo standard")-1,0) -> -1
A9: Minimum adoption | B9: Optional | C9: =SUMIFS(Cost_Register!$AC$5:$AC$504,Cost_Register!$C$5:$C$504,$A9,Cost_Register!$F$5:$F$504,$B9) -> 0 | D9: =SUMIFS(Cost_Register!$AD$5:$AD$504,Cost_Register!$C$5:$C$504,$A9,Cost_Register!$F$5:$F$504,$B9) -> 0 | E9: =SUMIFS(Cost_Register!$AE$5:$AE$504,Cost_Register!$C$5:$C$504,$A9,Cost_Register!$F$5:$F$504,$B9) -> 0 | F9: =SUMIFS(Cost_Register!$AF$5:$AF$504,Cost_Register!$C$5:$C$504,$A9,Cost_Register!$F$5:$F$504,$B9) -> 0 | G9: =SUMIFS(Cost_Register!$AG$5:$AG$504,Cost_Register!$C$5:$C$504,$A9,Cost_Register!$F$5:$F$504,$B9) -> 0 | H9: =SUM(C9:G9) -> 0 | I9: =SUMIFS(Benefits!$Q$5:$Q$304,Benefits!$C$5:$C$304,$A9)+SUMIFS(Benefits!$R$5:$R$304,Benefits!$C$5:$C$304,$A9) -> 3158375 | J9: =SUMIFS(Benefits!$Q$5:$Q$304,Benefits!$C$5:$C$304,$A9)+SUMIFS(Benefits!$R$5:$R$304,Benefits!$C$5:$C$304,$A9)*5 -> 15791875 | K9: =J9-H9 -> 15791875 | L9: =IFERROR(H9/5/COUNTA(AI_Agent_Inventory!$A$5:$A$201),0) -> 0 | M9: {=IFERROR((H9/5)/SUMPRODUCT((Demand_Scenarios!$B$5:$B$504=$A9)*Demand_Scenarios!$D$5:$D$504*Demand_Scenarios!$E$5:$E$504*Demand_Scenarios!$F$5:$F$504*Demand_Scenarios!$G$5:$G$504*12),0)} -> 0 | N9: {=IFERROR((H9/5)/SUMPRODUCT((Demand_Scenarios!$B$5:$B$504=$A9)*Demand_Scenarios!$D$5:$D$504*Demand_Scenarios!$E$5:$E$504*Demand_Scenarios!$F$5:$F$504*Demand_Scenarios!$G$5:$G$504*Demand_Scenarios!$I$5:$I$504*12),0)} -> 0 | O9: =IFERROR(H9/SUMIFS($H$5:$H$44,$A$5:$A$44,"PepsiCo standard")-1,0) -> -1
A10: Minimum adoption | B10: PepsiCo-funded | C10: =SUMIFS(Cost_Register!$AC$5:$AC$504,Cost_Register!$C$5:$C$504,$A10,Cost_Register!$F$5:$F$504,$B10) -> 0 | D10: =SUMIFS(Cost_Register!$AD$5:$AD$504,Cost_Register!$C$5:$C$504,$A10,Cost_Register!$F$5:$F$504,$B10) -> 0 | E10: =SUMIFS(Cost_Register!$AE$5:$AE$504,Cost_Register!$C$5:$C$504,$A10,Cost_Register!$F$5:$F$504,$B10) -> 0 | F10: =SUMIFS(Cost_Register!$AF$5:$AF$504,Cost_Register!$C$5:$C$504,$A10,Cost_Register!$F$5:$F$504,$B10) -> 0 | G10: =SUMIFS(Cost_Register!$AG$5:$AG$504,Cost_Register!$C$5:$C$504,$A10,Cost_Register!$F$5:$F$504,$B10) -> 0 | H10: =SUM(C10:G10) -> 0 | I10: =SUMIFS(Benefits!$Q$5:$Q$304,Benefits!$C$5:$C$304,$A10)+SUMIFS(Benefits!$R$5:$R$304,Benefits!$C$5:$C$304,$A10) -> 3158375 | J10: =SUMIFS(Benefits!$Q$5:$Q$304,Benefits!$C$5:$C$304,$A10)+SUMIFS(Benefits!$R$5:$R$304,Benefits!$C$5:$C$304,$A10)*5 -> 15791875 | K10: =J10-H10 -> 15791875 | L10: =IFERROR(H10/5/COUNTA(AI_Agent_Inventory!$A$5:$A$201),0) -> 0 | M10: {=IFERROR((H10/5)/SUMPRODUCT((Demand_Scenarios!$B$5:$B$504=$A10)*Demand_Scenarios!$D$5:$D$504*Demand_Scenarios!$E$5:$E$504*Demand_Scenarios!$F$5:$F$504*Demand_Scenarios!$G$5:$G$504*12),0)} -> 0 | N10: {=IFERROR((H10/5)/SUMPRODUCT((Demand_Scenarios!$B$5:$B$504=$A10)*Demand_Scenarios!$D$5:$D$504*Demand_Scenarios!$E$5:$E$504*Demand_Scenarios!$F$5:$F$504*Demand_Scenarios!$G$5:$G$504*Demand_Scenarios!$I$5:$I$504*12),0)} -> 0 | O10: =IFERROR(H10/SUMIFS($H$5:$H$44,$A$5:$A$44,"PepsiCo standard")-1,0) -> -1
A11: Minimum adoption | B11: Change/lifecycle | C11: =SUMIFS(Cost_Register!$AC$5:$AC$504,Cost_Register!$C$5:$C$504,$A11,Cost_Register!$F$5:$F$504,$B11) -> 0 | D11: =SUMIFS(Cost_Register!$AD$5:$AD$504,Cost_Register!$C$5:$C$504,$A11,Cost_Register!$F$5:$F$504,$B11) -> 0 | E11: =SUMIFS(Cost_Register!$AE$5:$AE$504,Cost_Register!$C$5:$C$504,$A11,Cost_Register!$F$5:$F$504,$B11) -> 0 | F11: =SUMIFS(Cost_Register!$AF$5:$AF$504,Cost_Register!$C$5:$C$504,$A11,Cost_Register!$F$5:$F$504,$B11) -> 0 | G11: =SUMIFS(Cost_Register!$AG$5:$AG$504,Cost_Register!$C$5:$C$504,$A11,Cost_Register!$F$5:$F$504,$B11) -> 0 | H11: =SUM(C11:G11) -> 0 | I11: =SUMIFS(Benefits!$Q$5:$Q$304,Benefits!$C$5:$C$304,$A11)+SUMIFS(Benefits!$R$5:$R$304,Benefits!$C$5:$C$304,$A11) -> 3158375 | J11: =SUMIFS(Benefits!$Q$5:$Q$304,Benefits!$C$5:$C$304,$A11)+SUMIFS(Benefits!$R$5:$R$304,Benefits!$C$5:$C$304,$A11)*5 -> 15791875 | K11: =J11-H11 -> 15791875 | L11: =IFERROR(H11/5/COUNTA(AI_Agent_Inventory!$A$5:$A$201),0) -> 0 | M11: {=IFERROR((H11/5)/SUMPRODUCT((Demand_Scenarios!$B$5:$B$504=$A11)*Demand_Scenarios!$D$5:$D$504*Demand_Scenarios!$E$5:$E$504*Demand_Scenarios!$F$5:$F$504*Demand_Scenarios!$G$5:$G$504*12),0)} -> 0 | N11: {=IFERROR((H11/5)/SUMPRODUCT((Demand_Scenarios!$B$5:$B$504=$A11)*Demand_Scenarios!$D$5:$D$504*Demand_Scenarios!$E$5:$E$504*Demand_Scenarios!$F$5:$F$504*Demand_Scenarios!$G$5:$G$504*Demand_Scenarios!$I$5:$I$504*12),0)} -> 0 | O11: =IFERROR(H11/SUMIFS($H$5:$H$44,$A$5:$A$44,"PepsiCo standard")-1,0) -> -1
A12: Minimum adoption | B12: Exit-related | C12: =SUMIFS(Cost_Register!$AC$5:$AC$504,Cost_Register!$C$5:$C$504,$A12,Cost_Register!$F$5:$F$504,$B12) -> 0 | D12: =SUMIFS(Cost_Register!$AD$5:$AD$504,Cost_Register!$C$5:$C$504,$A12,Cost_Register!$F$5:$F$504,$B12) -> 0 | E12: =SUMIFS(Cost_Register!$AE$5:$AE$504,Cost_Register!$C$5:$C$504,$A12,Cost_Register!$F$5:$F$504,$B12) -> 0 | F12: =SUMIFS(Cost_Register!$AF$5:$AF$504,Cost_Register!$C$5:$C$504,$A12,Cost_Register!$F$5:$F$504,$B12) -> 0 | G12: =SUMIFS(Cost_Register!$AG$5:$AG$504,Cost_Register!$C$5:$C$504,$A12,Cost_Register!$F$5:$F$504,$B12) -> 100000 | H12: =SUM(C12:G12) -> 100000 | I12: =SUMIFS(Benefits!$Q$5:$Q$304,Benefits!$C$5:$C$304,$A12)+SUMIFS(Benefits!$R$5:$R$304,Benefits!$C$5:$C$304,$A12) -> 3158375 | J12: =SUMIFS(Benefits!$Q$5:$Q$304,Benefits!$C$5:$C$304,$A12)+SUMIFS(Benefits!$R$5:$R$304,Benefits!$C$5:$C$304,$A12)*5 -> 15791875 | K12: =J12-H12 -> 15691875 | L12: =IFERROR(H12/5/COUNTA(AI_Agent_Inventory!$A$5:$A$201),0) -> 1176.4706 | M12: {=IFERROR((H12/5)/SUMPRODUCT((Demand_Scenarios!$B$5:$B$504=$A12)*Demand_Scenarios!$D$5:$D$504*Demand_Scenarios!$E$5:$E$504*Demand_Scenarios!$F$5:$F$504*Demand_Scenarios!$G$5:$G$504*12),0)} -> 0.34665349 | N12: {=IFERROR((H12/5)/SUMPRODUCT((Demand_Scenarios!$B$5:$B$504=$A12)*Demand_Scenarios!$D$5:$D$504*Demand_Scenarios!$E$5:$E$504*Demand_Scenarios!$F$5:$F$504*Demand_Scenarios!$G$5:$G$504*Demand_Scenarios!$I$5:$I$504*12),0)} -> 0.37679728 | O12: =IFERROR(H12/SUMIFS($H$5:$H$44,$A$5:$A$44,"PepsiCo standard")-1,0) -> -0.98209746
A13: Minimum adoption | B13: TOTAL | C13: =SUM(C5:C12) -> 917141.88 | D13: =SUM(D5:D12) -> 666608.64 | E13: =SUM(E5:E12) -> 686664.65 | F13: =SUM(F5:F12) -> 707328.11 | G13: =SUM(G5:G12) -> 828617.83 | H13: =SUM(H5:H12) -> 3806361.1 | I13: =SUMIFS(Benefits!$Q$5:$Q$304,Benefits!$C$5:$C$304,$A13)+SUMIFS(Benefits!$R$5:$R$304,Benefits!$C$5:$C$304,$A13) -> 3158375 | J13: =SUMIFS(Benefits!$Q$5:$Q$304,Benefits!$C$5:$C$304,$A13)+SUMIFS(Benefits!$R$5:$R$304,Benefits!$C$5:$C$304,$A13)*5 -> 15791875 | K13: =J13-H13 -> 11985514 | L13: =IFERROR(H13/5/COUNTA(AI_Agent_Inventory!$A$5:$A$201),0) -> 44780.719 | M13: {=IFERROR((H13/5)/SUMPRODUCT((Demand_Scenarios!$B$5:$B$504=$A13)*Demand_Scenarios!$D$5:$D$504*Demand_Scenarios!$E$5:$E$504*Demand_Scenarios!$F$5:$F$504*Demand_Scenarios!$G$5:$G$504*12),0)} -> 13.194884 | N13: {=IFERROR((H13/5)/SUMPRODUCT((Demand_Scenarios!$B$5:$B$504=$A13)*Demand_Scenarios!$D$5:$D$504*Demand_Scenarios!$E$5:$E$504*Demand_Scenarios!$F$5:$F$504*Demand_Scenarios!$G$5:$G$504*Demand_Scenarios!$I$5:$I$504*12),0)} -> 14.342265 | O13: =IFERROR(H13/SUMIFS($H$5:$H$49,$A$5:$A$49,"PepsiCo standard",$B$5:$B$49,"TOTAL")-1,0) -> -0.33054955
A14: Expected case | B14: One-time | C14: =SUMIFS(Cost_Register!$AC$5:$AC$504,Cost_Register!$C$5:$C$504,$A14,Cost_Register!$F$5:$F$504,$B14) -> 450000 | D14: =SUMIFS(Cost_Register!$AD$5:$AD$504,Cost_Register!$C$5:$C$504,$A14,Cost_Register!$F$5:$F$504,$B14) -> 0 | E14: =SUMIFS(Cost_Register!$AE$5:$AE$504,Cost_Register!$C$5:$C$504,$A14,Cost_Register!$F$5:$F$504,$B14) -> 0 | F14: =SUMIFS(Cost_Register!$AF$5:$AF$504,Cost_Register!$C$5:$C$504,$A14,Cost_Register!$F$5:$F$504,$B14) -> 0 | G14: =SUMIFS(Cost_Register!$AG$5:$AG$504,Cost_Register!$C$5:$C$504,$A14,Cost_Register!$F$5:$F$504,$B14) -> 0 | H14: =SUM(C14:G14) -> 450000 | I14: =SUMIFS(Benefits!$Q$5:$Q$304,Benefits!$C$5:$C$304,$A14)+SUMIFS(Benefits!$R$5:$R$304,Benefits!$C$5:$C$304,$A14) -> 7580100 | J14: =SUMIFS(Benefits!$Q$5:$Q$304,Benefits!$C$5:$C$304,$A14)+SUMIFS(Benefits!$R$5:$R$304,Benefits!$C$5:$C$304,$A14)*5 -> 37900500 | K14: =J14-H14 -> 37450500 | L14: =IFERROR(H14/5/COUNTA(AI_Agent_Inventory!$A$5:$A$201),0) -> 5294.1176 | M14: {=IFERROR((H14/5)/SUMPRODUCT((Demand_Scenarios!$B$5:$B$504=$A14)*Demand_Scenarios!$D$5:$D$504*Demand_Scenarios!$E$5:$E$504*Demand_Scenarios!$F$5:$F$504*Demand_Scenarios!$G$5:$G$504*12),0)} -> 0.6499753 | N14: {=IFERROR((H14/5)/SUMPRODUCT((Demand_Scenarios!$B$5:$B$504=$A14)*Demand_Scenarios!$D$5:$D$504*Demand_Scenarios!$E$5:$E$504*Demand_Scenarios!$F$5:$F$504*Demand_Scenarios!$G$5:$G$504*Demand_Scenarios!$I$5:$I$504*12),0)} -> 0.69146309 | O14: =IFERROR(H14/SUMIFS($H$5:$H$44,$A$5:$A$44,"PepsiCo standard")-1,0) -> -0.91943857
A15: Expected case | B15: Recurring fixed | C15: =SUMIFS(Cost_Register!$AC$5:$AC$504,Cost_Register!$C$5:$C$504,$A15,Cost_Register!$F$5:$F$504,$B15) -> 964764 | D15: =SUMIFS(Cost_Register!$AD$5:$AD$504,Cost_Register!$C$5:$C$504,$A15,Cost_Register!$F$5:$F$504,$B15) -> 993706.92 | E15: =SUMIFS(Cost_Register!$AE$5:$AE$504,Cost_Register!$C$5:$C$504,$A15,Cost_Register!$F$5:$F$504,$B15) -> 1023518.1 | F15: =SUMIFS(Cost_Register!$AF$5:$AF$504,Cost_Register!$C$5:$C$504,$A15,Cost_Register!$F$5:$F$504,$B15) -> 1054223.7 | G15: =SUMIFS(Cost_Register!$AG$5:$AG$504,Cost_Register!$C$5:$C$504,$A15,Cost_Register!$F$5:$F$504,$B15) -> 1085850.4 | H15: =SUM(C15:G15) -> 5122063.1 | I15: =SUMIFS(Benefits!$Q$5:$Q$304,Benefits!$C$5:$C$304,$A15)+SUMIFS(Benefits!$R$5:$R$304,Benefits!$C$5:$C$304,$A15) -> 7580100 | J15: =SUMIFS(Benefits!$Q$5:$Q$304,Benefits!$C$5:$C$304,$A15)+SUMIFS(Benefits!$R$5:$R$304,Benefits!$C$5:$C$304,$A15)*5 -> 37900500 | K15: =J15-H15 -> 32778437 | L15: =IFERROR(H15/5/COUNTA(AI_Agent_Inventory!$A$5:$A$201),0) -> 60259.566 | M15: {=IFERROR((H15/5)/SUMPRODUCT((Demand_Scenarios!$B$5:$B$504=$A15)*Demand_Scenarios!$D$5:$D$504*Demand_Scenarios!$E$5:$E$504*Demand_Scenarios!$F$5:$F$504*Demand_Scenarios!$G$5:$G$504*12),0)} -> 7.3982545 | N15: {=IFERROR((H15/5)/SUMPRODUCT((Demand_Scenarios!$B$5:$B$504=$A15)*Demand_Scenarios!$D$5:$D$504*Demand_Scenarios!$E$5:$E$504*Demand_Scenarios!$F$5:$F$504*Demand_Scenarios!$G$5:$G$504*Demand_Scenarios!$I$5:$I$504*12),0)} -> 7.8704835 | O15: =IFERROR(H15/SUMIFS($H$5:$H$44,$A$5:$A$44,"PepsiCo standard")-1,0) -> -0.083020608
A16: Expected case | B16: Recurring variable | C16: =SUMIFS(Cost_Register!$AC$5:$AC$504,Cost_Register!$C$5:$C$504,$A16,Cost_Register!$F$5:$F$504,$B16) -> 1750 | D16: =SUMIFS(Cost_Register!$AD$5:$AD$504,Cost_Register!$C$5:$C$504,$A16,Cost_Register!$F$5:$F$504,$B16) -> 1925 | E16: =SUMIFS(Cost_Register!$AE$5:$AE$504,Cost_Register!$C$5:$C$504,$A16,Cost_Register!$F$5:$F$504,$B16) -> 2117.5 | F16: =SUMIFS(Cost_Register!$AF$5:$AF$504,Cost_Register!$C$5:$C$504,$A16,Cost_Register!$F$5:$F$504,$B16) -> 2329.25 | G16: =SUMIFS(Cost_Register!$AG$5:$AG$504,Cost_Register!$C$5:$C$504,$A16,Cost_Register!$F$5:$F$504,$B16) -> 2562.175 | H16: =SUM(C16:G16) -> 10683.925 | I16: =SUMIFS(Benefits!$Q$5:$Q$304,Benefits!$C$5:$C$304,$A16)+SUMIFS(Benefits!$R$5:$R$304,Benefits!$C$5:$C$304,$A16) -> 7580100 | J16: =SUMIFS(Benefits!$Q$5:$Q$304,Benefits!$C$5:$C$304,$A16)+SUMIFS(Benefits!$R$5:$R$304,Benefits!$C$5:$C$304,$A16)*5 -> 37900500 | K16: =J16-H16 -> 37889816 | L16: =IFERROR(H16/5/COUNTA(AI_Agent_Inventory!$A$5:$A$201),0) -> 125.69324 | M16: {=IFERROR((H16/5)/SUMPRODUCT((Demand_Scenarios!$B$5:$B$504=$A16)*Demand_Scenarios!$D$5:$D$504*Demand_Scenarios!$E$5:$E$504*Demand_Scenarios!$F$5:$F$504*Demand_Scenarios!$G$5:$G$504*12),0)} -> 0.01543175 | N16: {=IFERROR((H16/5)/SUMPRODUCT((Demand_Scenarios!$B$5:$B$504=$A16)*Demand_Scenarios!$D$5:$D$504*Demand_Scenarios!$E$5:$E$504*Demand_Scenarios!$F$5:$F$504*Demand_Scenarios!$G$5:$G$504*Demand_Scenarios!$I$5:$I$504*12),0)} -> 0.016416755 | O16: =IFERROR(H16/SUMIFS($H$5:$H$44,$A$5:$A$44,"PepsiCo standard")-1,0) -> -0.99808731
A17: Expected case | B17: Pass-through | C17: =SUMIFS(Cost_Register!$AC$5:$AC$504,Cost_Register!$C$5:$C$504,$A17,Cost_Register!$F$5:$F$504,$B17) -> 0 | D17: =SUMIFS(Cost_Register!$AD$5:$AD$504,Cost_Register!$C$5:$C$504,$A17,Cost_Register!$F$5:$F$504,$B17) -> 0 | E17: =SUMIFS(Cost_Register!$AE$5:$AE$504,Cost_Register!$C$5:$C$504,$A17,Cost_Register!$F$5:$F$504,$B17) -> 0 | F17: =SUMIFS(Cost_Register!$AF$5:$AF$504,Cost_Register!$C$5:$C$504,$A17,Cost_Register!$F$5:$F$504,$B17) -> 0 | G17: =SUMIFS(Cost_Register!$AG$5:$AG$504,Cost_Register!$C$5:$C$504,$A17,Cost_Register!$F$5:$F$504,$B17) -> 0 | H17: =SUM(C17:G17) -> 0 | I17: =SUMIFS(Benefits!$Q$5:$Q$304,Benefits!$C$5:$C$304,$A17)+SUMIFS(Benefits!$R$5:$R$304,Benefits!$C$5:$C$304,$A17) -> 7580100 | J17: =SUMIFS(Benefits!$Q$5:$Q$304,Benefits!$C$5:$C$304,$A17)+SUMIFS(Benefits!$R$5:$R$304,Benefits!$C$5:$C$304,$A17)*5 -> 37900500 | K17: =J17-H17 -> 37900500 | L17: =IFERROR(H17/5/COUNTA(AI_Agent_Inventory!$A$5:$A$201),0) -> 0 | M17: {=IFERROR((H17/5)/SUMPRODUCT((Demand_Scenarios!$B$5:$B$504=$A17)*Demand_Scenarios!$D$5:$D$504*Demand_Scenarios!$E$5:$E$504*Demand_Scenarios!$F$5:$F$504*Demand_Scenarios!$G$5:$G$504*12),0)} -> 0 | N17: {=IFERROR((H17/5)/SUMPRODUCT((Demand_Scenarios!$B$5:$B$504=$A17)*Demand_Scenarios!$D$5:$D$504*Demand_Scenarios!$E$5:$E$504*Demand_Scenarios!$F$5:$F$504*Demand_Scenarios!$G$5:$G$504*Demand_Scenarios!$I$5:$I$504*12),0)} -> 0 | O17: =IFERROR(H17/SUMIFS($H$5:$H$44,$A$5:$A$44,"PepsiCo standard")-1,0) -> -1
A18: Expected case | B18: Optional | C18: =SUMIFS(Cost_Register!$AC$5:$AC$504,Cost_Register!$C$5:$C$504,$A18,Cost_Register!$F$5:$F$504,$B18) -> 0 | D18: =SUMIFS(Cost_Register!$AD$5:$AD$504,Cost_Register!$C$5:$C$504,$A18,Cost_Register!$F$5:$F$504,$B18) -> 0 | E18: =SUMIFS(Cost_Register!$AE$5:$AE$504,Cost_Register!$C$5:$C$504,$A18,Cost_Register!$F$5:$F$504,$B18) -> 0 | F18: =SUMIFS(Cost_Register!$AF$5:$AF$504,Cost_Register!$C$5:$C$504,$A18,Cost_Register!$F$5:$F$504,$B18) -> 0 | G18: =SUMIFS(Cost_Register!$AG$5:$AG$504,Cost_Register!$C$5:$C$504,$A18,Cost_Register!$F$5:$F$504,$B18) -> 0 | H18: =SUM(C18:G18) -> 0 | I18: =SUMIFS(Benefits!$Q$5:$Q$304,Benefits!$C$5:$C$304,$A18)+SUMIFS(Benefits!$R$5:$R$304,Benefits!$C$5:$C$304,$A18) -> 7580100 | J18: =SUMIFS(Benefits!$Q$5:$Q$304,Benefits!$C$5:$C$304,$A18)+SUMIFS(Benefits!$R$5:$R$304,Benefits!$C$5:$C$304,$A18)*5 -> 37900500 | K18: =J18-H18 -> 37900500 | L18: =IFERROR(H18/5/COUNTA(AI_Agent_Inventory!$A$5:$A$201),0) -> 0 | M18: {=IFERROR((H18/5)/SUMPRODUCT((Demand_Scenarios!$B$5:$B$504=$A18)*Demand_Scenarios!$D$5:$D$504*Demand_Scenarios!$E$5:$E$504*Demand_Scenarios!$F$5:$F$504*Demand_Scenarios!$G$5:$G$504*12),0)} -> 0 | N18: {=IFERROR((H18/5)/SUMPRODUCT((Demand_Scenarios!$B$5:$B$504=$A18)*Demand_Scenarios!$D$5:$D$504*Demand_Scenarios!$E$5:$E$504*Demand_Scenarios!$F$5:$F$504*Demand_Scenarios!$G$5:$G$504*Demand_Scenarios!$I$5:$I$504*12),0)} -> 0 | O18: =IFERROR(H18/SUMIFS($H$5:$H$44,$A$5:$A$44,"PepsiCo standard")-1,0) -> -1
A19: Expected case | B19: PepsiCo-funded | C19: =SUMIFS(Cost_Register!$AC$5:$AC$504,Cost_Register!$C$5:$C$504,$A19,Cost_Register!$F$5:$F$504,$B19) -> 0 | D19: =SUMIFS(Cost_Register!$AD$5:$AD$504,Cost_Register!$C$5:$C$504,$A19,Cost_Register!$F$5:$F$504,$B19) -> 0 | E19: =SUMIFS(Cost_Register!$AE$5:$AE$504,Cost_Register!$C$5:$C$504,$A19,Cost_Register!$F$5:$F$504,$B19) -> 0 | F19: =SUMIFS(Cost_Register!$AF$5:$AF$504,Cost_Register!$C$5:$C$504,$A19,Cost_Register!$F$5:$F$504,$B19) -> 0 | G19: =SUMIFS(Cost_Register!$AG$5:$AG$504,Cost_Register!$C$5:$C$504,$A19,Cost_Register!$F$5:$F$504,$B19) -> 0 | H19: =SUM(C19:G19) -> 0 | I19: =SUMIFS(Benefits!$Q$5:$Q$304,Benefits!$C$5:$C$304,$A19)+SUMIFS(Benefits!$R$5:$R$304,Benefits!$C$5:$C$304,$A19) -> 7580100 | J19: =SUMIFS(Benefits!$Q$5:$Q$304,Benefits!$C$5:$C$304,$A19)+SUMIFS(Benefits!$R$5:$R$304,Benefits!$C$5:$C$304,$A19)*5 -> 37900500 | K19: =J19-H19 -> 37900500 | L19: =IFERROR(H19/5/COUNTA(AI_Agent_Inventory!$A$5:$A$201),0) -> 0 | M19: {=IFERROR((H19/5)/SUMPRODUCT((Demand_Scenarios!$B$5:$B$504=$A19)*Demand_Scenarios!$D$5:$D$504*Demand_Scenarios!$E$5:$E$504*Demand_Scenarios!$F$5:$F$504*Demand_Scenarios!$G$5:$G$504*12),0)} -> 0 | N19: {=IFERROR((H19/5)/SUMPRODUCT((Demand_Scenarios!$B$5:$B$504=$A19)*Demand_Scenarios!$D$5:$D$504*Demand_Scenarios!$E$5:$E$504*Demand_Scenarios!$F$5:$F$504*Demand_Scenarios!$G$5:$G$504*Demand_Scenarios!$I$5:$I$504*12),0)} -> 0 | O19: =IFERROR(H19/SUMIFS($H$5:$H$44,$A$5:$A$44,"PepsiCo standard")-1,0) -> -1
A20: Expected case | B20: Change/lifecycle | C20: =SUMIFS(Cost_Register!$AC$5:$AC$504,Cost_Register!$C$5:$C$504,$A20,Cost_Register!$F$5:$F$504,$B20) -> 0 | D20: =SUMIFS(Cost_Register!$AD$5:$AD$504,Cost_Register!$C$5:$C$504,$A20,Cost_Register!$F$5:$F$504,$B20) -> 0 | E20: =SUMIFS(Cost_Register!$AE$5:$AE$504,Cost_Register!$C$5:$C$504,$A20,Cost_Register!$F$5:$F$504,$B20) -> 0 | F20: =SUMIFS(Cost_Register!$AF$5:$AF$504,Cost_Register!$C$5:$C$504,$A20,Cost_Register!$F$5:$F$504,$B20) -> 0 | G20: =SUMIFS(Cost_Register!$AG$5:$AG$504,Cost_Register!$C$5:$C$504,$A20,Cost_Register!$F$5:$F$504,$B20) -> 0 | H20: =SUM(C20:G20) -> 0 | I20: =SUMIFS(Benefits!$Q$5:$Q$304,Benefits!$C$5:$C$304,$A20)+SUMIFS(Benefits!$R$5:$R$304,Benefits!$C$5:$C$304,$A20) -> 7580100 | J20: =SUMIFS(Benefits!$Q$5:$Q$304,Benefits!$C$5:$C$304,$A20)+SUMIFS(Benefits!$R$5:$R$304,Benefits!$C$5:$C$304,$A20)*5 -> 37900500 | K20: =J20-H20 -> 37900500 | L20: =IFERROR(H20/5/COUNTA(AI_Agent_Inventory!$A$5:$A$201),0) -> 0 | M20: {=IFERROR((H20/5)/SUMPRODUCT((Demand_Scenarios!$B$5:$B$504=$A20)*Demand_Scenarios!$D$5:$D$504*Demand_Scenarios!$E$5:$E$504*Demand_Scenarios!$F$5:$F$504*Demand_Scenarios!$G$5:$G$504*12),0)} -> 0 | N20: {=IFERROR((H20/5)/SUMPRODUCT((Demand_Scenarios!$B$5:$B$504=$A20)*Demand_Scenarios!$D$5:$D$504*Demand_Scenarios!$E$5:$E$504*Demand_Scenarios!$F$5:$F$504*Demand_Scenarios!$G$5:$G$504*Demand_Scenarios!$I$5:$I$504*12),0)} -> 0 | O20: =IFERROR(H20/SUMIFS($H$5:$H$44,$A$5:$A$44,"PepsiCo standard")-1,0) -> -1
A21: Expected case | B21: Exit-related | C21: =SUMIFS(Cost_Register!$AC$5:$AC$504,Cost_Register!$C$5:$C$504,$A21,Cost_Register!$F$5:$F$504,$B21) -> 0 | D21: =SUMIFS(Cost_Register!$AD$5:$AD$504,Cost_Register!$C$5:$C$504,$A21,Cost_Register!$F$5:$F$504,$B21) -> 0 | E21: =SUMIFS(Cost_Register!$AE$5:$AE$504,Cost_Register!$C$5:$C$504,$A21,Cost_Register!$F$5:$F$504,$B21) -> 0 | F21: =SUMIFS(Cost_Register!$AF$5:$AF$504,Cost_Register!$C$5:$C$504,$A21,Cost_Register!$F$5:$F$504,$B21) -> 0 | G21: =SUMIFS(Cost_Register!$AG$5:$AG$504,Cost_Register!$C$5:$C$504,$A21,Cost_Register!$F$5:$F$504,$B21) -> 100000 | H21: =SUM(C21:G21) -> 100000 | I21: =SUMIFS(Benefits!$Q$5:$Q$304,Benefits!$C$5:$C$304,$A21)+SUMIFS(Benefits!$R$5:$R$304,Benefits!$C$5:$C$304,$A21) -> 7580100 | J21: =SUMIFS(Benefits!$Q$5:$Q$304,Benefits!$C$5:$C$304,$A21)+SUMIFS(Benefits!$R$5:$R$304,Benefits!$C$5:$C$304,$A21)*5 -> 37900500 | K21: =J21-H21 -> 37800500 | L21: =IFERROR(H21/5/COUNTA(AI_Agent_Inventory!$A$5:$A$201),0) -> 1176.4706 | M21: {=IFERROR((H21/5)/SUMPRODUCT((Demand_Scenarios!$B$5:$B$504=$A21)*Demand_Scenarios!$D$5:$D$504*Demand_Scenarios!$E$5:$E$504*Demand_Scenarios!$F$5:$F$504*Demand_Scenarios!$G$5:$G$504*12),0)} -> 0.14443896 | N21: {=IFERROR((H21/5)/SUMPRODUCT((Demand_Scenarios!$B$5:$B$504=$A21)*Demand_Scenarios!$D$5:$D$504*Demand_Scenarios!$E$5:$E$504*Demand_Scenarios!$F$5:$F$504*Demand_Scenarios!$G$5:$G$504*Demand_Scenarios!$I$5:$I$504*12),0)} -> 0.15365846 | O21: =IFERROR(H21/SUMIFS($H$5:$H$44,$A$5:$A$44,"PepsiCo standard")-1,0) -> -0.98209746
A22: Expected case | B22: TOTAL | C22: =SUM(C14:C21) -> 1416514 | D22: =SUM(D14:D21) -> 995631.92 | E22: =SUM(E14:E21) -> 1025635.6 | F22: =SUM(F14:F21) -> 1056552.9 | G22: =SUM(G14:G21) -> 1188412.6 | H22: =SUM(H14:H21) -> 5682747 | I22: =SUMIFS(Benefits!$Q$5:$Q$304,Benefits!$C$5:$C$304,$A22)+SUMIFS(Benefits!$R$5:$R$304,Benefits!$C$5:$C$304,$A22) -> 7580100 | J22: =SUMIFS(Benefits!$Q$5:$Q$304,Benefits!$C$5:$C$304,$A22)+SUMIFS(Benefits!$R$5:$R$304,Benefits!$C$5:$C$304,$A22)*5 -> 37900500 | K22: =J22-H22 -> 32217753 | L22: =IFERROR(H22/5/COUNTA(AI_Agent_Inventory!$A$5:$A$201),0) -> 66855.847 | M22: {=IFERROR((H22/5)/SUMPRODUCT((Demand_Scenarios!$B$5:$B$504=$A22)*Demand_Scenarios!$D$5:$D$504*Demand_Scenarios!$E$5:$E$504*Demand_Scenarios!$F$5:$F$504*Demand_Scenarios!$G$5:$G$504*12),0)} -> 8.2081005 | N22: {=IFERROR((H22/5)/SUMPRODUCT((Demand_Scenarios!$B$5:$B$504=$A22)*Demand_Scenarios!$D$5:$D$504*Demand_Scenarios!$E$5:$E$504*Demand_Scenarios!$F$5:$F$504*Demand_Scenarios!$G$5:$G$504*Demand_Scenarios!$I$5:$I$504*12),0)} -> 8.7320218 | O22: =IFERROR(H22/SUMIFS($H$5:$H$49,$A$5:$A$49,"PepsiCo standard",$B$5:$B$49,"TOTAL")-1,0) -> -0.0005368726
A23: High adoption | B23: One-time | C23: =SUMIFS(Cost_Register!$AC$5:$AC$504,Cost_Register!$C$5:$C$504,$A23,Cost_Register!$F$5:$F$504,$B23) -> 450000 | D23: =SUMIFS(Cost_Register!$AD$5:$AD$504,Cost_Register!$C$5:$C$504,$A23,Cost_Register!$F$5:$F$504,$B23) -> 0 | E23: =SUMIFS(Cost_Register!$AE$5:$AE$504,Cost_Register!$C$5:$C$504,$A23,Cost_Register!$F$5:$F$504,$B23) -> 0 | F23: =SUMIFS(Cost_Register!$AF$5:$AF$504,Cost_Register!$C$5:$C$504,$A23,Cost_Register!$F$5:$F$504,$B23) -> 0 | G23: =SUMIFS(Cost_Register!$AG$5:$AG$504,Cost_Register!$C$5:$C$504,$A23,Cost_Register!$F$5:$F$504,$B23) -> 0 | H23: =SUM(C23:G23) -> 450000 | I23: =SUMIFS(Benefits!$Q$5:$Q$304,Benefits!$C$5:$C$304,$A23)+SUMIFS(Benefits!$R$5:$R$304,Benefits!$C$5:$C$304,$A23) -> 10106800 | J23: =SUMIFS(Benefits!$Q$5:$Q$304,Benefits!$C$5:$C$304,$A23)+SUMIFS(Benefits!$R$5:$R$304,Benefits!$C$5:$C$304,$A23)*5 -> 50534000 | K23: =J23-H23 -> 50084000 | L23: =IFERROR(H23/5/COUNTA(AI_Agent_Inventory!$A$5:$A$201),0) -> 5294.1176 | M23: {=IFERROR((H23/5)/SUMPRODUCT((Demand_Scenarios!$B$5:$B$504=$A23)*Demand_Scenarios!$D$5:$D$504*Demand_Scenarios!$E$5:$E$504*Demand_Scenarios!$F$5:$F$504*Demand_Scenarios!$G$5:$G$504*12),0)} -> 0.48748148 | N23: {=IFERROR((H23/5)/SUMPRODUCT((Demand_Scenarios!$B$5:$B$504=$A23)*Demand_Scenarios!$D$5:$D$504*Demand_Scenarios!$E$5:$E$504*Demand_Scenarios!$F$5:$F$504*Demand_Scenarios!$G$5:$G$504*Demand_Scenarios!$I$5:$I$504*12),0)} -> 0.5131384 | O23: =IFERROR(H23/SUMIFS($H$5:$H$44,$A$5:$A$44,"PepsiCo standard")-1,0) -> -0.91943857
A24: High adoption | B24: Recurring fixed | C24: =SUMIFS(Cost_Register!$AC$5:$AC$504,Cost_Register!$C$5:$C$504,$A24,Cost_Register!$F$5:$F$504,$B24) -> 1157716.8 | D24: =SUMIFS(Cost_Register!$AD$5:$AD$504,Cost_Register!$C$5:$C$504,$A24,Cost_Register!$F$5:$F$504,$B24) -> 1192448.3 | E24: =SUMIFS(Cost_Register!$AE$5:$AE$504,Cost_Register!$C$5:$C$504,$A24,Cost_Register!$F$5:$F$504,$B24) -> 1228221.8 | F24: =SUMIFS(Cost_Register!$AF$5:$AF$504,Cost_Register!$C$5:$C$504,$A24,Cost_Register!$F$5:$F$504,$B24) -> 1265068.4 | G24: =SUMIFS(Cost_Register!$AG$5:$AG$504,Cost_Register!$C$5:$C$504,$A24,Cost_Register!$F$5:$F$504,$B24) -> 1303020.5 | H24: =SUM(C24:G24) -> 6146475.7 | I24: =SUMIFS(Benefits!$Q$5:$Q$304,Benefits!$C$5:$C$304,$A24)+SUMIFS(Benefits!$R$5:$R$304,Benefits!$C$5:$C$304,$A24) -> 10106800 | J24: =SUMIFS(Benefits!$Q$5:$Q$304,Benefits!$C$5:$C$304,$A24)+SUMIFS(Benefits!$R$5:$R$304,Benefits!$C$5:$C$304,$A24)*5 -> 50534000 | K24: =J24-H24 -> 44387524 | L24: =IFERROR(H24/5/COUNTA(AI_Agent_Inventory!$A$5:$A$201),0) -> 72311.479 | M24: {=IFERROR((H24/5)/SUMPRODUCT((Demand_Scenarios!$B$5:$B$504=$A24)*Demand_Scenarios!$D$5:$D$504*Demand_Scenarios!$E$5:$E$504*Demand_Scenarios!$F$5:$F$504*Demand_Scenarios!$G$5:$G$504*12),0)} -> 6.658429 | N24: {=IFERROR((H24/5)/SUMPRODUCT((Demand_Scenarios!$B$5:$B$504=$A24)*Demand_Scenarios!$D$5:$D$504*Demand_Scenarios!$E$5:$E$504*Demand_Scenarios!$F$5:$F$504*Demand_Scenarios!$G$5:$G$504*Demand_Scenarios!$I$5:$I$504*12),0)} -> 7.0088726 | O24: =IFERROR(H24/SUMIFS($H$5:$H$44,$A$5:$A$44,"PepsiCo standard")-1,0) -> 0.10037527
A25: High adoption | B25: Recurring variable | C25: =SUMIFS(Cost_Register!$AC$5:$AC$504,Cost_Register!$C$5:$C$504,$A25,Cost_Register!$F$5:$F$504,$B25) -> 3000 | D25: =SUMIFS(Cost_Register!$AD$5:$AD$504,Cost_Register!$C$5:$C$504,$A25,Cost_Register!$F$5:$F$504,$B25) -> 3300 | E25: =SUMIFS(Cost_Register!$AE$5:$AE$504,Cost_Register!$C$5:$C$504,$A25,Cost_Register!$F$5:$F$504,$B25) -> 3630 | F25: =SUMIFS(Cost_Register!$AF$5:$AF$504,Cost_Register!$C$5:$C$504,$A25,Cost_Register!$F$5:$F$504,$B25) -> 3993 | G25: =SUMIFS(Cost_Register!$AG$5:$AG$504,Cost_Register!$C$5:$C$504,$A25,Cost_Register!$F$5:$F$504,$B25) -> 4392.3 | H25: =SUM(C25:G25) -> 18315.3 | I25: =SUMIFS(Benefits!$Q$5:$Q$304,Benefits!$C$5:$C$304,$A25)+SUMIFS(Benefits!$R$5:$R$304,Benefits!$C$5:$C$304,$A25) -> 10106800 | J25: =SUMIFS(Benefits!$Q$5:$Q$304,Benefits!$C$5:$C$304,$A25)+SUMIFS(Benefits!$R$5:$R$304,Benefits!$C$5:$C$304,$A25)*5 -> 50534000 | K25: =J25-H25 -> 50515685 | L25: =IFERROR(H25/5/COUNTA(AI_Agent_Inventory!$A$5:$A$201),0) -> 215.47412 | M25: {=IFERROR((H25/5)/SUMPRODUCT((Demand_Scenarios!$B$5:$B$504=$A25)*Demand_Scenarios!$D$5:$D$504*Demand_Scenarios!$E$5:$E$504*Demand_Scenarios!$F$5:$F$504*Demand_Scenarios!$G$5:$G$504*12),0)} -> 0.019840821 | N25: {=IFERROR((H25/5)/SUMPRODUCT((Demand_Scenarios!$B$5:$B$504=$A25)*Demand_Scenarios!$D$5:$D$504*Demand_Scenarios!$E$5:$E$504*Demand_Scenarios!$F$5:$F$504*Demand_Scenarios!$G$5:$G$504*Demand_Scenarios!$I$5:$I$504*12),0)} -> 0.020885075 | O25: =IFERROR(H25/SUMIFS($H$5:$H$44,$A$5:$A$44,"PepsiCo standard")-1,0) -> -0.9967211
A26: High adoption | B26: Pass-through | C26: =SUMIFS(Cost_Register!$AC$5:$AC$504,Cost_Register!$C$5:$C$504,$A26,Cost_Register!$F$5:$F$504,$B26) -> 0 | D26: =SUMIFS(Cost_Register!$AD$5:$AD$504,Cost_Register!$C$5:$C$504,$A26,Cost_Register!$F$5:$F$504,$B26) -> 0 | E26: =SUMIFS(Cost_Register!$AE$5:$AE$504,Cost_Register!$C$5:$C$504,$A26,Cost_Register!$F$5:$F$504,$B26) -> 0 | F26: =SUMIFS(Cost_Register!$AF$5:$AF$504,Cost_Register!$C$5:$C$504,$A26,Cost_Register!$F$5:$F$504,$B26) -> 0 | G26: =SUMIFS(Cost_Register!$AG$5:$AG$504,Cost_Register!$C$5:$C$504,$A26,Cost_Register!$F$5:$F$504,$B26) -> 0 | H26: =SUM(C26:G26) -> 0 | I26: =SUMIFS(Benefits!$Q$5:$Q$304,Benefits!$C$5:$C$304,$A26)+SUMIFS(Benefits!$R$5:$R$304,Benefits!$C$5:$C$304,$A26) -> 10106800 | J26: =SUMIFS(Benefits!$Q$5:$Q$304,Benefits!$C$5:$C$304,$A26)+SUMIFS(Benefits!$R$5:$R$304,Benefits!$C$5:$C$304,$A26)*5 -> 50534000 | K26: =J26-H26 -> 50534000 | L26: =IFERROR(H26/5/COUNTA(AI_Agent_Inventory!$A$5:$A$201),0) -> 0 | M26: {=IFERROR((H26/5)/SUMPRODUCT((Demand_Scenarios!$B$5:$B$504=$A26)*Demand_Scenarios!$D$5:$D$504*Demand_Scenarios!$E$5:$E$504*Demand_Scenarios!$F$5:$F$504*Demand_Scenarios!$G$5:$G$504*12),0)} -> 0 | N26: {=IFERROR((H26/5)/SUMPRODUCT((Demand_Scenarios!$B$5:$B$504=$A26)*Demand_Scenarios!$D$5:$D$504*Demand_Scenarios!$E$5:$E$504*Demand_Scenarios!$F$5:$F$504*Demand_Scenarios!$G$5:$G$504*Demand_Scenarios!$I$5:$I$504*12),0)} -> 0 | O26: =IFERROR(H26/SUMIFS($H$5:$H$44,$A$5:$A$44,"PepsiCo standard")-1,0) -> -1
A27: High adoption | B27: Optional | C27: =SUMIFS(Cost_Register!$AC$5:$AC$504,Cost_Register!$C$5:$C$504,$A27,Cost_Register!$F$5:$F$504,$B27) -> 0 | D27: =SUMIFS(Cost_Register!$AD$5:$AD$504,Cost_Register!$C$5:$C$504,$A27,Cost_Register!$F$5:$F$504,$B27) -> 0 | E27: =SUMIFS(Cost_Register!$AE$5:$AE$504,Cost_Register!$C$5:$C$504,$A27,Cost_Register!$F$5:$F$504,$B27) -> 0 | F27: =SUMIFS(Cost_Register!$AF$5:$AF$504,Cost_Register!$C$5:$C$504,$A27,Cost_Register!$F$5:$F$504,$B27) -> 0 | G27: =SUMIFS(Cost_Register!$AG$5:$AG$504,Cost_Register!$C$5:$C$504,$A27,Cost_Register!$F$5:$F$504,$B27) -> 0 | H27: =SUM(C27:G27) -> 0 | I27: =SUMIFS(Benefits!$Q$5:$Q$304,Benefits!$C$5:$C$304,$A27)+SUMIFS(Benefits!$R$5:$R$304,Benefits!$C$5:$C$304,$A27) -> 10106800 | J27: =SUMIFS(Benefits!$Q$5:$Q$304,Benefits!$C$5:$C$304,$A27)+SUMIFS(Benefits!$R$5:$R$304,Benefits!$C$5:$C$304,$A27)*5 -> 50534000 | K27: =J27-H27 -> 50534000 | L27: =IFERROR(H27/5/COUNTA(AI_Agent_Inventory!$A$5:$A$201),0) -> 0 | M27: {=IFERROR((H27/5)/SUMPRODUCT((Demand_Scenarios!$B$5:$B$504=$A27)*Demand_Scenarios!$D$5:$D$504*Demand_Scenarios!$E$5:$E$504*Demand_Scenarios!$F$5:$F$504*Demand_Scenarios!$G$5:$G$504*12),0)} -> 0 | N27: {=IFERROR((H27/5)/SUMPRODUCT((Demand_Scenarios!$B$5:$B$504=$A27)*Demand_Scenarios!$D$5:$D$504*Demand_Scenarios!$E$5:$E$504*Demand_Scenarios!$F$5:$F$504*Demand_Scenarios!$G$5:$G$504*Demand_Scenarios!$I$5:$I$504*12),0)} -> 0 | O27: =IFERROR(H27/SUMIFS($H$5:$H$44,$A$5:$A$44,"PepsiCo standard")-1,0) -> -1
A28: High adoption | B28: PepsiCo-funded | C28: =SUMIFS(Cost_Register!$AC$5:$AC$504,Cost_Register!$C$5:$C$504,$A28,Cost_Register!$F$5:$F$504,$B28) -> 0 | D28: =SUMIFS(Cost_Register!$AD$5:$AD$504,Cost_Register!$C$5:$C$504,$A28,Cost_Register!$F$5:$F$504,$B28) -> 0 | E28: =SUMIFS(Cost_Register!$AE$5:$AE$504,Cost_Register!$C$5:$C$504,$A28,Cost_Register!$F$5:$F$504,$B28) -> 0 | F28: =SUMIFS(Cost_Register!$AF$5:$AF$504,Cost_Register!$C$5:$C$504,$A28,Cost_Register!$F$5:$F$504,$B28) -> 0 | G28: =SUMIFS(Cost_Register!$AG$5:$AG$504,Cost_Register!$C$5:$C$504,$A28,Cost_Register!$F$5:$F$504,$B28) -> 0 | H28: =SUM(C28:G28) -> 0 | I28: =SUMIFS(Benefits!$Q$5:$Q$304,Benefits!$C$5:$C$304,$A28)+SUMIFS(Benefits!$R$5:$R$304,Benefits!$C$5:$C$304,$A28) -> 10106800 | J28: =SUMIFS(Benefits!$Q$5:$Q$304,Benefits!$C$5:$C$304,$A28)+SUMIFS(Benefits!$R$5:$R$304,Benefits!$C$5:$C$304,$A28)*5 -> 50534000 | K28: =J28-H28 -> 50534000 | L28: =IFERROR(H28/5/COUNTA(AI_Agent_Inventory!$A$5:$A$201),0) -> 0 | M28: {=IFERROR((H28/5)/SUMPRODUCT((Demand_Scenarios!$B$5:$B$504=$A28)*Demand_Scenarios!$D$5:$D$504*Demand_Scenarios!$E$5:$E$504*Demand_Scenarios!$F$5:$F$504*Demand_Scenarios!$G$5:$G$504*12),0)} -> 0 | N28: {=IFERROR((H28/5)/SUMPRODUCT((Demand_Scenarios!$B$5:$B$504=$A28)*Demand_Scenarios!$D$5:$D$504*Demand_Scenarios!$E$5:$E$504*Demand_Scenarios!$F$5:$F$504*Demand_Scenarios!$G$5:$G$504*Demand_Scenarios!$I$5:$I$504*12),0)} -> 0 | O28: =IFERROR(H28/SUMIFS($H$5:$H$44,$A$5:$A$44,"PepsiCo standard")-1,0) -> -1
A29: High adoption | B29: Change/lifecycle | C29: =SUMIFS(Cost_Register!$AC$5:$AC$504,Cost_Register!$C$5:$C$504,$A29,Cost_Register!$F$5:$F$504,$B29) -> 0 | D29: =SUMIFS(Cost_Register!$AD$5:$AD$504,Cost_Register!$C$5:$C$504,$A29,Cost_Register!$F$5:$F$504,$B29) -> 0 | E29: =SUMIFS(Cost_Register!$AE$5:$AE$504,Cost_Register!$C$5:$C$504,$A29,Cost_Register!$F$5:$F$504,$B29) -> 0 | F29: =SUMIFS(Cost_Register!$AF$5:$AF$504,Cost_Register!$C$5:$C$504,$A29,Cost_Register!$F$5:$F$504,$B29) -> 0 | G29: =SUMIFS(Cost_Register!$AG$5:$AG$504,Cost_Register!$C$5:$C$504,$A29,Cost_Register!$F$5:$F$504,$B29) -> 0 | H29: =SUM(C29:G29) -> 0 | I29: =SUMIFS(Benefits!$Q$5:$Q$304,Benefits!$C$5:$C$304,$A29)+SUMIFS(Benefits!$R$5:$R$304,Benefits!$C$5:$C$304,$A29) -> 10106800 | J29: =SUMIFS(Benefits!$Q$5:$Q$304,Benefits!$C$5:$C$304,$A29)+SUMIFS(Benefits!$R$5:$R$304,Benefits!$C$5:$C$304,$A29)*5 -> 50534000 | K29: =J29-H29 -> 50534000 | L29: =IFERROR(H29/5/COUNTA(AI_Agent_Inventory!$A$5:$A$201),0) -> 0 | M29: {=IFERROR((H29/5)/SUMPRODUCT((Demand_Scenarios!$B$5:$B$504=$A29)*Demand_Scenarios!$D$5:$D$504*Demand_Scenarios!$E$5:$E$504*Demand_Scenarios!$F$5:$F$504*Demand_Scenarios!$G$5:$G$504*12),0)} -> 0 | N29: {=IFERROR((H29/5)/SUMPRODUCT((Demand_Scenarios!$B$5:$B$504=$A29)*Demand_Scenarios!$D$5:$D$504*Demand_Scenarios!$E$5:$E$504*Demand_Scenarios!$F$5:$F$504*Demand_Scenarios!$G$5:$G$504*Demand_Scenarios!$I$5:$I$504*12),0)} -> 0 | O29: =IFERROR(H29/SUMIFS($H$5:$H$44,$A$5:$A$44,"PepsiCo standard")-1,0) -> -1
A30: High adoption | B30: Exit-related | C30: =SUMIFS(Cost_Register!$AC$5:$AC$504,Cost_Register!$C$5:$C$504,$A30,Cost_Register!$F$5:$F$504,$B30) -> 0 | D30: =SUMIFS(Cost_Register!$AD$5:$AD$504,Cost_Register!$C$5:$C$504,$A30,Cost_Register!$F$5:$F$504,$B30) -> 0 | E30: =SUMIFS(Cost_Register!$AE$5:$AE$504,Cost_Register!$C$5:$C$504,$A30,Cost_Register!$F$5:$F$504,$B30) -> 0 | F30: =SUMIFS(Cost_Register!$AF$5:$AF$504,Cost_Register!$C$5:$C$504,$A30,Cost_Register!$F$5:$F$504,$B30) -> 0 | G30: =SUMIFS(Cost_Register!$AG$5:$AG$504,Cost_Register!$C$5:$C$504,$A30,Cost_Register!$F$5:$F$504,$B30) -> 100000 | H30: =SUM(C30:G30) -> 100000 | I30: =SUMIFS(Benefits!$Q$5:$Q$304,Benefits!$C$5:$C$304,$A30)+SUMIFS(Benefits!$R$5:$R$304,Benefits!$C$5:$C$304,$A30) -> 10106800 | J30: =SUMIFS(Benefits!$Q$5:$Q$304,Benefits!$C$5:$C$304,$A30)+SUMIFS(Benefits!$R$5:$R$304,Benefits!$C$5:$C$304,$A30)*5 -> 50534000 | K30: =J30-H30 -> 50434000 | L30: =IFERROR(H30/5/COUNTA(AI_Agent_Inventory!$A$5:$A$201),0) -> 1176.4706 | M30: {=IFERROR((H30/5)/SUMPRODUCT((Demand_Scenarios!$B$5:$B$504=$A30)*Demand_Scenarios!$D$5:$D$504*Demand_Scenarios!$E$5:$E$504*Demand_Scenarios!$F$5:$F$504*Demand_Scenarios!$G$5:$G$504*12),0)} -> 0.10832922 | N30: {=IFERROR((H30/5)/SUMPRODUCT((Demand_Scenarios!$B$5:$B$504=$A30)*Demand_Scenarios!$D$5:$D$504*Demand_Scenarios!$E$5:$E$504*Demand_Scenarios!$F$5:$F$504*Demand_Scenarios!$G$5:$G$504*Demand_Scenarios!$I$5:$I$504*12),0)} -> 0.11403075 | O30: =IFERROR(H30/SUMIFS($H$5:$H$44,$A$5:$A$44,"PepsiCo standard")-1,0) -> -0.98209746
A31: High adoption | B31: TOTAL | C31: =SUM(C23:C30) -> 1610716.8 | D31: =SUM(D23:D30) -> 1195748.3 | E31: =SUM(E23:E30) -> 1231851.8 | F31: =SUM(F23:F30) -> 1269061.4 | G31: =SUM(G23:G30) -> 1407412.8 | H31: =SUM(H23:H30) -> 6714791 | I31: =SUMIFS(Benefits!$Q$5:$Q$304,Benefits!$C$5:$C$304,$A31)+SUMIFS(Benefits!$R$5:$R$304,Benefits!$C$5:$C$304,$A31) -> 10106800 | J31: =SUMIFS(Benefits!$Q$5:$Q$304,Benefits!$C$5:$C$304,$A31)+SUMIFS(Benefits!$R$5:$R$304,Benefits!$C$5:$C$304,$A31)*5 -> 50534000 | K31: =J31-H31 -> 43819209 | L31: =IFERROR(H31/5/COUNTA(AI_Agent_Inventory!$A$5:$A$201),0) -> 78997.541 | M31: {=IFERROR((H31/5)/SUMPRODUCT((Demand_Scenarios!$B$5:$B$504=$A31)*Demand_Scenarios!$D$5:$D$504*Demand_Scenarios!$E$5:$E$504*Demand_Scenarios!$F$5:$F$504*Demand_Scenarios!$G$5:$G$504*12),0)} -> 7.2740805 | N31: {=IFERROR((H31/5)/SUMPRODUCT((Demand_Scenarios!$B$5:$B$504=$A31)*Demand_Scenarios!$D$5:$D$504*Demand_Scenarios!$E$5:$E$504*Demand_Scenarios!$F$5:$F$504*Demand_Scenarios!$G$5:$G$504*Demand_Scenarios!$I$5:$I$504*12),0)} -> 7.6569269 | O31: =IFERROR(H31/SUMIFS($H$5:$H$49,$A$5:$A$49,"PepsiCo standard",$B$5:$B$49,"TOTAL")-1,0) -> 0.18097568
A32: Peak/stress case | B32: One-time | C32: =SUMIFS(Cost_Register!$AC$5:$AC$504,Cost_Register!$C$5:$C$504,$A32,Cost_Register!$F$5:$F$504,$B32) -> 450000 | D32: =SUMIFS(Cost_Register!$AD$5:$AD$504,Cost_Register!$C$5:$C$504,$A32,Cost_Register!$F$5:$F$504,$B32) -> 0 | E32: =SUMIFS(Cost_Register!$AE$5:$AE$504,Cost_Register!$C$5:$C$504,$A32,Cost_Register!$F$5:$F$504,$B32) -> 0 | F32: =SUMIFS(Cost_Register!$AF$5:$AF$504,Cost_Register!$C$5:$C$504,$A32,Cost_Register!$F$5:$F$504,$B32) -> 0 | G32: =SUMIFS(Cost_Register!$AG$5:$AG$504,Cost_Register!$C$5:$C$504,$A32,Cost_Register!$F$5:$F$504,$B32) -> 0 | H32: =SUM(C32:G32) -> 450000 | I32: =SUMIFS(Benefits!$Q$5:$Q$304,Benefits!$C$5:$C$304,$A32)+SUMIFS(Benefits!$R$5:$R$304,Benefits!$C$5:$C$304,$A32) -> 11370150 | J32: =SUMIFS(Benefits!$Q$5:$Q$304,Benefits!$C$5:$C$304,$A32)+SUMIFS(Benefits!$R$5:$R$304,Benefits!$C$5:$C$304,$A32)*5 -> 56850750 | K32: =J32-H32 -> 56400750 | L32: =IFERROR(H32/5/COUNTA(AI_Agent_Inventory!$A$5:$A$201),0) -> 5294.1176 | M32: {=IFERROR((H32/5)/SUMPRODUCT((Demand_Scenarios!$B$5:$B$504=$A32)*Demand_Scenarios!$D$5:$D$504*Demand_Scenarios!$E$5:$E$504*Demand_Scenarios!$F$5:$F$504*Demand_Scenarios!$G$5:$G$504*12),0)} -> 0.41051072 | N32: {=IFERROR((H32/5)/SUMPRODUCT((Demand_Scenarios!$B$5:$B$504=$A32)*Demand_Scenarios!$D$5:$D$504*Demand_Scenarios!$E$5:$E$504*Demand_Scenarios!$F$5:$F$504*Demand_Scenarios!$G$5:$G$504*Demand_Scenarios!$I$5:$I$504*12),0)} -> 0.44140937 | O32: =IFERROR(H32/SUMIFS($H$5:$H$44,$A$5:$A$44,"PepsiCo standard")-1,0) -> -0.91943857
A33: Peak/stress case | B33: Recurring fixed | C33: =SUMIFS(Cost_Register!$AC$5:$AC$504,Cost_Register!$C$5:$C$504,$A33,Cost_Register!$F$5:$F$504,$B33) -> 1350669.6 | D33: =SUMIFS(Cost_Register!$AD$5:$AD$504,Cost_Register!$C$5:$C$504,$A33,Cost_Register!$F$5:$F$504,$B33) -> 1391189.7 | E33: =SUMIFS(Cost_Register!$AE$5:$AE$504,Cost_Register!$C$5:$C$504,$A33,Cost_Register!$F$5:$F$504,$B33) -> 1432925.4 | F33: =SUMIFS(Cost_Register!$AF$5:$AF$504,Cost_Register!$C$5:$C$504,$A33,Cost_Register!$F$5:$F$504,$B33) -> 1475913.1 | G33: =SUMIFS(Cost_Register!$AG$5:$AG$504,Cost_Register!$C$5:$C$504,$A33,Cost_Register!$F$5:$F$504,$B33) -> 1520190.5 | H33: =SUM(C33:G33) -> 7170888.3 | I33: =SUMIFS(Benefits!$Q$5:$Q$304,Benefits!$C$5:$C$304,$A33)+SUMIFS(Benefits!$R$5:$R$304,Benefits!$C$5:$C$304,$A33) -> 11370150 | J33: =SUMIFS(Benefits!$Q$5:$Q$304,Benefits!$C$5:$C$304,$A33)+SUMIFS(Benefits!$R$5:$R$304,Benefits!$C$5:$C$304,$A33)*5 -> 56850750 | K33: =J33-H33 -> 49679862 | L33: =IFERROR(H33/5/COUNTA(AI_Agent_Inventory!$A$5:$A$201),0) -> 84363.392 | M33: {=IFERROR((H33/5)/SUMPRODUCT((Demand_Scenarios!$B$5:$B$504=$A33)*Demand_Scenarios!$D$5:$D$504*Demand_Scenarios!$E$5:$E$504*Demand_Scenarios!$F$5:$F$504*Demand_Scenarios!$G$5:$G$504*12),0)} -> 6.5416145 | N33: {=IFERROR((H33/5)/SUMPRODUCT((Demand_Scenarios!$B$5:$B$504=$A33)*Demand_Scenarios!$D$5:$D$504*Demand_Scenarios!$E$5:$E$504*Demand_Scenarios!$F$5:$F$504*Demand_Scenarios!$G$5:$G$504*Demand_Scenarios!$I$5:$I$504*12),0)} -> 7.033994 | O33: =IFERROR(H33/SUMIFS($H$5:$H$44,$A$5:$A$44,"PepsiCo standard")-1,0) -> 0.28377115
A34: Peak/stress case | B34: Recurring variable | C34: =SUMIFS(Cost_Register!$AC$5:$AC$504,Cost_Register!$C$5:$C$504,$A34,Cost_Register!$F$5:$F$504,$B34) -> 4500 | D34: =SUMIFS(Cost_Register!$AD$5:$AD$504,Cost_Register!$C$5:$C$504,$A34,Cost_Register!$F$5:$F$504,$B34) -> 4950 | E34: =SUMIFS(Cost_Register!$AE$5:$AE$504,Cost_Register!$C$5:$C$504,$A34,Cost_Register!$F$5:$F$504,$B34) -> 5445 | F34: =SUMIFS(Cost_Register!$AF$5:$AF$504,Cost_Register!$C$5:$C$504,$A34,Cost_Register!$F$5:$F$504,$B34) -> 5989.5 | G34: =SUMIFS(Cost_Register!$AG$5:$AG$504,Cost_Register!$C$5:$C$504,$A34,Cost_Register!$F$5:$F$504,$B34) -> 6588.45 | H34: =SUM(C34:G34) -> 27472.95 | I34: =SUMIFS(Benefits!$Q$5:$Q$304,Benefits!$C$5:$C$304,$A34)+SUMIFS(Benefits!$R$5:$R$304,Benefits!$C$5:$C$304,$A34) -> 11370150 | J34: =SUMIFS(Benefits!$Q$5:$Q$304,Benefits!$C$5:$C$304,$A34)+SUMIFS(Benefits!$R$5:$R$304,Benefits!$C$5:$C$304,$A34)*5 -> 56850750 | K34: =J34-H34 -> 56823277 | L34: =IFERROR(H34/5/COUNTA(AI_Agent_Inventory!$A$5:$A$201),0) -> 323.21118 | M34: {=IFERROR((H34/5)/SUMPRODUCT((Demand_Scenarios!$B$5:$B$504=$A34)*Demand_Scenarios!$D$5:$D$504*Demand_Scenarios!$E$5:$E$504*Demand_Scenarios!$F$5:$F$504*Demand_Scenarios!$G$5:$G$504*12),0)} -> 0.02506209 | N34: {=IFERROR((H34/5)/SUMPRODUCT((Demand_Scenarios!$B$5:$B$504=$A34)*Demand_Scenarios!$D$5:$D$504*Demand_Scenarios!$E$5:$E$504*Demand_Scenarios!$F$5:$F$504*Demand_Scenarios!$G$5:$G$504*Demand_Scenarios!$I$5:$I$504*12),0)} -> 0.026948484 | O34: =IFERROR(H34/SUMIFS($H$5:$H$44,$A$5:$A$44,"PepsiCo standard")-1,0) -> -0.99508164
A35: Peak/stress case | B35: Pass-through | C35: =SUMIFS(Cost_Register!$AC$5:$AC$504,Cost_Register!$C$5:$C$504,$A35,Cost_Register!$F$5:$F$504,$B35) -> 0 | D35: =SUMIFS(Cost_Register!$AD$5:$AD$504,Cost_Register!$C$5:$C$504,$A35,Cost_Register!$F$5:$F$504,$B35) -> 0 | E35: =SUMIFS(Cost_Register!$AE$5:$AE$504,Cost_Register!$C$5:$C$504,$A35,Cost_Register!$F$5:$F$504,$B35) -> 0 | F35: =SUMIFS(Cost_Register!$AF$5:$AF$504,Cost_Register!$C$5:$C$504,$A35,Cost_Register!$F$5:$F$504,$B35) -> 0 | G35: =SUMIFS(Cost_Register!$AG$5:$AG$504,Cost_Register!$C$5:$C$504,$A35,Cost_Register!$F$5:$F$504,$B35) -> 0 | H35: =SUM(C35:G35) -> 0 | I35: =SUMIFS(Benefits!$Q$5:$Q$304,Benefits!$C$5:$C$304,$A35)+SUMIFS(Benefits!$R$5:$R$304,Benefits!$C$5:$C$304,$A35) -> 11370150 | J35: =SUMIFS(Benefits!$Q$5:$Q$304,Benefits!$C$5:$C$304,$A35)+SUMIFS(Benefits!$R$5:$R$304,Benefits!$C$5:$C$304,$A35)*5 -> 56850750 | K35: =J35-H35 -> 56850750 | L35: =IFERROR(H35/5/COUNTA(AI_Agent_Inventory!$A$5:$A$201),0) -> 0 | M35: {=IFERROR((H35/5)/SUMPRODUCT((Demand_Scenarios!$B$5:$B$504=$A35)*Demand_Scenarios!$D$5:$D$504*Demand_Scenarios!$E$5:$E$504*Demand_Scenarios!$F$5:$F$504*Demand_Scenarios!$G$5:$G$504*12),0)} -> 0 | N35: {=IFERROR((H35/5)/SUMPRODUCT((Demand_Scenarios!$B$5:$B$504=$A35)*Demand_Scenarios!$D$5:$D$504*Demand_Scenarios!$E$5:$E$504*Demand_Scenarios!$F$5:$F$504*Demand_Scenarios!$G$5:$G$504*Demand_Scenarios!$I$5:$I$504*12),0)} -> 0 | O35: =IFERROR(H35/SUMIFS($H$5:$H$44,$A$5:$A$44,"PepsiCo standard")-1,0) -> -1
A36: Peak/stress case | B36: Optional | C36: =SUMIFS(Cost_Register!$AC$5:$AC$504,Cost_Register!$C$5:$C$504,$A36,Cost_Register!$F$5:$F$504,$B36) -> 0 | D36: =SUMIFS(Cost_Register!$AD$5:$AD$504,Cost_Register!$C$5:$C$504,$A36,Cost_Register!$F$5:$F$504,$B36) -> 0 | E36: =SUMIFS(Cost_Register!$AE$5:$AE$504,Cost_Register!$C$5:$C$504,$A36,Cost_Register!$F$5:$F$504,$B36) -> 0 | F36: =SUMIFS(Cost_Register!$AF$5:$AF$504,Cost_Register!$C$5:$C$504,$A36,Cost_Register!$F$5:$F$504,$B36) -> 0 | G36: =SUMIFS(Cost_Register!$AG$5:$AG$504,Cost_Register!$C$5:$C$504,$A36,Cost_Register!$F$5:$F$504,$B36) -> 0 | H36: =SUM(C36:G36) -> 0 | I36: =SUMIFS(Benefits!$Q$5:$Q$304,Benefits!$C$5:$C$304,$A36)+SUMIFS(Benefits!$R$5:$R$304,Benefits!$C$5:$C$304,$A36) -> 11370150 | J36: =SUMIFS(Benefits!$Q$5:$Q$304,Benefits!$C$5:$C$304,$A36)+SUMIFS(Benefits!$R$5:$R$304,Benefits!$C$5:$C$304,$A36)*5 -> 56850750 | K36: =J36-H36 -> 56850750 | L36: =IFERROR(H36/5/COUNTA(AI_Agent_Inventory!$A$5:$A$201),0) -> 0 | M36: {=IFERROR((H36/5)/SUMPRODUCT((Demand_Scenarios!$B$5:$B$504=$A36)*Demand_Scenarios!$D$5:$D$504*Demand_Scenarios!$E$5:$E$504*Demand_Scenarios!$F$5:$F$504*Demand_Scenarios!$G$5:$G$504*12),0)} -> 0 | N36: {=IFERROR((H36/5)/SUMPRODUCT((Demand_Scenarios!$B$5:$B$504=$A36)*Demand_Scenarios!$D$5:$D$504*Demand_Scenarios!$E$5:$E$504*Demand_Scenarios!$F$5:$F$504*Demand_Scenarios!$G$5:$G$504*Demand_Scenarios!$I$5:$I$504*12),0)} -> 0 | O36: =IFERROR(H36/SUMIFS($H$5:$H$44,$A$5:$A$44,"PepsiCo standard")-1,0) -> -1
A37: Peak/stress case | B37: PepsiCo-funded | C37: =SUMIFS(Cost_Register!$AC$5:$AC$504,Cost_Register!$C$5:$C$504,$A37,Cost_Register!$F$5:$F$504,$B37) -> 0 | D37: =SUMIFS(Cost_Register!$AD$5:$AD$504,Cost_Register!$C$5:$C$504,$A37,Cost_Register!$F$5:$F$504,$B37) -> 0 | E37: =SUMIFS(Cost_Register!$AE$5:$AE$504,Cost_Register!$C$5:$C$504,$A37,Cost_Register!$F$5:$F$504,$B37) -> 0 | F37: =SUMIFS(Cost_Register!$AF$5:$AF$504,Cost_Register!$C$5:$C$504,$A37,Cost_Register!$F$5:$F$504,$B37) -> 0 | G37: =SUMIFS(Cost_Register!$AG$5:$AG$504,Cost_Register!$C$5:$C$504,$A37,Cost_Register!$F$5:$F$504,$B37) -> 0 | H37: =SUM(C37:G37) -> 0 | I37: =SUMIFS(Benefits!$Q$5:$Q$304,Benefits!$C$5:$C$304,$A37)+SUMIFS(Benefits!$R$5:$R$304,Benefits!$C$5:$C$304,$A37) -> 11370150 | J37: =SUMIFS(Benefits!$Q$5:$Q$304,Benefits!$C$5:$C$304,$A37)+SUMIFS(Benefits!$R$5:$R$304,Benefits!$C$5:$C$304,$A37)*5 -> 56850750 | K37: =J37-H37 -> 56850750 | L37: =IFERROR(H37/5/COUNTA(AI_Agent_Inventory!$A$5:$A$201),0) -> 0 | M37: {=IFERROR((H37/5)/SUMPRODUCT((Demand_Scenarios!$B$5:$B$504=$A37)*Demand_Scenarios!$D$5:$D$504*Demand_Scenarios!$E$5:$E$504*Demand_Scenarios!$F$5:$F$504*Demand_Scenarios!$G$5:$G$504*12),0)} -> 0 | N37: {=IFERROR((H37/5)/SUMPRODUCT((Demand_Scenarios!$B$5:$B$504=$A37)*Demand_Scenarios!$D$5:$D$504*Demand_Scenarios!$E$5:$E$504*Demand_Scenarios!$F$5:$F$504*Demand_Scenarios!$G$5:$G$504*Demand_Scenarios!$I$5:$I$504*12),0)} -> 0 | O37: =IFERROR(H37/SUMIFS($H$5:$H$44,$A$5:$A$44,"PepsiCo standard")-1,0) -> -1
A38: Peak/stress case | B38: Change/lifecycle | C38: =SUMIFS(Cost_Register!$AC$5:$AC$504,Cost_Register!$C$5:$C$504,$A38,Cost_Register!$F$5:$F$504,$B38) -> 0 | D38: =SUMIFS(Cost_Register!$AD$5:$AD$504,Cost_Register!$C$5:$C$504,$A38,Cost_Register!$F$5:$F$504,$B38) -> 0 | E38: =SUMIFS(Cost_Register!$AE$5:$AE$504,Cost_Register!$C$5:$C$504,$A38,Cost_Register!$F$5:$F$504,$B38) -> 0 | F38: =SUMIFS(Cost_Register!$AF$5:$AF$504,Cost_Register!$C$5:$C$504,$A38,Cost_Register!$F$5:$F$504,$B38) -> 0 | G38: =SUMIFS(Cost_Register!$AG$5:$AG$504,Cost_Register!$C$5:$C$504,$A38,Cost_Register!$F$5:$F$504,$B38) -> 0 | H38: =SUM(C38:G38) -> 0 | I38: =SUMIFS(Benefits!$Q$5:$Q$304,Benefits!$C$5:$C$304,$A38)+SUMIFS(Benefits!$R$5:$R$304,Benefits!$C$5:$C$304,$A38) -> 11370150 | J38: =SUMIFS(Benefits!$Q$5:$Q$304,Benefits!$C$5:$C$304,$A38)+SUMIFS(Benefits!$R$5:$R$304,Benefits!$C$5:$C$304,$A38)*5 -> 56850750 | K38: =J38-H38 -> 56850750 | L38: =IFERROR(H38/5/COUNTA(AI_Agent_Inventory!$A$5:$A$201),0) -> 0 | M38: {=IFERROR((H38/5)/SUMPRODUCT((Demand_Scenarios!$B$5:$B$504=$A38)*Demand_Scenarios!$D$5:$D$504*Demand_Scenarios!$E$5:$E$504*Demand_Scenarios!$F$5:$F$504*Demand_Scenarios!$G$5:$G$504*12),0)} -> 0 | N38: {=IFERROR((H38/5)/SUMPRODUCT((Demand_Scenarios!$B$5:$B$504=$A38)*Demand_Scenarios!$D$5:$D$504*Demand_Scenarios!$E$5:$E$504*Demand_Scenarios!$F$5:$F$504*Demand_Scenarios!$G$5:$G$504*Demand_Scenarios!$I$5:$I$504*12),0)} -> 0 | O38: =IFERROR(H38/SUMIFS($H$5:$H$44,$A$5:$A$44,"PepsiCo standard")-1,0) -> -1
A39: Peak/stress case | B39: Exit-related | C39: =SUMIFS(Cost_Register!$AC$5:$AC$504,Cost_Register!$C$5:$C$504,$A39,Cost_Register!$F$5:$F$504,$B39) -> 0 | D39: =SUMIFS(Cost_Register!$AD$5:$AD$504,Cost_Register!$C$5:$C$504,$A39,Cost_Register!$F$5:$F$504,$B39) -> 0 | E39: =SUMIFS(Cost_Register!$AE$5:$AE$504,Cost_Register!$C$5:$C$504,$A39,Cost_Register!$F$5:$F$504,$B39) -> 0 | F39: =SUMIFS(Cost_Register!$AF$5:$AF$504,Cost_Register!$C$5:$C$504,$A39,Cost_Register!$F$5:$F$504,$B39) -> 0 | G39: =SUMIFS(Cost_Register!$AG$5:$AG$504,Cost_Register!$C$5:$C$504,$A39,Cost_Register!$F$5:$F$504,$B39) -> 100000 | H39: =SUM(C39:G39) -> 100000 | I39: =SUMIFS(Benefits!$Q$5:$Q$304,Benefits!$C$5:$C$304,$A39)+SUMIFS(Benefits!$R$5:$R$304,Benefits!$C$5:$C$304,$A39) -> 11370150 | J39: =SUMIFS(Benefits!$Q$5:$Q$304,Benefits!$C$5:$C$304,$A39)+SUMIFS(Benefits!$R$5:$R$304,Benefits!$C$5:$C$304,$A39)*5 -> 56850750 | K39: =J39-H39 -> 56750750 | L39: =IFERROR(H39/5/COUNTA(AI_Agent_Inventory!$A$5:$A$201),0) -> 1176.4706 | M39: {=IFERROR((H39/5)/SUMPRODUCT((Demand_Scenarios!$B$5:$B$504=$A39)*Demand_Scenarios!$D$5:$D$504*Demand_Scenarios!$E$5:$E$504*Demand_Scenarios!$F$5:$F$504*Demand_Scenarios!$G$5:$G$504*12),0)} -> 0.091224604 | N39: {=IFERROR((H39/5)/SUMPRODUCT((Demand_Scenarios!$B$5:$B$504=$A39)*Demand_Scenarios!$D$5:$D$504*Demand_Scenarios!$E$5:$E$504*Demand_Scenarios!$F$5:$F$504*Demand_Scenarios!$G$5:$G$504*Demand_Scenarios!$I$5:$I$504*12),0)} -> 0.098090972 | O39: =IFERROR(H39/SUMIFS($H$5:$H$44,$A$5:$A$44,"PepsiCo standard")-1,0) -> -0.98209746
A40: Peak/stress case | B40: TOTAL | C40: =SUM(C32:C39) -> 1805169.6 | D40: =SUM(D32:D39) -> 1396139.7 | E40: =SUM(E32:E39) -> 1438370.4 | F40: =SUM(F32:F39) -> 1481902.6 | G40: =SUM(G32:G39) -> 1626779 | H40: =SUM(H32:H39) -> 7748361.3 | I40: =SUMIFS(Benefits!$Q$5:$Q$304,Benefits!$C$5:$C$304,$A40)+SUMIFS(Benefits!$R$5:$R$304,Benefits!$C$5:$C$304,$A40) -> 11370150 | J40: =SUMIFS(Benefits!$Q$5:$Q$304,Benefits!$C$5:$C$304,$A40)+SUMIFS(Benefits!$R$5:$R$304,Benefits!$C$5:$C$304,$A40)*5 -> 56850750 | K40: =J40-H40 -> 49102389 | L40: =IFERROR(H40/5/COUNTA(AI_Agent_Inventory!$A$5:$A$201),0) -> 91157.192 | M40: {=IFERROR((H40/5)/SUMPRODUCT((Demand_Scenarios!$B$5:$B$504=$A40)*Demand_Scenarios!$D$5:$D$504*Demand_Scenarios!$E$5:$E$504*Demand_Scenarios!$F$5:$F$504*Demand_Scenarios!$G$5:$G$504*12),0)} -> 7.0684119 | N40: {=IFERROR((H40/5)/SUMPRODUCT((Demand_Scenarios!$B$5:$B$504=$A40)*Demand_Scenarios!$D$5:$D$504*Demand_Scenarios!$E$5:$E$504*Demand_Scenarios!$F$5:$F$504*Demand_Scenarios!$G$5:$G$504*Demand_Scenarios!$I$5:$I$504*12),0)} -> 7.6004429 | O40: =IFERROR(H40/SUMIFS($H$5:$H$49,$A$5:$A$49,"PepsiCo standard",$B$5:$B$49,"TOTAL")-1,0) -> 0.36275667
A41: PepsiCo standard | B41: One-time | C41: =SUMIFS(Cost_Register!$AC$5:$AC$504,Cost_Register!$C$5:$C$504,$A41,Cost_Register!$F$5:$F$504,$B41) -> 450000 | D41: =SUMIFS(Cost_Register!$AD$5:$AD$504,Cost_Register!$C$5:$C$504,$A41,Cost_Register!$F$5:$F$504,$B41) -> 0 | E41: =SUMIFS(Cost_Register!$AE$5:$AE$504,Cost_Register!$C$5:$C$504,$A41,Cost_Register!$F$5:$F$504,$B41) -> 0 | F41: =SUMIFS(Cost_Register!$AF$5:$AF$504,Cost_Register!$C$5:$C$504,$A41,Cost_Register!$F$5:$F$504,$B41) -> 0 | G41: =SUMIFS(Cost_Register!$AG$5:$AG$504,Cost_Register!$C$5:$C$504,$A41,Cost_Register!$F$5:$F$504,$B41) -> 0 | H41: =SUM(C41:G41) -> 450000 | I41: =SUMIFS(Benefits!$Q$5:$Q$304,Benefits!$C$5:$C$304,$A41)+SUMIFS(Benefits!$R$5:$R$304,Benefits!$C$5:$C$304,$A41) -> 8211775 | J41: =SUMIFS(Benefits!$Q$5:$Q$304,Benefits!$C$5:$C$304,$A41)+SUMIFS(Benefits!$R$5:$R$304,Benefits!$C$5:$C$304,$A41)*5 -> 41058875 | K41: =J41-H41 -> 40608875 | L41: =IFERROR(H41/5/COUNTA(AI_Agent_Inventory!$A$5:$A$201),0) -> 5294.1176 | M41: {=IFERROR((H41/5)/SUMPRODUCT((Demand_Scenarios!$B$5:$B$504=$A41)*Demand_Scenarios!$D$5:$D$504*Demand_Scenarios!$E$5:$E$504*Demand_Scenarios!$F$5:$F$504*Demand_Scenarios!$G$5:$G$504*12),0)} -> 0.55712169 | N41: {=IFERROR((H41/5)/SUMPRODUCT((Demand_Scenarios!$B$5:$B$504=$A41)*Demand_Scenarios!$D$5:$D$504*Demand_Scenarios!$E$5:$E$504*Demand_Scenarios!$F$5:$F$504*Demand_Scenarios!$G$5:$G$504*Demand_Scenarios!$I$5:$I$504*12),0)} -> 0.58644388 | O41: =IFERROR(H41/SUMIFS($H$5:$H$44,$A$5:$A$44,"PepsiCo standard")-1,0) -> -0.91943857
